{
  "updated_at": "2026-06-18T11:00:01.393022+08:00",
  "source": "D:\\FOREX\\zf_validation_reports\\zf_validation_summary_20260618_100406.csv",
  "rules": {
    "min_expectancy_r": 0.03,
    "min_win_rate_resolved": 43.0,
    "min_signals": 15
  },
  "active_symbol_limit": 10,
  "primary_symbols": [
    "GBPCADm",
    "CADCHFm",
    "GBPNZDm",
    "USDCHFm",
    "BTCJPYm",
    "BTCCNHm",
    "AUDJPYm",
    "EURCADm",
    "BTCUSDm",
    "USDCADm"
  ],
  "primary_routes": [
    {
      "symbol": "GBPCADm",
      "timeframe": "M15",
      "exit_mode": "dynamic_sl_tp",
      "win_rate_resolved": 81.25,
      "expectancy_r": 0.633,
      "selection_score": 80.68
    },
    {
      "symbol": "CADCHFm",
      "timeframe": "M15",
      "exit_mode": "dynamic_sl_tp",
      "win_rate_resolved": 81.25,
      "expectancy_r": 0.3989,
      "selection_score": 80.64
    },
    {
      "symbol": "GBPNZDm",
      "timeframe": "M15",
      "exit_mode": "dynamic_sl_tp",
      "win_rate_resolved": 73.33,
      "expectancy_r": 0.3584,
      "selection_score": 76.52
    },
    {
      "symbol": "USDCHFm",
      "timeframe": "M15",
      "exit_mode": "dynamic_sl_tp",
      "win_rate_resolved": 65.22,
      "expectancy_r": 0.2677,
      "selection_score": 70.58
    },
    {
      "symbol": "BTCJPYm",
      "timeframe": "M15",
      "exit_mode": "dynamic_sl_tp",
      "win_rate_resolved": 68.75,
      "expectancy_r": 0.1932,
      "selection_score": 67.63
    },
    {
      "symbol": "BTCCNHm",
      "timeframe": "M15",
      "exit_mode": "dynamic_sl_tp",
      "win_rate_resolved": 71.43,
      "expectancy_r": 0.1491,
      "selection_score": 66.95
    },
    {
      "symbol": "AUDJPYm",
      "timeframe": "M15",
      "exit_mode": "dynamic_sl_tp",
      "win_rate_resolved": 63.16,
      "expectancy_r": 0.1447,
      "selection_score": 62.96
    },
    {
      "symbol": "EURCADm",
      "timeframe": "M15",
      "exit_mode": "dynamic_sl_tp",
      "win_rate_resolved": 56.25,
      "expectancy_r": 0.1091,
      "selection_score": 57.42
    },
    {
      "symbol": "BTCUSDm",
      "timeframe": "M15",
      "exit_mode": "dynamic_sl_tp",
      "win_rate_resolved": 69.05,
      "expectancy_r": 0.089,
      "selection_score": 64.81
    },
    {
      "symbol": "USDCADm",
      "timeframe": "M15",
      "exit_mode": "dynamic_sl_tp",
      "win_rate_resolved": 63.64,
      "expectancy_r": 0.0832,
      "selection_score": 60.53
    }
  ],
  "tradeable_symbols": [
    "AUDJPYm",
    "BTCCNHm",
    "BTCJPYm",
    "BTCUSDm",
    "BTCZARm",
    "CADCHFm",
    "EURCADm",
    "GBPCADm",
    "GBPNZDm",
    "GBPUSDm",
    "USDCADm",
    "USDCHFm"
  ],
  "watch_only_symbols": [
    "AUDCADm",
    "AUDCHFm",
    "AUDNZDm",
    "AUDUSDm",
    "BTCXAGm",
    "BTCXAUm",
    "CHFJPYm",
    "EURAUDm",
    "EURGBPm",
    "GBPAUDm",
    "GBPCHFm",
    "GBPJPYm",
    "NZDCADm",
    "NZDCHFm",
    "SOLUSDm",
    "XAUAUDm",
    "XAUEURm",
    "XAUGBPm"
  ],
  "avoid_symbols": [
    "ADAUSDm",
    "BNBUSDm",
    "BTCAUDm",
    "BTCKRWm",
    "BTCTHBm",
    "CADJPYm",
    "DOGEUSDm",
    "DOTUSDm",
    "ETHUSDm",
    "EURCHFm",
    "EURJPYm",
    "EURNZDm",
    "EURUSDm",
    "LINKUSDm",
    "LTCUSDm",
    "NZDJPYm",
    "NZDUSDm",
    "UKOILm",
    "USDJPYm",
    "USOILm",
    "XAGAUDm",
    "XAGEURm",
    "XAGGBPm",
    "XAGJPYm",
    "XAGUSDm",
    "XAUUSDm",
    "XRPUSDm"
  ],
  "symbols": {
    "EURAUDm": {
      "status": "WATCH_ONLY",
      "expectancy_r": 0.6291,
      "win_rate_resolved": 100.0,
      "signals": 10,
      "asset_class": "forex",
      "timeframe": "M15",
      "exit_mode": "dynamic_sl_tp",
      "optimizer_zf_floor": 0.5,
      "optimizer_fibo_filter": true,
      "optimizer_trailing": true,
      "avg_hours_to_result": 4.6,
      "selection_score": 89.85,
      "live_expectancy_r": -1.0,
      "live_win_rate_resolved": 0.0,
      "live_signals": 1,
      "blended_expectancy_r": 0.6291
    },
    "AUDCADm": {
      "status": "WATCH_ONLY",
      "expectancy_r": 0.6592,
      "win_rate_resolved": 100.0,
      "signals": 5,
      "asset_class": "forex",
      "timeframe": "M15",
      "exit_mode": "dynamic_sl_tp",
      "optimizer_zf_floor": 0.55,
      "optimizer_fibo_filter": true,
      "optimizer_trailing": true,
      "avg_hours_to_result": 10.1,
      "selection_score": 89.2,
      "live_expectancy_r": -1.0,
      "live_win_rate_resolved": 0.0,
      "live_signals": 1,
      "blended_expectancy_r": 0.6592
    },
    "AUDUSDm": {
      "status": "WATCH_ONLY",
      "expectancy_r": 0.3664,
      "win_rate_resolved": 92.86,
      "signals": 14,
      "asset_class": "forex",
      "timeframe": "M15",
      "exit_mode": "dynamic_sl_tp",
      "optimizer_zf_floor": 0.55,
      "optimizer_fibo_filter": true,
      "optimizer_trailing": true,
      "avg_hours_to_result": 3.25,
      "selection_score": 86.25,
      "live_expectancy_r": 1.25,
      "live_win_rate_resolved": 100.0,
      "live_signals": 1,
      "blended_expectancy_r": 0.3664
    },
    "AUDCHFm": {
      "status": "WATCH_ONLY",
      "expectancy_r": 0.5253,
      "win_rate_resolved": 90.91,
      "signals": 11,
      "asset_class": "forex",
      "timeframe": "M15",
      "exit_mode": "dynamic_sl_tp",
      "optimizer_zf_floor": 0.55,
      "optimizer_fibo_filter": true,
      "optimizer_trailing": true,
      "avg_hours_to_result": 5.77,
      "selection_score": 85.24,
      "live_expectancy_r": -1.0,
      "live_win_rate_resolved": 0.0,
      "live_signals": 1,
      "blended_expectancy_r": 0.5253
    },
    "NZDCADm": {
      "status": "WATCH_ONLY",
      "expectancy_r": 0.295,
      "win_rate_resolved": 90.0,
      "signals": 10,
      "asset_class": "forex",
      "timeframe": "M15",
      "exit_mode": "dynamic_sl_tp",
      "optimizer_zf_floor": 0.55,
      "optimizer_fibo_filter": true,
      "optimizer_trailing": true,
      "avg_hours_to_result": 7.72,
      "selection_score": 82.66,
      "live_expectancy_r": 1.25,
      "live_win_rate_resolved": 100.0,
      "live_signals": 1,
      "blended_expectancy_r": 0.295
    },
    "GBPCADm": {
      "status": "TRADEABLE",
      "expectancy_r": 0.633,
      "win_rate_resolved": 81.25,
      "signals": 17,
      "asset_class": "forex",
      "timeframe": "M15",
      "exit_mode": "dynamic_sl_tp",
      "optimizer_zf_floor": 0.5,
      "optimizer_fibo_filter": true,
      "optimizer_trailing": true,
      "avg_hours_to_result": 4.54,
      "selection_score": 80.68,
      "live_expectancy_r": NaN,
      "live_win_rate_resolved": NaN,
      "live_signals": 0,
      "blended_expectancy_r": 0.633
    },
    "CADCHFm": {
      "status": "TRADEABLE",
      "expectancy_r": 0.3989,
      "win_rate_resolved": 81.25,
      "signals": 17,
      "asset_class": "forex",
      "timeframe": "M15",
      "exit_mode": "dynamic_sl_tp",
      "optimizer_zf_floor": 0.5,
      "optimizer_fibo_filter": true,
      "optimizer_trailing": true,
      "avg_hours_to_result": 7.28,
      "selection_score": 80.64,
      "live_expectancy_r": NaN,
      "live_win_rate_resolved": NaN,
      "live_signals": 0,
      "blended_expectancy_r": 0.3989
    },
    "GBPAUDm": {
      "status": "WATCH_ONLY",
      "expectancy_r": 0.3251,
      "win_rate_resolved": 75.0,
      "signals": 8,
      "asset_class": "forex",
      "timeframe": "M15",
      "exit_mode": "dynamic_sl_tp",
      "optimizer_zf_floor": 0.55,
      "optimizer_fibo_filter": true,
      "optimizer_trailing": true,
      "avg_hours_to_result": 9.22,
      "selection_score": 76.84,
      "live_expectancy_r": NaN,
      "live_win_rate_resolved": NaN,
      "live_signals": 0,
      "blended_expectancy_r": 0.3251
    },
    "GBPNZDm": {
      "status": "TRADEABLE",
      "expectancy_r": 0.3584,
      "win_rate_resolved": 73.33,
      "signals": 15,
      "asset_class": "forex",
      "timeframe": "M15",
      "exit_mode": "dynamic_sl_tp",
      "optimizer_zf_floor": 0.55,
      "optimizer_fibo_filter": true,
      "optimizer_trailing": true,
      "avg_hours_to_result": 3.43,
      "selection_score": 76.52,
      "live_expectancy_r": NaN,
      "live_win_rate_resolved": NaN,
      "live_signals": 0,
      "blended_expectancy_r": 0.3584
    },
    "BTCXAGm": {
      "status": "WATCH_ONLY",
      "expectancy_r": 0.3196,
      "win_rate_resolved": 75.0,
      "signals": 9,
      "asset_class": "crypto",
      "timeframe": "M15",
      "exit_mode": "dynamic_sl_tp",
      "optimizer_zf_floor": 0.55,
      "optimizer_fibo_filter": true,
      "optimizer_trailing": true,
      "avg_hours_to_result": 5.42,
      "selection_score": 76.51,
      "live_expectancy_r": NaN,
      "live_win_rate_resolved": NaN,
      "live_signals": 0,
      "blended_expectancy_r": 0.3196
    },
    "BTCXAUm": {
      "status": "WATCH_ONLY",
      "expectancy_r": 0.3135,
      "win_rate_resolved": 70.0,
      "signals": 10,
      "asset_class": "crypto",
      "timeframe": "M15",
      "exit_mode": "dynamic_sl_tp",
      "optimizer_zf_floor": 0.55,
      "optimizer_fibo_filter": true,
      "optimizer_trailing": true,
      "avg_hours_to_result": 5.03,
      "selection_score": 73.65,
      "live_expectancy_r": NaN,
      "live_win_rate_resolved": NaN,
      "live_signals": 0,
      "blended_expectancy_r": 0.3135
    },
    "XAUAUDm": {
      "status": "WATCH_ONLY",
      "expectancy_r": 0.26,
      "win_rate_resolved": 75.0,
      "signals": 4,
      "asset_class": "metal",
      "timeframe": "M15",
      "exit_mode": "dynamic_sl_tp",
      "optimizer_zf_floor": 0.55,
      "optimizer_fibo_filter": true,
      "optimizer_trailing": true,
      "avg_hours_to_result": 9.25,
      "selection_score": 73.25,
      "live_expectancy_r": NaN,
      "live_win_rate_resolved": NaN,
      "live_signals": 0,
      "blended_expectancy_r": 0.26
    },
    "USDCHFm": {
      "status": "TRADEABLE",
      "expectancy_r": 0.2677,
      "win_rate_resolved": 65.22,
      "signals": 29,
      "asset_class": "forex",
      "timeframe": "M15",
      "exit_mode": "dynamic_sl_tp",
      "optimizer_zf_floor": 0.5,
      "optimizer_fibo_filter": true,
      "optimizer_trailing": true,
      "avg_hours_to_result": 7.1,
      "selection_score": 70.58,
      "live_expectancy_r": NaN,
      "live_win_rate_resolved": NaN,
      "live_signals": 0,
      "blended_expectancy_r": 0.2677
    },
    "NZDCHFm": {
      "status": "WATCH_ONLY",
      "expectancy_r": 0.284,
      "win_rate_resolved": 66.67,
      "signals": 3,
      "asset_class": "forex",
      "timeframe": "M15",
      "exit_mode": "dynamic_sl_tp",
      "optimizer_zf_floor": 0.55,
      "optimizer_fibo_filter": true,
      "optimizer_trailing": true,
      "avg_hours_to_result": 8.17,
      "selection_score": 69.86,
      "live_expectancy_r": NaN,
      "live_win_rate_resolved": NaN,
      "live_signals": 0,
      "blended_expectancy_r": 0.284
    },
    "BTCJPYm": {
      "status": "TRADEABLE",
      "expectancy_r": 0.1932,
      "win_rate_resolved": 68.75,
      "signals": 16,
      "asset_class": "crypto",
      "timeframe": "M15",
      "exit_mode": "dynamic_sl_tp",
      "optimizer_zf_floor": 0.55,
      "optimizer_fibo_filter": true,
      "optimizer_trailing": true,
      "avg_hours_to_result": 4.88,
      "selection_score": 67.63,
      "live_expectancy_r": NaN,
      "live_win_rate_resolved": NaN,
      "live_signals": 0,
      "blended_expectancy_r": 0.1932
    },
    "BTCCNHm": {
      "status": "TRADEABLE",
      "expectancy_r": 0.1491,
      "win_rate_resolved": 71.43,
      "signals": 16,
      "asset_class": "crypto",
      "timeframe": "M15",
      "exit_mode": "dynamic_sl_tp",
      "optimizer_zf_floor": 0.45,
      "optimizer_fibo_filter": true,
      "optimizer_trailing": true,
      "avg_hours_to_result": 6.94,
      "selection_score": 66.95,
      "live_expectancy_r": NaN,
      "live_win_rate_resolved": NaN,
      "live_signals": 0,
      "blended_expectancy_r": 0.1491
    },
    "BTCUSDm": {
      "status": "TRADEABLE",
      "expectancy_r": 0.089,
      "win_rate_resolved": 69.05,
      "signals": 42,
      "asset_class": "crypto",
      "timeframe": "M15",
      "exit_mode": "dynamic_sl_tp",
      "optimizer_zf_floor": 0.45,
      "optimizer_fibo_filter": true,
      "optimizer_trailing": true,
      "avg_hours_to_result": 3.76,
      "selection_score": 64.81,
      "live_expectancy_r": NaN,
      "live_win_rate_resolved": NaN,
      "live_signals": 0,
      "blended_expectancy_r": 0.089
    },
    "GBPCHFm": {
      "status": "WATCH_ONLY",
      "expectancy_r": 0.1675,
      "win_rate_resolved": 66.67,
      "signals": 6,
      "asset_class": "forex",
      "timeframe": "M15",
      "exit_mode": "dynamic_sl_tp",
      "optimizer_zf_floor": 0.55,
      "optimizer_fibo_filter": true,
      "optimizer_trailing": true,
      "avg_hours_to_result": 4.46,
      "selection_score": 64.46,
      "live_expectancy_r": -1.0,
      "live_win_rate_resolved": 0.0,
      "live_signals": 1,
      "blended_expectancy_r": 0.1675
    },
    "AUDNZDm": {
      "status": "WATCH_ONLY",
      "expectancy_r": 0.2262,
      "win_rate_resolved": 60.0,
      "signals": 10,
      "asset_class": "forex",
      "timeframe": "M15",
      "exit_mode": "dynamic_sl_tp",
      "optimizer_zf_floor": 0.45,
      "optimizer_fibo_filter": true,
      "optimizer_trailing": true,
      "avg_hours_to_result": 7.15,
      "selection_score": 64.36,
      "live_expectancy_r": NaN,
      "live_win_rate_resolved": NaN,
      "live_signals": 0,
      "blended_expectancy_r": 0.2262
    },
    "SOLUSDm": {
      "status": "WATCH_ONLY",
      "expectancy_r": 0.0941,
      "win_rate_resolved": 70.0,
      "signals": 11,
      "asset_class": "crypto",
      "timeframe": "M15",
      "exit_mode": "dynamic_sl_tp",
      "optimizer_zf_floor": 0.55,
      "optimizer_fibo_filter": true,
      "optimizer_trailing": true,
      "avg_hours_to_result": 5.3,
      "selection_score": 63.3,
      "live_expectancy_r": NaN,
      "live_win_rate_resolved": NaN,
      "live_signals": 0,
      "blended_expectancy_r": 0.0941
    },
    "AUDJPYm": {
      "status": "TRADEABLE",
      "expectancy_r": 0.1447,
      "win_rate_resolved": 63.16,
      "signals": 21,
      "asset_class": "forex",
      "timeframe": "M15",
      "exit_mode": "dynamic_sl_tp",
      "optimizer_zf_floor": 0.5,
      "optimizer_fibo_filter": true,
      "optimizer_trailing": true,
      "avg_hours_to_result": 2.83,
      "selection_score": 62.96,
      "live_expectancy_r": NaN,
      "live_win_rate_resolved": NaN,
      "live_signals": 0,
      "blended_expectancy_r": 0.1447
    },
    "EURGBPm": {
      "status": "WATCH_ONLY",
      "expectancy_r": 0.055,
      "win_rate_resolved": 72.73,
      "signals": 11,
      "asset_class": "forex",
      "timeframe": "M15",
      "exit_mode": "dynamic_sl_tp",
      "optimizer_zf_floor": 0.5,
      "optimizer_fibo_filter": true,
      "optimizer_trailing": true,
      "avg_hours_to_result": 3.82,
      "selection_score": 62.78,
      "live_expectancy_r": NaN,
      "live_win_rate_resolved": NaN,
      "live_signals": 0,
      "blended_expectancy_r": 0.055
    },
    "GBPJPYm": {
      "status": "WATCH_ONLY",
      "expectancy_r": 0.1781,
      "win_rate_resolved": 60.0,
      "signals": 12,
      "asset_class": "forex",
      "timeframe": "M15",
      "exit_mode": "dynamic_sl_tp",
      "optimizer_zf_floor": 0.55,
      "optimizer_fibo_filter": true,
      "optimizer_trailing": true,
      "avg_hours_to_result": 6.1,
      "selection_score": 62.46,
      "live_expectancy_r": NaN,
      "live_win_rate_resolved": NaN,
      "live_signals": 0,
      "blended_expectancy_r": 0.1781
    },
    "USDCADm": {
      "status": "TRADEABLE",
      "expectancy_r": 0.0832,
      "win_rate_resolved": 63.64,
      "signals": 24,
      "asset_class": "forex",
      "timeframe": "M15",
      "exit_mode": "dynamic_sl_tp",
      "optimizer_zf_floor": 0.45,
      "optimizer_fibo_filter": true,
      "optimizer_trailing": true,
      "avg_hours_to_result": 7.31,
      "selection_score": 60.53,
      "live_expectancy_r": NaN,
      "live_win_rate_resolved": NaN,
      "live_signals": 0,
      "blended_expectancy_r": 0.0832
    },
    "XAUGBPm": {
      "status": "WATCH_ONLY",
      "expectancy_r": 0.0639,
      "win_rate_resolved": 63.64,
      "signals": 11,
      "asset_class": "metal",
      "timeframe": "M15",
      "exit_mode": "dynamic_sl_tp",
      "optimizer_zf_floor": 0.55,
      "optimizer_fibo_filter": true,
      "optimizer_trailing": true,
      "avg_hours_to_result": 5.75,
      "selection_score": 58.42,
      "live_expectancy_r": NaN,
      "live_win_rate_resolved": NaN,
      "live_signals": 0,
      "blended_expectancy_r": 0.0639
    },
    "GBPUSDm": {
      "status": "TRADEABLE",
      "expectancy_r": 0.0448,
      "win_rate_resolved": 61.29,
      "signals": 35,
      "asset_class": "forex",
      "timeframe": "M15",
      "exit_mode": "dynamic_sl_tp",
      "optimizer_zf_floor": 0.5,
      "optimizer_fibo_filter": true,
      "optimizer_trailing": true,
      "avg_hours_to_result": 4.43,
      "selection_score": 58.3,
      "live_expectancy_r": NaN,
      "live_win_rate_resolved": NaN,
      "live_signals": 0,
      "blended_expectancy_r": 0.0448
    },
    "EURCADm": {
      "status": "TRADEABLE",
      "expectancy_r": 0.1091,
      "win_rate_resolved": 56.25,
      "signals": 17,
      "asset_class": "forex",
      "timeframe": "M15",
      "exit_mode": "dynamic_sl_tp",
      "optimizer_zf_floor": 0.5,
      "optimizer_fibo_filter": true,
      "optimizer_trailing": true,
      "avg_hours_to_result": 6.71,
      "selection_score": 57.42,
      "live_expectancy_r": NaN,
      "live_win_rate_resolved": NaN,
      "live_signals": 0,
      "blended_expectancy_r": 0.1091
    },
    "LTCUSDm": {
      "status": "AVOID",
      "expectancy_r": -0.0044,
      "win_rate_resolved": 63.64,
      "signals": 34,
      "asset_class": "crypto",
      "timeframe": "M15",
      "exit_mode": "dynamic_sl_tp",
      "optimizer_zf_floor": 0.5,
      "optimizer_fibo_filter": true,
      "optimizer_trailing": true,
      "avg_hours_to_result": 3.09,
      "selection_score": 57.13,
      "live_expectancy_r": NaN,
      "live_win_rate_resolved": NaN,
      "live_signals": 0,
      "blended_expectancy_r": -0.0044
    },
    "BTCZARm": {
      "status": "TRADEABLE",
      "expectancy_r": 0.0385,
      "win_rate_resolved": 60.0,
      "signals": 17,
      "asset_class": "crypto",
      "timeframe": "M15",
      "exit_mode": "dynamic_sl_tp",
      "optimizer_zf_floor": 0.5,
      "optimizer_fibo_filter": true,
      "optimizer_trailing": true,
      "avg_hours_to_result": 4.26,
      "selection_score": 55.76,
      "live_expectancy_r": NaN,
      "live_win_rate_resolved": NaN,
      "live_signals": 0,
      "blended_expectancy_r": 0.0385
    },
    "NZDUSDm": {
      "status": "AVOID",
      "expectancy_r": -0.0178,
      "win_rate_resolved": 64.71,
      "signals": 18,
      "asset_class": "forex",
      "timeframe": "M15",
      "exit_mode": "dynamic_sl_tp",
      "optimizer_zf_floor": 0.45,
      "optimizer_fibo_filter": true,
      "optimizer_trailing": true,
      "avg_hours_to_result": 5.14,
      "selection_score": 55.74,
      "live_expectancy_r": NaN,
      "live_win_rate_resolved": NaN,
      "live_signals": 0,
      "blended_expectancy_r": -0.0178
    },
    "XAUEURm": {
      "status": "WATCH_ONLY",
      "expectancy_r": 0.0052,
      "win_rate_resolved": 61.54,
      "signals": 13,
      "asset_class": "metal",
      "timeframe": "M15",
      "exit_mode": "dynamic_sl_tp",
      "optimizer_zf_floor": 0.55,
      "optimizer_fibo_filter": true,
      "optimizer_trailing": true,
      "avg_hours_to_result": 6.5,
      "selection_score": 54.76,
      "live_expectancy_r": NaN,
      "live_win_rate_resolved": NaN,
      "live_signals": 0,
      "blended_expectancy_r": 0.0052
    },
    "XRPUSDm": {
      "status": "AVOID",
      "expectancy_r": -0.0217,
      "win_rate_resolved": 60.0,
      "signals": 15,
      "asset_class": "crypto",
      "timeframe": "M15",
      "exit_mode": "dynamic_sl_tp",
      "optimizer_zf_floor": 0.55,
      "optimizer_fibo_filter": true,
      "optimizer_trailing": true,
      "avg_hours_to_result": 3.15,
      "selection_score": 53.16,
      "live_expectancy_r": NaN,
      "live_win_rate_resolved": NaN,
      "live_signals": 0,
      "blended_expectancy_r": -0.0217
    },
    "EURCHFm": {
      "status": "AVOID",
      "expectancy_r": -0.012,
      "win_rate_resolved": 60.0,
      "signals": 6,
      "asset_class": "forex",
      "timeframe": "M15",
      "exit_mode": "dynamic_sl_tp",
      "optimizer_zf_floor": 0.55,
      "optimizer_fibo_filter": true,
      "optimizer_trailing": true,
      "avg_hours_to_result": 9.25,
      "selection_score": 52.55,
      "live_expectancy_r": NaN,
      "live_win_rate_resolved": NaN,
      "live_signals": 0,
      "blended_expectancy_r": -0.012
    },
    "CHFJPYm": {
      "status": "WATCH_ONLY",
      "expectancy_r": 0.0161,
      "win_rate_resolved": 52.94,
      "signals": 20,
      "asset_class": "forex",
      "timeframe": "M15",
      "exit_mode": "dynamic_sl_tp",
      "optimizer_zf_floor": 0.55,
      "optimizer_fibo_filter": true,
      "optimizer_trailing": true,
      "avg_hours_to_result": 5.11,
      "selection_score": 51.64,
      "live_expectancy_r": NaN,
      "live_win_rate_resolved": NaN,
      "live_signals": 0,
      "blended_expectancy_r": 0.0161
    },
    "ETHUSDm": {
      "status": "AVOID",
      "expectancy_r": -0.0989,
      "win_rate_resolved": 62.07,
      "signals": 29,
      "asset_class": "crypto",
      "timeframe": "M15",
      "exit_mode": "dynamic_sl_tp",
      "optimizer_zf_floor": 0.45,
      "optimizer_fibo_filter": true,
      "optimizer_trailing": true,
      "avg_hours_to_result": 5.66,
      "selection_score": 51.46,
      "live_expectancy_r": NaN,
      "live_win_rate_resolved": NaN,
      "live_signals": 0,
      "blended_expectancy_r": -0.0989
    },
    "BTCAUDm": {
      "status": "AVOID",
      "expectancy_r": -0.0405,
      "win_rate_resolved": 58.82,
      "signals": 17,
      "asset_class": "crypto",
      "timeframe": "M15",
      "exit_mode": "dynamic_sl_tp",
      "optimizer_zf_floor": 0.5,
      "optimizer_fibo_filter": true,
      "optimizer_trailing": true,
      "avg_hours_to_result": 2.9,
      "selection_score": 51.43,
      "live_expectancy_r": NaN,
      "live_win_rate_resolved": NaN,
      "live_signals": 0,
      "blended_expectancy_r": -0.0405
    },
    "USDJPYm": {
      "status": "AVOID",
      "expectancy_r": -0.0411,
      "win_rate_resolved": 51.61,
      "signals": 34,
      "asset_class": "forex",
      "timeframe": "M15",
      "exit_mode": "dynamic_sl_tp",
      "optimizer_zf_floor": 0.5,
      "optimizer_fibo_filter": true,
      "optimizer_trailing": true,
      "avg_hours_to_result": 5.27,
      "selection_score": 49.3,
      "live_expectancy_r": NaN,
      "live_win_rate_resolved": NaN,
      "live_signals": 0,
      "blended_expectancy_r": -0.0411
    },
    "EURJPYm": {
      "status": "AVOID",
      "expectancy_r": -0.0331,
      "win_rate_resolved": 48.0,
      "signals": 32,
      "asset_class": "forex",
      "timeframe": "M15",
      "exit_mode": "dynamic_sl_tp",
      "optimizer_zf_floor": 0.5,
      "optimizer_fibo_filter": true,
      "optimizer_trailing": true,
      "avg_hours_to_result": 4.94,
      "selection_score": 47.82,
      "live_expectancy_r": NaN,
      "live_win_rate_resolved": NaN,
      "live_signals": 0,
      "blended_expectancy_r": -0.0331
    },
    "CADJPYm": {
      "status": "AVOID",
      "expectancy_r": -0.1275,
      "win_rate_resolved": 56.52,
      "signals": 24,
      "asset_class": "forex",
      "timeframe": "M15",
      "exit_mode": "dynamic_sl_tp",
      "optimizer_zf_floor": 0.5,
      "optimizer_fibo_filter": true,
      "optimizer_trailing": true,
      "avg_hours_to_result": 4.92,
      "selection_score": 46.86,
      "live_expectancy_r": NaN,
      "live_win_rate_resolved": NaN,
      "live_signals": 0,
      "blended_expectancy_r": -0.1275
    },
    "XAUUSDm": {
      "status": "AVOID",
      "expectancy_r": -0.1695,
      "win_rate_resolved": 52.63,
      "signals": 38,
      "asset_class": "metal",
      "timeframe": "M15",
      "exit_mode": "dynamic_sl_tp",
      "optimizer_zf_floor": 0.45,
      "optimizer_fibo_filter": true,
      "optimizer_trailing": true,
      "avg_hours_to_result": 3.2,
      "selection_score": 43.87,
      "live_expectancy_r": NaN,
      "live_win_rate_resolved": NaN,
      "live_signals": 0,
      "blended_expectancy_r": -0.1695
    },
    "EURUSDm": {
      "status": "AVOID",
      "expectancy_r": -0.1348,
      "win_rate_resolved": 50.0,
      "signals": 19,
      "asset_class": "forex",
      "timeframe": "M15",
      "exit_mode": "dynamic_sl_tp",
      "optimizer_zf_floor": 0.55,
      "optimizer_fibo_filter": true,
      "optimizer_trailing": true,
      "avg_hours_to_result": 5.45,
      "selection_score": 42.8,
      "live_expectancy_r": NaN,
      "live_win_rate_resolved": NaN,
      "live_signals": 0,
      "blended_expectancy_r": -0.1348
    },
    "BNBUSDm": {
      "status": "AVOID",
      "expectancy_r": -0.1526,
      "win_rate_resolved": 50.0,
      "signals": 20,
      "asset_class": "crypto",
      "timeframe": "M15",
      "exit_mode": "dynamic_sl_tp",
      "optimizer_zf_floor": 0.45,
      "optimizer_fibo_filter": true,
      "optimizer_trailing": true,
      "avg_hours_to_result": 2.92,
      "selection_score": 42.08,
      "live_expectancy_r": NaN,
      "live_win_rate_resolved": NaN,
      "live_signals": 0,
      "blended_expectancy_r": -0.1526
    },
    "XAGAUDm": {
      "status": "AVOID",
      "expectancy_r": -0.1526,
      "win_rate_resolved": 43.48,
      "signals": 26,
      "asset_class": "metal",
      "timeframe": "M15",
      "exit_mode": "dynamic_sl_tp",
      "optimizer_zf_floor": 0.5,
      "optimizer_fibo_filter": true,
      "optimizer_trailing": true,
      "avg_hours_to_result": 7.18,
      "selection_score": 39.35,
      "live_expectancy_r": NaN,
      "live_win_rate_resolved": NaN,
      "live_signals": 0,
      "blended_expectancy_r": -0.1526
    },
    "NZDJPYm": {
      "status": "AVOID",
      "expectancy_r": -0.1556,
      "win_rate_resolved": 45.45,
      "signals": 11,
      "asset_class": "forex",
      "timeframe": "M15",
      "exit_mode": "dynamic_sl_tp",
      "optimizer_zf_floor": 0.55,
      "optimizer_fibo_filter": true,
      "optimizer_trailing": true,
      "avg_hours_to_result": 4.52,
      "selection_score": 39.04,
      "live_expectancy_r": NaN,
      "live_win_rate_resolved": NaN,
      "live_signals": 0,
      "blended_expectancy_r": -0.1556
    },
    "XAGGBPm": {
      "status": "AVOID",
      "expectancy_r": -0.1983,
      "win_rate_resolved": 45.83,
      "signals": 27,
      "asset_class": "metal",
      "timeframe": "M15",
      "exit_mode": "dynamic_sl_tp",
      "optimizer_zf_floor": 0.5,
      "optimizer_fibo_filter": true,
      "optimizer_trailing": true,
      "avg_hours_to_result": 7.31,
      "selection_score": 38.36,
      "live_expectancy_r": NaN,
      "live_win_rate_resolved": NaN,
      "live_signals": 0,
      "blended_expectancy_r": -0.1983
    },
    "XAGEURm": {
      "status": "AVOID",
      "expectancy_r": -0.2171,
      "win_rate_resolved": 44.44,
      "signals": 29,
      "asset_class": "metal",
      "timeframe": "M15",
      "exit_mode": "dynamic_sl_tp",
      "optimizer_zf_floor": 0.5,
      "optimizer_fibo_filter": true,
      "optimizer_trailing": true,
      "avg_hours_to_result": 5.92,
      "selection_score": 36.87,
      "live_expectancy_r": NaN,
      "live_win_rate_resolved": NaN,
      "live_signals": 0,
      "blended_expectancy_r": -0.2171
    },
    "UKOILm": {
      "status": "AVOID",
      "expectancy_r": -0.2821,
      "win_rate_resolved": 50.0,
      "signals": 9,
      "asset_class": "energy",
      "timeframe": "M15",
      "exit_mode": "dynamic_sl_tp",
      "optimizer_zf_floor": 0.55,
      "optimizer_fibo_filter": true,
      "optimizer_trailing": true,
      "avg_hours_to_result": 4.72,
      "selection_score": 35.18,
      "live_expectancy_r": NaN,
      "live_win_rate_resolved": NaN,
      "live_signals": 0,
      "blended_expectancy_r": -0.2821
    },
    "XAGUSDm": {
      "status": "AVOID",
      "expectancy_r": -0.4357,
      "win_rate_resolved": 36.36,
      "signals": 46,
      "asset_class": "metal",
      "timeframe": "M15",
      "exit_mode": "dynamic_sl_tp",
      "optimizer_zf_floor": 0.45,
      "optimizer_fibo_filter": true,
      "optimizer_trailing": true,
      "avg_hours_to_result": 4.54,
      "selection_score": 28.61,
      "live_expectancy_r": NaN,
      "live_win_rate_resolved": NaN,
      "live_signals": 0,
      "blended_expectancy_r": -0.4357
    },
    "USOILm": {
      "status": "AVOID",
      "expectancy_r": -0.5714,
      "win_rate_resolved": 31.37,
      "signals": 52,
      "asset_class": "energy",
      "timeframe": "M15",
      "exit_mode": "dynamic_sl_tp",
      "optimizer_zf_floor": 0.45,
      "optimizer_fibo_filter": true,
      "optimizer_trailing": true,
      "avg_hours_to_result": 3.19,
      "selection_score": 26.5,
      "live_expectancy_r": NaN,
      "live_win_rate_resolved": NaN,
      "live_signals": 0,
      "blended_expectancy_r": -0.5714
    },
    "XAGJPYm": {
      "status": "AVOID",
      "expectancy_r": -0.4117,
      "win_rate_resolved": 28.57,
      "signals": 47,
      "asset_class": "metal",
      "timeframe": "M15",
      "exit_mode": "dynamic_sl_tp",
      "optimizer_zf_floor": 0.5,
      "optimizer_fibo_filter": true,
      "optimizer_trailing": true,
      "avg_hours_to_result": 4.62,
      "selection_score": 24.7,
      "live_expectancy_r": NaN,
      "live_win_rate_resolved": NaN,
      "live_signals": 0,
      "blended_expectancy_r": -0.4117
    },
    "EURNZDm": {
      "status": "AVOID",
      "expectancy_r": -0.5022,
      "win_rate_resolved": 33.33,
      "signals": 9,
      "asset_class": "forex",
      "timeframe": "M15",
      "exit_mode": "dynamic_sl_tp",
      "optimizer_zf_floor": 0.5,
      "optimizer_fibo_filter": true,
      "optimizer_trailing": true,
      "avg_hours_to_result": 3.67,
      "selection_score": 24.33,
      "live_expectancy_r": NaN,
      "live_win_rate_resolved": NaN,
      "live_signals": 0,
      "blended_expectancy_r": -0.5022
    },
    "BTCTHBm": {
      "status": "AVOID",
      "expectancy_r": -1.0,
      "win_rate_resolved": 0.0,
      "signals": 1,
      "asset_class": "crypto",
      "timeframe": "M15",
      "exit_mode": "dynamic_sl_tp",
      "optimizer_zf_floor": 0.45,
      "optimizer_fibo_filter": true,
      "optimizer_trailing": true,
      "avg_hours_to_result": 18.25,
      "selection_score": 7.33,
      "live_expectancy_r": NaN,
      "live_win_rate_resolved": NaN,
      "live_signals": 0,
      "blended_expectancy_r": -1.0
    },
    "ADAUSDm": {
      "status": "AVOID",
      "expectancy_r": NaN,
      "win_rate_resolved": NaN,
      "signals": 0,
      "asset_class": "crypto",
      "timeframe": "M15",
      "exit_mode": "nan",
      "optimizer_zf_floor": 0.45,
      "optimizer_fibo_filter": true,
      "optimizer_trailing": true,
      "avg_hours_to_result": NaN,
      "selection_score": 0.0,
      "live_expectancy_r": NaN,
      "live_win_rate_resolved": NaN,
      "live_signals": 0,
      "blended_expectancy_r": NaN
    },
    "BTCKRWm": {
      "status": "AVOID",
      "expectancy_r": NaN,
      "win_rate_resolved": NaN,
      "signals": 0,
      "asset_class": "crypto",
      "timeframe": "M15",
      "exit_mode": "nan",
      "optimizer_zf_floor": 0.45,
      "optimizer_fibo_filter": true,
      "optimizer_trailing": true,
      "avg_hours_to_result": NaN,
      "selection_score": 0.0,
      "live_expectancy_r": NaN,
      "live_win_rate_resolved": NaN,
      "live_signals": 0,
      "blended_expectancy_r": NaN
    },
    "DOGEUSDm": {
      "status": "AVOID",
      "expectancy_r": NaN,
      "win_rate_resolved": NaN,
      "signals": 0,
      "asset_class": "crypto",
      "timeframe": "M15",
      "exit_mode": "nan",
      "optimizer_zf_floor": 0.45,
      "optimizer_fibo_filter": true,
      "optimizer_trailing": true,
      "avg_hours_to_result": NaN,
      "selection_score": 0.0,
      "live_expectancy_r": NaN,
      "live_win_rate_resolved": NaN,
      "live_signals": 0,
      "blended_expectancy_r": NaN
    },
    "DOTUSDm": {
      "status": "AVOID",
      "expectancy_r": NaN,
      "win_rate_resolved": NaN,
      "signals": 0,
      "asset_class": "crypto",
      "timeframe": "M15",
      "exit_mode": "nan",
      "optimizer_zf_floor": 0.45,
      "optimizer_fibo_filter": true,
      "optimizer_trailing": true,
      "avg_hours_to_result": NaN,
      "selection_score": 0.0,
      "live_expectancy_r": NaN,
      "live_win_rate_resolved": NaN,
      "live_signals": 0,
      "blended_expectancy_r": NaN
    },
    "LINKUSDm": {
      "status": "AVOID",
      "expectancy_r": NaN,
      "win_rate_resolved": NaN,
      "signals": 0,
      "asset_class": "crypto",
      "timeframe": "M15",
      "exit_mode": "nan",
      "optimizer_zf_floor": 0.45,
      "optimizer_fibo_filter": true,
      "optimizer_trailing": true,
      "avg_hours_to_result": NaN,
      "selection_score": 0.0,
      "live_expectancy_r": NaN,
      "live_win_rate_resolved": NaN,
      "live_signals": 0,
      "blended_expectancy_r": NaN
    }
  }
}