{
  "scan_time": "2026-06-16T01:30:02.718802+08:00",
  "account_equity": 9980.76,
  "news_status": "LOW RISK",
  "macro": {
    "DXY": 99.59100341796875,
    "US10Y": 4.468999862670898,
    "GOLD": 4352.39990234375
  },
  "summary": {
    "symbols_scanned": 28,
    "buy_candidates": 0,
    "sell_candidates": 0,
    "resonance_mismatches": 7
  },
  "previous_archive": "D:\\FOREX\\zf_archival_vault\\zf_scan_20260616_010007.json",
  "top_buy": [],
  "top_sell": [],
  "resonance_mismatches": [
    {
      "Symbol": "NZDJPY.m",
      "Close": 93.437,
      "Bid": 93.437,
      "Ask": 93.452,
      "Mid_Price": 93.4445,
      "Direction": "BUY",
      "Projected_Direction": "BUY",
      "Signal_Type": "PROJECTED",
      "Setup_Maturity": 0.8874,
      "Projection_Score": 0.7461,
      "Projection_Price_Slope": -0.012800000000000296,
      "Regime": "TREND",
      "Confidence": 55,
      "Optimizer_Mode": "DEFAULT",
      "Optimizer_Confidence_Floor": 60,
      "Optimizer_Max_Spread_Pips": 3.0,
      "Optimizer_Max_Slippage_Pips": 2.0,
      "Optimizer_Projection_Maturity_Floor": 0.55,
      "Optimizer_Projection_ZF_Floor": 0.45,
      "Optimizer_Projection_Confidence_Floor": 58,
      "Dynamic_Lot": 0.0,
      "Entry_Price": 93.437,
      "SL_Pips": 13.5,
      "SL_Points": 135.0,
      "SL_Price": 93.302,
      "SL_Model": "DATA_DRIVEN",
      "TP_Pips": 16.9,
      "TP_Points": 169.0,
      "TP_Price": 93.606,
      "TP_Model": "DATA_DRIVEN",
      "RR_Ratio": 1.25,
      "Spread_Pips": 1.5000000000000568,
      "Slippage_Est_Pips": 1.31,
      "Bid_Depth": 0.0,
      "Ask_Depth": 0.0,
      "Total_Depth": 0.0,
      "Depth_Imbalance": 0.0,
      "Depth_Available": false,
      "Liquidity_Cluster_Price": NaN,
      "Liquidity_Cluster_Volume": 0.0,
      "Liquidity_Stress": 0.8250000000000199,
      "Liquidity_Status": "STRESSED",
      "Liquidity_Void": false,
      "Lambda_Liquidity": 0.9250000000000199,
      "Drift": 0.009427113420764698,
      "Decay_Integral": -0.6525958342492998,
      "Inflection_Detected": false,
      "ZF_Score": 0.7053291706232698,
      "Previous_Direction": "BUY",
      "Previous_Drift": 0.023594061630878006,
      "Previous_ZF_Score": 0.6446272339582325,
      "Previous_Lambda_Liquidity": 0.7499999999996817,
      "Previous_Liquidity_Status": "LAMINAR",
      "Delta_Drift": -0.014166948210113307,
      "Delta_ZF_Score": 0.060701936665037315,
      "Delta_Lambda": 0.17500000000033822,
      "Direction_Changed": false,
      "Liquidity_Status_Changed": true,
      "Memory_Status": "RESONANCE_MISMATCH",
      "Risk_Mode": "PROFILE_LOCK",
      "Trade_Allowed": false,
      "Action_Signal": "WATCH HISTORIS",
      "Risk_Note": "Pair historis negatif/belum tervalidasi; tidak masuk TOP eksekusi.",
      "Session_Phase": "ANOMALOUS",
      "User_Recommendation": "Jangan entry. Pair ini belum lolos validasi historis.",
      "Historical_Status": "AVOID",
      "Historical_Expectancy_R": -0.0455,
      "Historical_Win_Rate": 41.31,
      "Historical_Signals": 823,
      "Live_Expectancy_R": NaN,
      "Live_Signals": 0,
      "Market_Session": "NEW_YORK",
      "Accuracy_Quality_Score": 42.3,
      "Accuracy_Gate": "WATCH",
      "Accuracy_Gate_Reason": "quality 42.3 < 62 | status historis AVOID | winrate historis 41.31% < 45.00% | expectancy historis -0.0455R < 0.0200R",
      "Mismatch_Rank": 0.17500000000033822
    },
    {
      "Symbol": "AUDJPY.m",
      "Close": 113.453,
      "Bid": 113.453,
      "Ask": 113.468,
      "Mid_Price": 113.4605,
      "Direction": "NEUTRAL",
      "Projected_Direction": "NEUTRAL",
      "Signal_Type": "NEUTRAL",
      "Setup_Maturity": 0.3159,
      "Projection_Score": 0.4058,
      "Projection_Price_Slope": 0.0024857142857151733,
      "Regime": "RANGE",
      "Confidence": 0,
      "Optimizer_Mode": "DEFAULT",
      "Optimizer_Confidence_Floor": 60,
      "Optimizer_Max_Spread_Pips": 3.0,
      "Optimizer_Max_Slippage_Pips": 2.0,
      "Optimizer_Projection_Maturity_Floor": 0.55,
      "Optimizer_Projection_ZF_Floor": 0.45,
      "Optimizer_Projection_Confidence_Floor": 58,
      "Dynamic_Lot": 0.0,
      "Entry_Price": 113.453,
      "SL_Pips": 10.7,
      "SL_Points": 107.0,
      "SL_Price": NaN,
      "SL_Model": "DATA_DRIVEN",
      "TP_Pips": 0.0,
      "TP_Points": 0.0,
      "TP_Price": NaN,
      "TP_Model": "NO_SIGNAL",
      "RR_Ratio": 0.0,
      "Spread_Pips": 1.5000000000000568,
      "Slippage_Est_Pips": 1.31,
      "Bid_Depth": 0.0,
      "Ask_Depth": 0.0,
      "Total_Depth": 0.0,
      "Depth_Imbalance": 0.0,
      "Depth_Available": false,
      "Liquidity_Cluster_Price": NaN,
      "Liquidity_Cluster_Volume": 0.0,
      "Liquidity_Stress": 0.8250000000000199,
      "Liquidity_Status": "STRESSED",
      "Liquidity_Void": false,
      "Lambda_Liquidity": 0.9250000000000199,
      "Drift": 0.011817247258755496,
      "Decay_Integral": -0.008820035227986665,
      "Inflection_Detected": true,
      "ZF_Score": 0.7164418417817764,
      "Previous_Direction": "NEUTRAL",
      "Previous_Drift": 0.007259762043143588,
      "Previous_ZF_Score": 0.6934760886296344,
      "Previous_Lambda_Liquidity": 0.7500000000001791,
      "Previous_Liquidity_Status": "LAMINAR",
      "Delta_Drift": 0.004557485215611908,
      "Delta_ZF_Score": 0.022965753152142,
      "Delta_Lambda": 0.17499999999984084,
      "Direction_Changed": false,
      "Liquidity_Status_Changed": true,
      "Memory_Status": "RESONANCE_MISMATCH",
      "Risk_Mode": "NORMAL",
      "Trade_Allowed": false,
      "Action_Signal": "WASPADA",
      "Risk_Note": "",
      "Session_Phase": "ANOMALOUS",
      "User_Recommendation": "Waspada. Ada tanda anomali, tetapi belum ada arah entry yang matang. Likuiditas: STRESSED.",
      "Historical_Status": "TRADEABLE",
      "Historical_Expectancy_R": 0.1164,
      "Historical_Win_Rate": 49.71,
      "Historical_Signals": 840,
      "Live_Expectancy_R": NaN,
      "Live_Signals": 0,
      "Market_Session": "NEW_YORK",
      "Accuracy_Quality_Score": 20.69,
      "Accuracy_Gate": "NEUTRAL",
      "Accuracy_Gate_Reason": "Belum ada arah BUY/SELL matang.",
      "Mismatch_Rank": 0.17499999999984084
    },
    {
      "Symbol": "AUDNZD.m",
      "Close": 1.21412,
      "Bid": 1.21412,
      "Ask": 1.21427,
      "Mid_Price": 1.2141950000000001,
      "Direction": "NEUTRAL",
      "Projected_Direction": "NEUTRAL",
      "Signal_Type": "NEUTRAL",
      "Setup_Maturity": 0.7849,
      "Projection_Score": 0.694,
      "Projection_Price_Slope": 0.00018714285714288204,
      "Regime": "TREND",
      "Confidence": 0,
      "Optimizer_Mode": "DEFAULT",
      "Optimizer_Confidence_Floor": 60,
      "Optimizer_Max_Spread_Pips": 3.0,
      "Optimizer_Max_Slippage_Pips": 2.0,
      "Optimizer_Projection_Maturity_Floor": 0.55,
      "Optimizer_Projection_ZF_Floor": 0.45,
      "Optimizer_Projection_Confidence_Floor": 58,
      "Dynamic_Lot": 0.0,
      "Entry_Price": 1.21412,
      "SL_Pips": 13.5,
      "SL_Points": 135.0,
      "SL_Price": NaN,
      "SL_Model": "DATA_DRIVEN",
      "TP_Pips": 0.0,
      "TP_Points": 0.0,
      "TP_Price": NaN,
      "TP_Model": "NO_SIGNAL",
      "RR_Ratio": 0.0,
      "Spread_Pips": 1.4999999999987244,
      "Slippage_Est_Pips": 1.31,
      "Bid_Depth": 0.0,
      "Ask_Depth": 0.0,
      "Total_Depth": 0.0,
      "Depth_Imbalance": 0.0,
      "Depth_Available": false,
      "Liquidity_Cluster_Price": NaN,
      "Liquidity_Cluster_Volume": 0.0,
      "Liquidity_Stress": 0.8249999999995534,
      "Liquidity_Status": "STRESSED",
      "Liquidity_Void": false,
      "Lambda_Liquidity": 0.9249999999995534,
      "Drift": 0.006639934105068609,
      "Decay_Integral": 0.5397610665607828,
      "Inflection_Detected": false,
      "ZF_Score": 0.7358286052420959,
      "Previous_Direction": "SELL",
      "Previous_Drift": 0.01428043970055422,
      "Previous_ZF_Score": 0.6851708955981649,
      "Previous_Lambda_Liquidity": 0.7850000000001905,
      "Previous_Liquidity_Status": "LAMINAR",
      "Delta_Drift": -0.00764050559548561,
      "Delta_ZF_Score": 0.050657709643931015,
      "Delta_Lambda": 0.13999999999936286,
      "Direction_Changed": true,
      "Liquidity_Status_Changed": true,
      "Memory_Status": "RESONANCE_MISMATCH",
      "Risk_Mode": "NORMAL",
      "Trade_Allowed": false,
      "Action_Signal": "WASPADA",
      "Risk_Note": "",
      "Session_Phase": "ANOMALOUS",
      "User_Recommendation": "Waspada. Ada tanda anomali, tetapi belum ada arah entry yang matang. Likuiditas: STRESSED.",
      "Historical_Status": "AVOID",
      "Historical_Expectancy_R": -0.0447,
      "Historical_Win_Rate": 41.37,
      "Historical_Signals": 750,
      "Live_Expectancy_R": NaN,
      "Live_Signals": 0,
      "Market_Session": "NEW_YORK",
      "Accuracy_Quality_Score": 25.07,
      "Accuracy_Gate": "NEUTRAL",
      "Accuracy_Gate_Reason": "Belum ada arah BUY/SELL matang.",
      "Mismatch_Rank": 0.13999999999936286
    },
    {
      "Symbol": "CHFJPY.m",
      "Close": 201.93,
      "Bid": 201.93,
      "Ask": 201.955,
      "Mid_Price": 201.9425,
      "Direction": "NEUTRAL",
      "Projected_Direction": "NEUTRAL",
      "Signal_Type": "NEUTRAL",
      "Setup_Maturity": 0.7821,
      "Projection_Score": 0.6917,
      "Projection_Price_Slope": 0.015400000000001163,
      "Regime": "RANGE",
      "Confidence": 0,
      "Optimizer_Mode": "DEFAULT",
      "Optimizer_Confidence_Floor": 60,
      "Optimizer_Max_Spread_Pips": 3.0,
      "Optimizer_Max_Slippage_Pips": 2.0,
      "Optimizer_Projection_Maturity_Floor": 0.55,
      "Optimizer_Projection_ZF_Floor": 0.45,
      "Optimizer_Projection_Confidence_Floor": 58,
      "Dynamic_Lot": 0.0,
      "Entry_Price": 201.93,
      "SL_Pips": 15.8,
      "SL_Points": 158.0,
      "SL_Price": NaN,
      "SL_Model": "DATA_DRIVEN",
      "TP_Pips": 0.0,
      "TP_Points": 0.0,
      "TP_Price": NaN,
      "TP_Model": "NO_SIGNAL",
      "RR_Ratio": 0.0,
      "Spread_Pips": 2.5000000000005684,
      "Slippage_Est_Pips": 2.19,
      "Bid_Depth": 0.0,
      "Ask_Depth": 0.0,
      "Total_Depth": 0.0,
      "Depth_Imbalance": 0.0,
      "Depth_Available": false,
      "Liquidity_Cluster_Price": NaN,
      "Liquidity_Cluster_Volume": 0.0,
      "Liquidity_Stress": 1.0,
      "Liquidity_Status": "STRESSED",
      "Liquidity_Void": false,
      "Lambda_Liquidity": 1.1,
      "Drift": 0.008252100174090471,
      "Decay_Integral": -0.3639378999007315,
      "Inflection_Detected": true,
      "ZF_Score": 0.729675479407552,
      "Previous_Direction": "BUY",
      "Previous_Drift": 0.011862022045144301,
      "Previous_ZF_Score": 0.6997938030239359,
      "Previous_Lambda_Liquidity": 0.9949999999998568,
      "Previous_Liquidity_Status": "STRESSED",
      "Delta_Drift": -0.00360992187105383,
      "Delta_ZF_Score": 0.02988167638361605,
      "Delta_Lambda": 0.10500000000014331,
      "Direction_Changed": true,
      "Liquidity_Status_Changed": false,
      "Memory_Status": "RESONANCE_MISMATCH",
      "Risk_Mode": "SLIPPAGE_LOCK",
      "Trade_Allowed": false,
      "Action_Signal": "TUNGGU SLIPPAGE",
      "Risk_Note": "Estimasi slippage melebihi batas.",
      "Session_Phase": "ANOMALOUS",
      "User_Recommendation": "Jangan entry. Risiko slippage terlalu besar.",
      "Historical_Status": "AVOID",
      "Historical_Expectancy_R": -0.1405,
      "Historical_Win_Rate": 36.11,
      "Historical_Signals": 838,
      "Live_Expectancy_R": NaN,
      "Live_Signals": 0,
      "Market_Session": "NEW_YORK",
      "Accuracy_Quality_Score": 14.04,
      "Accuracy_Gate": "NEUTRAL",
      "Accuracy_Gate_Reason": "Belum ada arah BUY/SELL matang.",
      "Mismatch_Rank": 0.10500000000014331
    },
    {
      "Symbol": "EURCHF.m",
      "Close": 0.92068,
      "Bid": 0.92068,
      "Ask": 0.92073,
      "Mid_Price": 0.9207050000000001,
      "Direction": "SELL",
      "Projected_Direction": "SELL",
      "Signal_Type": "PROJECTED",
      "Setup_Maturity": 0.7519,
      "Projection_Score": 0.6485,
      "Projection_Price_Slope": 5.0000000000092044e-05,
      "Regime": "RANGE",
      "Confidence": 72,
      "Optimizer_Mode": "DEFAULT",
      "Optimizer_Confidence_Floor": 60,
      "Optimizer_Max_Spread_Pips": 3.0,
      "Optimizer_Max_Slippage_Pips": 2.0,
      "Optimizer_Projection_Maturity_Floor": 0.55,
      "Optimizer_Projection_ZF_Floor": 0.45,
      "Optimizer_Projection_Confidence_Floor": 58,
      "Dynamic_Lot": 0.0,
      "Entry_Price": 0.92068,
      "SL_Pips": 5.5,
      "SL_Points": 55.0,
      "SL_Price": 0.92123,
      "SL_Model": "DATA_DRIVEN",
      "TP_Pips": 6.9,
      "TP_Points": 69.0,
      "TP_Price": 0.91999,
      "TP_Model": "DATA_DRIVEN",
      "RR_Ratio": 1.25,
      "Spread_Pips": 0.49999999999994493,
      "Slippage_Est_Pips": 0.44,
      "Bid_Depth": 0.0,
      "Ask_Depth": 0.0,
      "Total_Depth": 0.0,
      "Depth_Imbalance": 0.0,
      "Depth_Available": false,
      "Liquidity_Cluster_Price": NaN,
      "Liquidity_Cluster_Volume": 0.0,
      "Liquidity_Stress": 0.4749999999999807,
      "Liquidity_Status": "LAMINAR",
      "Liquidity_Void": false,
      "Lambda_Liquidity": 0.5749999999999807,
      "Drift": 0.006925795703981857,
      "Decay_Integral": 0.020029625617229083,
      "Inflection_Detected": true,
      "ZF_Score": 0.6554633860653818,
      "Previous_Direction": "NEUTRAL",
      "Previous_Drift": 0.021729806831657497,
      "Previous_ZF_Score": 0.5662662724699818,
      "Previous_Lambda_Liquidity": 0.6100000000002099,
      "Previous_Liquidity_Status": "LAMINAR",
      "Delta_Drift": -0.01480401112767564,
      "Delta_ZF_Score": 0.08919711359539995,
      "Delta_Lambda": -0.03500000000022918,
      "Direction_Changed": true,
      "Liquidity_Status_Changed": false,
      "Memory_Status": "RESONANCE_MISMATCH",
      "Risk_Mode": "PROFILE_LOCK",
      "Trade_Allowed": false,
      "Action_Signal": "WATCH HISTORIS",
      "Risk_Note": "Pair historis negatif/belum tervalidasi; tidak masuk TOP eksekusi.",
      "Session_Phase": "ANOMALOUS",
      "User_Recommendation": "Jangan entry. Pair ini belum lolos validasi historis.",
      "Historical_Status": "AVOID",
      "Historical_Expectancy_R": -0.0096,
      "Historical_Win_Rate": 43.14,
      "Historical_Signals": 801,
      "Live_Expectancy_R": NaN,
      "Live_Signals": 0,
      "Market_Session": "NEW_YORK",
      "Accuracy_Quality_Score": 52.75,
      "Accuracy_Gate": "WATCH",
      "Accuracy_Gate_Reason": "quality 52.8 < 62 | status historis AVOID | winrate historis 43.14% < 45.00% | expectancy historis -0.0096R < 0.0200R",
      "Mismatch_Rank": 0.08919711359539995
    },
    {
      "Symbol": "EURCAD.m",
      "Close": 1.62182,
      "Bid": 1.62182,
      "Ask": 1.6219000000000001,
      "Mid_Price": 1.62186,
      "Direction": "NEUTRAL",
      "Projected_Direction": "NEUTRAL",
      "Signal_Type": "NEUTRAL",
      "Setup_Maturity": 0.6934,
      "Projection_Score": 0.606,
      "Projection_Price_Slope": -1.9428571428694423e-05,
      "Regime": "RANGE",
      "Confidence": 0,
      "Optimizer_Mode": "DEFAULT",
      "Optimizer_Confidence_Floor": 60,
      "Optimizer_Max_Spread_Pips": 3.0,
      "Optimizer_Max_Slippage_Pips": 2.0,
      "Optimizer_Projection_Maturity_Floor": 0.55,
      "Optimizer_Projection_ZF_Floor": 0.45,
      "Optimizer_Projection_Confidence_Floor": 58,
      "Dynamic_Lot": 0.0,
      "Entry_Price": 1.62182,
      "SL_Pips": 11.8,
      "SL_Points": 118.0,
      "SL_Price": NaN,
      "SL_Model": "DATA_DRIVEN",
      "TP_Pips": 0.0,
      "TP_Points": 0.0,
      "TP_Price": NaN,
      "TP_Model": "NO_SIGNAL",
      "RR_Ratio": 0.0,
      "Spread_Pips": 0.8000000000008001,
      "Slippage_Est_Pips": 0.7,
      "Bid_Depth": 0.0,
      "Ask_Depth": 0.0,
      "Total_Depth": 0.0,
      "Depth_Imbalance": 0.0,
      "Depth_Available": false,
      "Liquidity_Cluster_Price": NaN,
      "Liquidity_Cluster_Volume": 0.0,
      "Liquidity_Stress": 0.5800000000002801,
      "Liquidity_Status": "LAMINAR",
      "Liquidity_Void": false,
      "Lambda_Liquidity": 0.68000000000028,
      "Drift": 0.021433385565672692,
      "Decay_Integral": -0.08368580307373957,
      "Inflection_Detected": false,
      "ZF_Score": 0.6312000146226262,
      "Previous_Direction": "BUY",
      "Previous_Drift": 0.01724352635854631,
      "Previous_ZF_Score": 0.6528330658705792,
      "Previous_Lambda_Liquidity": 0.7150000000005093,
      "Previous_Liquidity_Status": "LAMINAR",
      "Delta_Drift": 0.004189859207126383,
      "Delta_ZF_Score": -0.021633051247953006,
      "Delta_Lambda": -0.03500000000022929,
      "Direction_Changed": true,
      "Liquidity_Status_Changed": false,
      "Memory_Status": "RESONANCE_MISMATCH",
      "Risk_Mode": "NORMAL",
      "Trade_Allowed": false,
      "Action_Signal": "WASPADA",
      "Risk_Note": "",
      "Session_Phase": "ANOMALOUS",
      "User_Recommendation": "Waspada. Ada tanda anomali, tetapi belum ada arah entry yang matang. Likuiditas: LAMINAR.",
      "Historical_Status": "AVOID",
      "Historical_Expectancy_R": -0.1581,
      "Historical_Win_Rate": 34.83,
      "Historical_Signals": 757,
      "Live_Expectancy_R": NaN,
      "Live_Signals": 0,
      "Market_Session": "NEW_YORK",
      "Accuracy_Quality_Score": 25.57,
      "Accuracy_Gate": "NEUTRAL",
      "Accuracy_Gate_Reason": "Belum ada arah BUY/SELL matang.",
      "Mismatch_Rank": 0.03500000000022929
    },
    {
      "Symbol": "GBPJPY.m",
      "Close": 215.212,
      "Bid": 215.212,
      "Ask": 215.242,
      "Mid_Price": 215.22699999999998,
      "Direction": "NEUTRAL",
      "Projected_Direction": "NEUTRAL",
      "Signal_Type": "NEUTRAL",
      "Setup_Maturity": 0.4059,
      "Projection_Score": 0.4771,
      "Projection_Price_Slope": 0.012542857142844074,
      "Regime": "RANGE",
      "Confidence": 0,
      "Optimizer_Mode": "DEFAULT",
      "Optimizer_Confidence_Floor": 60,
      "Optimizer_Max_Spread_Pips": 3.0,
      "Optimizer_Max_Slippage_Pips": 2.0,
      "Optimizer_Projection_Maturity_Floor": 0.55,
      "Optimizer_Projection_ZF_Floor": 0.45,
      "Optimizer_Projection_Confidence_Floor": 58,
      "Dynamic_Lot": 0.0,
      "Entry_Price": 215.212,
      "SL_Pips": 16.1,
      "SL_Points": 161.0,
      "SL_Price": NaN,
      "SL_Model": "DATA_DRIVEN",
      "TP_Pips": 0.0,
      "TP_Points": 0.0,
      "TP_Price": NaN,
      "TP_Model": "NO_SIGNAL",
      "RR_Ratio": 0.0,
      "Spread_Pips": 3.0000000000001137,
      "Slippage_Est_Pips": 2.63,
      "Bid_Depth": 0.0,
      "Ask_Depth": 0.0,
      "Total_Depth": 0.0,
      "Depth_Imbalance": 0.0,
      "Depth_Available": false,
      "Liquidity_Cluster_Price": NaN,
      "Liquidity_Cluster_Volume": 0.0,
      "Liquidity_Stress": 1.0,
      "Liquidity_Status": "VOID",
      "Liquidity_Void": true,
      "Lambda_Liquidity": 1.1,
      "Drift": 0.003925402702085742,
      "Decay_Integral": -0.24423534129087582,
      "Inflection_Detected": true,
      "ZF_Score": 0.7738631578589075,
      "Previous_Direction": "NEUTRAL",
      "Previous_Drift": 0.00822389058686801,
      "Previous_ZF_Score": 0.7578581215736293,
      "Previous_Lambda_Liquidity": 1.0650000000001911,
      "Previous_Liquidity_Status": "STRESSED",
      "Delta_Drift": -0.004298487884782268,
      "Delta_ZF_Score": 0.016005036285278162,
      "Delta_Lambda": 0.03499999999980896,
      "Direction_Changed": false,
      "Liquidity_Status_Changed": true,
      "Memory_Status": "RESONANCE_MISMATCH",
      "Risk_Mode": "LIQUIDITY_LOCK",
      "Trade_Allowed": false,
      "Action_Signal": "PERTAHANAN LIKUIDITAS",
      "Risk_Note": "Liquidity void atau spread terlalu lebar.",
      "Session_Phase": "ANOMALOUS",
      "User_Recommendation": "Jangan entry. Likuiditas/spread sedang tidak sehat.",
      "Historical_Status": "AVOID",
      "Historical_Expectancy_R": -0.054,
      "Historical_Win_Rate": 40.56,
      "Historical_Signals": 816,
      "Live_Expectancy_R": NaN,
      "Live_Signals": 0,
      "Market_Session": "NEW_YORK",
      "Accuracy_Quality_Score": 5.57,
      "Accuracy_Gate": "NEUTRAL",
      "Accuracy_Gate_Reason": "Belum ada arah BUY/SELL matang.",
      "Mismatch_Rank": 0.03499999999980896
    }
  ],
  "results": [
    {
      "Symbol": "AUDNZD.m",
      "Close": 1.21412,
      "Bid": 1.21412,
      "Ask": 1.21427,
      "Mid_Price": 1.2141950000000001,
      "Direction": "NEUTRAL",
      "Projected_Direction": "NEUTRAL",
      "Signal_Type": "NEUTRAL",
      "Setup_Maturity": 0.7849,
      "Projection_Score": 0.694,
      "Projection_Price_Slope": 0.00018714285714288204,
      "Regime": "TREND",
      "Confidence": 0,
      "Optimizer_Mode": "DEFAULT",
      "Optimizer_Confidence_Floor": 60,
      "Optimizer_Max_Spread_Pips": 3.0,
      "Optimizer_Max_Slippage_Pips": 2.0,
      "Optimizer_Projection_Maturity_Floor": 0.55,
      "Optimizer_Projection_ZF_Floor": 0.45,
      "Optimizer_Projection_Confidence_Floor": 58,
      "Dynamic_Lot": 0.0,
      "Entry_Price": 1.21412,
      "SL_Pips": 13.5,
      "SL_Points": 135.0,
      "SL_Price": NaN,
      "SL_Model": "DATA_DRIVEN",
      "TP_Pips": 0.0,
      "TP_Points": 0.0,
      "TP_Price": NaN,
      "TP_Model": "NO_SIGNAL",
      "RR_Ratio": 0.0,
      "Spread_Pips": 1.4999999999987244,
      "Slippage_Est_Pips": 1.31,
      "Bid_Depth": 0.0,
      "Ask_Depth": 0.0,
      "Total_Depth": 0.0,
      "Depth_Imbalance": 0.0,
      "Depth_Available": false,
      "Liquidity_Cluster_Price": NaN,
      "Liquidity_Cluster_Volume": 0.0,
      "Liquidity_Stress": 0.8249999999995534,
      "Liquidity_Status": "STRESSED",
      "Liquidity_Void": false,
      "Lambda_Liquidity": 0.9249999999995534,
      "Drift": 0.006639934105068609,
      "Decay_Integral": 0.5397610665607828,
      "Inflection_Detected": false,
      "ZF_Score": 0.7358286052420959,
      "Previous_Direction": "SELL",
      "Previous_Drift": 0.01428043970055422,
      "Previous_ZF_Score": 0.6851708955981649,
      "Previous_Lambda_Liquidity": 0.7850000000001905,
      "Previous_Liquidity_Status": "LAMINAR",
      "Delta_Drift": -0.00764050559548561,
      "Delta_ZF_Score": 0.050657709643931015,
      "Delta_Lambda": 0.13999999999936286,
      "Direction_Changed": true,
      "Liquidity_Status_Changed": true,
      "Memory_Status": "RESONANCE_MISMATCH",
      "Risk_Mode": "NORMAL",
      "Trade_Allowed": false,
      "Action_Signal": "WASPADA",
      "Risk_Note": "",
      "Session_Phase": "ANOMALOUS",
      "User_Recommendation": "Waspada. Ada tanda anomali, tetapi belum ada arah entry yang matang. Likuiditas: STRESSED.",
      "Historical_Status": "AVOID",
      "Historical_Expectancy_R": -0.0447,
      "Historical_Win_Rate": 41.37,
      "Historical_Signals": 750,
      "Live_Expectancy_R": NaN,
      "Live_Signals": 0,
      "Market_Session": "NEW_YORK",
      "Accuracy_Quality_Score": 25.07,
      "Accuracy_Gate": "NEUTRAL",
      "Accuracy_Gate_Reason": "Belum ada arah BUY/SELL matang.",
      "Ranking_Score": 32.97804302621048
    },
    {
      "Symbol": "AUDUSD.m",
      "Close": 0.70789,
      "Bid": 0.70789,
      "Ask": 0.70795,
      "Mid_Price": 0.70792,
      "Direction": "NEUTRAL",
      "Projected_Direction": "NEUTRAL",
      "Signal_Type": "NEUTRAL",
      "Setup_Maturity": 0.2469,
      "Projection_Score": 0.3325,
      "Projection_Price_Slope": -8.942857142858883e-05,
      "Regime": "RANGE",
      "Confidence": 0,
      "Optimizer_Mode": "DEFAULT",
      "Optimizer_Confidence_Floor": 60,
      "Optimizer_Max_Spread_Pips": 3.0,
      "Optimizer_Max_Slippage_Pips": 2.0,
      "Optimizer_Projection_Maturity_Floor": 0.55,
      "Optimizer_Projection_ZF_Floor": 0.45,
      "Optimizer_Projection_Confidence_Floor": 58,
      "Dynamic_Lot": 0.0,
      "Entry_Price": 0.70789,
      "SL_Pips": 7.3,
      "SL_Points": 73.0,
      "SL_Price": NaN,
      "SL_Model": "DATA_DRIVEN",
      "TP_Pips": 0.0,
      "TP_Points": 0.0,
      "TP_Price": NaN,
      "TP_Model": "NO_SIGNAL",
      "RR_Ratio": 0.0,
      "Spread_Pips": 0.5999999999994897,
      "Slippage_Est_Pips": 0.52,
      "Bid_Depth": 0.0,
      "Ask_Depth": 0.0,
      "Total_Depth": 0.0,
      "Depth_Imbalance": 0.0,
      "Depth_Available": false,
      "Liquidity_Cluster_Price": NaN,
      "Liquidity_Cluster_Volume": 0.0,
      "Liquidity_Stress": 0.5099999999998214,
      "Liquidity_Status": "LAMINAR",
      "Liquidity_Void": false,
      "Lambda_Liquidity": 0.6099999999998214,
      "Drift": 0.0408420402988129,
      "Decay_Integral": 0.000354426418912146,
      "Inflection_Detected": true,
      "ZF_Score": 0.5966889086792149,
      "Previous_Direction": "NEUTRAL",
      "Previous_Drift": 0.026919058344659783,
      "Previous_ZF_Score": 0.6087705624772337,
      "Previous_Lambda_Liquidity": 0.5749999999999807,
      "Previous_Liquidity_Status": "LAMINAR",
      "Delta_Drift": 0.013922981954153119,
      "Delta_ZF_Score": -0.012081653798018843,
      "Delta_Lambda": 0.0349999999998406,
      "Direction_Changed": false,
      "Liquidity_Status_Changed": false,
      "Memory_Status": "LAMINAR",
      "Risk_Mode": "NORMAL",
      "Trade_Allowed": false,
      "Action_Signal": "STANDBY",
      "Risk_Note": "",
      "Session_Phase": "LAMINAR",
      "User_Recommendation": "Tidak ada entry. Tunggu sinyal BUY/SELL berikutnya.",
      "Historical_Status": "AVOID",
      "Historical_Expectancy_R": -0.0318,
      "Historical_Win_Rate": 41.72,
      "Historical_Signals": 826,
      "Live_Expectancy_R": NaN,
      "Live_Signals": 0,
      "Market_Session": "NEW_YORK",
      "Accuracy_Quality_Score": 22.37,
      "Accuracy_Gate": "NEUTRAL",
      "Accuracy_Gate_Reason": "Belum ada arah BUY/SELL matang.",
      "Ranking_Score": 22.32054454339608
    },
    {
      "Symbol": "AUDJPY.m",
      "Close": 113.453,
      "Bid": 113.453,
      "Ask": 113.468,
      "Mid_Price": 113.4605,
      "Direction": "NEUTRAL",
      "Projected_Direction": "NEUTRAL",
      "Signal_Type": "NEUTRAL",
      "Setup_Maturity": 0.3159,
      "Projection_Score": 0.4058,
      "Projection_Price_Slope": 0.0024857142857151733,
      "Regime": "RANGE",
      "Confidence": 0,
      "Optimizer_Mode": "DEFAULT",
      "Optimizer_Confidence_Floor": 60,
      "Optimizer_Max_Spread_Pips": 3.0,
      "Optimizer_Max_Slippage_Pips": 2.0,
      "Optimizer_Projection_Maturity_Floor": 0.55,
      "Optimizer_Projection_ZF_Floor": 0.45,
      "Optimizer_Projection_Confidence_Floor": 58,
      "Dynamic_Lot": 0.0,
      "Entry_Price": 113.453,
      "SL_Pips": 10.7,
      "SL_Points": 107.0,
      "SL_Price": NaN,
      "SL_Model": "DATA_DRIVEN",
      "TP_Pips": 0.0,
      "TP_Points": 0.0,
      "TP_Price": NaN,
      "TP_Model": "NO_SIGNAL",
      "RR_Ratio": 0.0,
      "Spread_Pips": 1.5000000000000568,
      "Slippage_Est_Pips": 1.31,
      "Bid_Depth": 0.0,
      "Ask_Depth": 0.0,
      "Total_Depth": 0.0,
      "Depth_Imbalance": 0.0,
      "Depth_Available": false,
      "Liquidity_Cluster_Price": NaN,
      "Liquidity_Cluster_Volume": 0.0,
      "Liquidity_Stress": 0.8250000000000199,
      "Liquidity_Status": "STRESSED",
      "Liquidity_Void": false,
      "Lambda_Liquidity": 0.9250000000000199,
      "Drift": 0.011817247258755496,
      "Decay_Integral": -0.008820035227986665,
      "Inflection_Detected": true,
      "ZF_Score": 0.7164418417817764,
      "Previous_Direction": "NEUTRAL",
      "Previous_Drift": 0.007259762043143588,
      "Previous_ZF_Score": 0.6934760886296344,
      "Previous_Lambda_Liquidity": 0.7500000000001791,
      "Previous_Liquidity_Status": "LAMINAR",
      "Delta_Drift": 0.004557485215611908,
      "Delta_ZF_Score": 0.022965753152142,
      "Delta_Lambda": 0.17499999999984084,
      "Direction_Changed": false,
      "Liquidity_Status_Changed": true,
      "Memory_Status": "RESONANCE_MISMATCH",
      "Risk_Mode": "NORMAL",
      "Trade_Allowed": false,
      "Action_Signal": "WASPADA",
      "Risk_Note": "",
      "Session_Phase": "ANOMALOUS",
      "User_Recommendation": "Waspada. Ada tanda anomali, tetapi belum ada arah entry yang matang. Likuiditas: STRESSED.",
      "Historical_Status": "TRADEABLE",
      "Historical_Expectancy_R": 0.1164,
      "Historical_Win_Rate": 49.71,
      "Historical_Signals": 840,
      "Live_Expectancy_R": NaN,
      "Live_Signals": 0,
      "Market_Session": "NEW_YORK",
      "Accuracy_Quality_Score": 20.69,
      "Accuracy_Gate": "NEUTRAL",
      "Accuracy_Gate_Reason": "Belum ada arah BUY/SELL matang.",
      "Ranking_Score": 24.924109208908884
    },
    {
      "Symbol": "CHFJPY.m",
      "Close": 201.93,
      "Bid": 201.93,
      "Ask": 201.955,
      "Mid_Price": 201.9425,
      "Direction": "NEUTRAL",
      "Projected_Direction": "NEUTRAL",
      "Signal_Type": "NEUTRAL",
      "Setup_Maturity": 0.7821,
      "Projection_Score": 0.6917,
      "Projection_Price_Slope": 0.015400000000001163,
      "Regime": "RANGE",
      "Confidence": 0,
      "Optimizer_Mode": "DEFAULT",
      "Optimizer_Confidence_Floor": 60,
      "Optimizer_Max_Spread_Pips": 3.0,
      "Optimizer_Max_Slippage_Pips": 2.0,
      "Optimizer_Projection_Maturity_Floor": 0.55,
      "Optimizer_Projection_ZF_Floor": 0.45,
      "Optimizer_Projection_Confidence_Floor": 58,
      "Dynamic_Lot": 0.0,
      "Entry_Price": 201.93,
      "SL_Pips": 15.8,
      "SL_Points": 158.0,
      "SL_Price": NaN,
      "SL_Model": "DATA_DRIVEN",
      "TP_Pips": 0.0,
      "TP_Points": 0.0,
      "TP_Price": NaN,
      "TP_Model": "NO_SIGNAL",
      "RR_Ratio": 0.0,
      "Spread_Pips": 2.5000000000005684,
      "Slippage_Est_Pips": 2.19,
      "Bid_Depth": 0.0,
      "Ask_Depth": 0.0,
      "Total_Depth": 0.0,
      "Depth_Imbalance": 0.0,
      "Depth_Available": false,
      "Liquidity_Cluster_Price": NaN,
      "Liquidity_Cluster_Volume": 0.0,
      "Liquidity_Stress": 1.0,
      "Liquidity_Status": "STRESSED",
      "Liquidity_Void": false,
      "Lambda_Liquidity": 1.1,
      "Drift": 0.008252100174090471,
      "Decay_Integral": -0.3639378999007315,
      "Inflection_Detected": true,
      "ZF_Score": 0.729675479407552,
      "Previous_Direction": "BUY",
      "Previous_Drift": 0.011862022045144301,
      "Previous_ZF_Score": 0.6997938030239359,
      "Previous_Lambda_Liquidity": 0.9949999999998568,
      "Previous_Liquidity_Status": "STRESSED",
      "Delta_Drift": -0.00360992187105383,
      "Delta_ZF_Score": 0.02988167638361605,
      "Delta_Lambda": 0.10500000000014331,
      "Direction_Changed": true,
      "Liquidity_Status_Changed": false,
      "Memory_Status": "RESONANCE_MISMATCH",
      "Risk_Mode": "SLIPPAGE_LOCK",
      "Trade_Allowed": false,
      "Action_Signal": "TUNGGU SLIPPAGE",
      "Risk_Note": "Estimasi slippage melebihi batas.",
      "Session_Phase": "ANOMALOUS",
      "User_Recommendation": "Jangan entry. Risiko slippage terlalu besar.",
      "Historical_Status": "AVOID",
      "Historical_Expectancy_R": -0.1405,
      "Historical_Win_Rate": 36.11,
      "Historical_Signals": 838,
      "Live_Expectancy_R": NaN,
      "Live_Signals": 0,
      "Market_Session": "NEW_YORK",
      "Accuracy_Quality_Score": 14.04,
      "Accuracy_Gate": "NEUTRAL",
      "Accuracy_Gate_Reason": "Belum ada arah BUY/SELL matang.",
      "Ranking_Score": 25.64877739703776
    },
    {
      "Symbol": "EURAUD.m",
      "Close": 1.6386500000000002,
      "Bid": 1.6386500000000002,
      "Ask": 1.63876,
      "Mid_Price": 1.638705,
      "Direction": "NEUTRAL",
      "Projected_Direction": "NEUTRAL",
      "Signal_Type": "NEUTRAL",
      "Setup_Maturity": 0.2958,
      "Projection_Score": 0.3701,
      "Projection_Price_Slope": 0.0001682857142857641,
      "Regime": "RANGE",
      "Confidence": 0,
      "Optimizer_Mode": "LEARNING",
      "Optimizer_Confidence_Floor": 60,
      "Optimizer_Max_Spread_Pips": 3.0,
      "Optimizer_Max_Slippage_Pips": 2.0,
      "Optimizer_Projection_Maturity_Floor": 0.55,
      "Optimizer_Projection_ZF_Floor": 0.45,
      "Optimizer_Projection_Confidence_Floor": 58,
      "Dynamic_Lot": 0.0,
      "Entry_Price": 1.63865,
      "SL_Pips": 12.7,
      "SL_Points": 127.0,
      "SL_Price": NaN,
      "SL_Model": "DATA_DRIVEN",
      "TP_Pips": 0.0,
      "TP_Points": 0.0,
      "TP_Price": NaN,
      "TP_Model": "NO_SIGNAL",
      "RR_Ratio": 0.0,
      "Spread_Pips": 1.0999999999983243,
      "Slippage_Est_Pips": 0.96,
      "Bid_Depth": 0.0,
      "Ask_Depth": 0.0,
      "Total_Depth": 0.0,
      "Depth_Imbalance": 0.0,
      "Depth_Available": false,
      "Liquidity_Cluster_Price": NaN,
      "Liquidity_Cluster_Volume": 0.0,
      "Liquidity_Stress": 0.6849999999994134,
      "Liquidity_Status": "LAMINAR",
      "Liquidity_Void": false,
      "Lambda_Liquidity": 0.7849999999994134,
      "Drift": 0.02554535907775015,
      "Decay_Integral": -0.2322402224003995,
      "Inflection_Detected": true,
      "ZF_Score": 0.6330134996553818,
      "Previous_Direction": "NEUTRAL",
      "Previous_Drift": 0.0165885471819509,
      "Previous_ZF_Score": 0.6328508479255237,
      "Previous_Lambda_Liquidity": 0.68000000000028,
      "Previous_Liquidity_Status": "LAMINAR",
      "Delta_Drift": 0.00895681189579925,
      "Delta_ZF_Score": 0.00016265172985807652,
      "Delta_Lambda": 0.10499999999913334,
      "Direction_Changed": false,
      "Liquidity_Status_Changed": false,
      "Memory_Status": "LAMINAR",
      "Risk_Mode": "NORMAL",
      "Trade_Allowed": false,
      "Action_Signal": "STANDBY",
      "Risk_Note": "",
      "Session_Phase": "LAMINAR",
      "User_Recommendation": "Tidak ada entry. Tunggu sinyal BUY/SELL berikutnya.",
      "Historical_Status": "TRADEABLE",
      "Historical_Expectancy_R": 0.0397,
      "Historical_Win_Rate": 45.62,
      "Historical_Signals": 818,
      "Live_Expectancy_R": -1.0,
      "Live_Signals": 1,
      "Market_Session": "NEW_YORK",
      "Accuracy_Quality_Score": 16.17,
      "Accuracy_Gate": "NEUTRAL",
      "Accuracy_Gate_Reason": "Belum ada arah BUY/SELL matang.",
      "Ranking_Score": 20.758567498276907
    },
    {
      "Symbol": "EURCAD.m",
      "Close": 1.62182,
      "Bid": 1.62182,
      "Ask": 1.6219000000000001,
      "Mid_Price": 1.62186,
      "Direction": "NEUTRAL",
      "Projected_Direction": "NEUTRAL",
      "Signal_Type": "NEUTRAL",
      "Setup_Maturity": 0.6934,
      "Projection_Score": 0.606,
      "Projection_Price_Slope": -1.9428571428694423e-05,
      "Regime": "RANGE",
      "Confidence": 0,
      "Optimizer_Mode": "DEFAULT",
      "Optimizer_Confidence_Floor": 60,
      "Optimizer_Max_Spread_Pips": 3.0,
      "Optimizer_Max_Slippage_Pips": 2.0,
      "Optimizer_Projection_Maturity_Floor": 0.55,
      "Optimizer_Projection_ZF_Floor": 0.45,
      "Optimizer_Projection_Confidence_Floor": 58,
      "Dynamic_Lot": 0.0,
      "Entry_Price": 1.62182,
      "SL_Pips": 11.8,
      "SL_Points": 118.0,
      "SL_Price": NaN,
      "SL_Model": "DATA_DRIVEN",
      "TP_Pips": 0.0,
      "TP_Points": 0.0,
      "TP_Price": NaN,
      "TP_Model": "NO_SIGNAL",
      "RR_Ratio": 0.0,
      "Spread_Pips": 0.8000000000008001,
      "Slippage_Est_Pips": 0.7,
      "Bid_Depth": 0.0,
      "Ask_Depth": 0.0,
      "Total_Depth": 0.0,
      "Depth_Imbalance": 0.0,
      "Depth_Available": false,
      "Liquidity_Cluster_Price": NaN,
      "Liquidity_Cluster_Volume": 0.0,
      "Liquidity_Stress": 0.5800000000002801,
      "Liquidity_Status": "LAMINAR",
      "Liquidity_Void": false,
      "Lambda_Liquidity": 0.68000000000028,
      "Drift": 0.021433385565672692,
      "Decay_Integral": -0.08368580307373957,
      "Inflection_Detected": false,
      "ZF_Score": 0.6312000146226262,
      "Previous_Direction": "BUY",
      "Previous_Drift": 0.01724352635854631,
      "Previous_ZF_Score": 0.6528330658705792,
      "Previous_Lambda_Liquidity": 0.7150000000005093,
      "Previous_Liquidity_Status": "LAMINAR",
      "Delta_Drift": 0.004189859207126383,
      "Delta_ZF_Score": -0.021633051247953006,
      "Delta_Lambda": -0.03500000000022929,
      "Direction_Changed": true,
      "Liquidity_Status_Changed": false,
      "Memory_Status": "RESONANCE_MISMATCH",
      "Risk_Mode": "NORMAL",
      "Trade_Allowed": false,
      "Action_Signal": "WASPADA",
      "Risk_Note": "",
      "Session_Phase": "ANOMALOUS",
      "User_Recommendation": "Waspada. Ada tanda anomali, tetapi belum ada arah entry yang matang. Likuiditas: LAMINAR.",
      "Historical_Status": "AVOID",
      "Historical_Expectancy_R": -0.1581,
      "Historical_Win_Rate": 34.83,
      "Historical_Signals": 757,
      "Live_Expectancy_R": NaN,
      "Live_Signals": 0,
      "Market_Session": "NEW_YORK",
      "Accuracy_Quality_Score": 25.57,
      "Accuracy_Gate": "NEUTRAL",
      "Accuracy_Gate_Reason": "Belum ada arah BUY/SELL matang.",
      "Ranking_Score": 29.83550007311313
    },
    {
      "Symbol": "EURCHF.m",
      "Close": 0.92068,
      "Bid": 0.92068,
      "Ask": 0.92073,
      "Mid_Price": 0.9207050000000001,
      "Direction": "SELL",
      "Projected_Direction": "SELL",
      "Signal_Type": "PROJECTED",
      "Setup_Maturity": 0.7519,
      "Projection_Score": 0.6485,
      "Projection_Price_Slope": 5.0000000000092044e-05,
      "Regime": "RANGE",
      "Confidence": 72,
      "Optimizer_Mode": "DEFAULT",
      "Optimizer_Confidence_Floor": 60,
      "Optimizer_Max_Spread_Pips": 3.0,
      "Optimizer_Max_Slippage_Pips": 2.0,
      "Optimizer_Projection_Maturity_Floor": 0.55,
      "Optimizer_Projection_ZF_Floor": 0.45,
      "Optimizer_Projection_Confidence_Floor": 58,
      "Dynamic_Lot": 0.0,
      "Entry_Price": 0.92068,
      "SL_Pips": 5.5,
      "SL_Points": 55.0,
      "SL_Price": 0.92123,
      "SL_Model": "DATA_DRIVEN",
      "TP_Pips": 6.9,
      "TP_Points": 69.0,
      "TP_Price": 0.91999,
      "TP_Model": "DATA_DRIVEN",
      "RR_Ratio": 1.25,
      "Spread_Pips": 0.49999999999994493,
      "Slippage_Est_Pips": 0.44,
      "Bid_Depth": 0.0,
      "Ask_Depth": 0.0,
      "Total_Depth": 0.0,
      "Depth_Imbalance": 0.0,
      "Depth_Available": false,
      "Liquidity_Cluster_Price": NaN,
      "Liquidity_Cluster_Volume": 0.0,
      "Liquidity_Stress": 0.4749999999999807,
      "Liquidity_Status": "LAMINAR",
      "Liquidity_Void": false,
      "Lambda_Liquidity": 0.5749999999999807,
      "Drift": 0.006925795703981857,
      "Decay_Integral": 0.020029625617229083,
      "Inflection_Detected": true,
      "ZF_Score": 0.6554633860653818,
      "Previous_Direction": "NEUTRAL",
      "Previous_Drift": 0.021729806831657497,
      "Previous_ZF_Score": 0.5662662724699818,
      "Previous_Lambda_Liquidity": 0.6100000000002099,
      "Previous_Liquidity_Status": "LAMINAR",
      "Delta_Drift": -0.01480401112767564,
      "Delta_ZF_Score": 0.08919711359539995,
      "Delta_Lambda": -0.03500000000022918,
      "Direction_Changed": true,
      "Liquidity_Status_Changed": false,
      "Memory_Status": "RESONANCE_MISMATCH",
      "Risk_Mode": "PROFILE_LOCK",
      "Trade_Allowed": false,
      "Action_Signal": "WATCH HISTORIS",
      "Risk_Note": "Pair historis negatif/belum tervalidasi; tidak masuk TOP eksekusi.",
      "Session_Phase": "ANOMALOUS",
      "User_Recommendation": "Jangan entry. Pair ini belum lolos validasi historis.",
      "Historical_Status": "AVOID",
      "Historical_Expectancy_R": -0.0096,
      "Historical_Win_Rate": 43.14,
      "Historical_Signals": 801,
      "Live_Expectancy_R": NaN,
      "Live_Signals": 0,
      "Market_Session": "NEW_YORK",
      "Accuracy_Quality_Score": 52.75,
      "Accuracy_Gate": "WATCH",
      "Accuracy_Gate_Reason": "quality 52.8 < 62 | status historis AVOID | winrate historis 43.14% < 45.00% | expectancy historis -0.0096R < 0.0200R",
      "Ranking_Score": 60.65461693032692
    },
    {
      "Symbol": "EURGBP.m",
      "Close": 0.86384,
      "Bid": 0.86384,
      "Ask": 0.86389,
      "Mid_Price": 0.8638650000000001,
      "Direction": "NEUTRAL",
      "Projected_Direction": "NEUTRAL",
      "Signal_Type": "NEUTRAL",
      "Setup_Maturity": 0.4131,
      "Projection_Score": 0.4369,
      "Projection_Price_Slope": 6.228571428575284e-05,
      "Regime": "RANGE",
      "Confidence": 0,
      "Optimizer_Mode": "LEARNING",
      "Optimizer_Confidence_Floor": 60,
      "Optimizer_Max_Spread_Pips": 3.0,
      "Optimizer_Max_Slippage_Pips": 2.0,
      "Optimizer_Projection_Maturity_Floor": 0.55,
      "Optimizer_Projection_ZF_Floor": 0.45,
      "Optimizer_Projection_Confidence_Floor": 58,
      "Dynamic_Lot": 0.0,
      "Entry_Price": 0.86384,
      "SL_Pips": 5.5,
      "SL_Points": 55.0,
      "SL_Price": NaN,
      "SL_Model": "DATA_DRIVEN",
      "TP_Pips": 0.0,
      "TP_Points": 0.0,
      "TP_Price": NaN,
      "TP_Model": "NO_SIGNAL",
      "RR_Ratio": 0.0,
      "Spread_Pips": 0.49999999999994493,
      "Slippage_Est_Pips": 0.44,
      "Bid_Depth": 0.0,
      "Ask_Depth": 0.0,
      "Total_Depth": 0.0,
      "Depth_Imbalance": 0.0,
      "Depth_Available": false,
      "Liquidity_Cluster_Price": NaN,
      "Liquidity_Cluster_Volume": 0.0,
      "Liquidity_Stress": 0.4749999999999807,
      "Liquidity_Status": "LAMINAR",
      "Liquidity_Void": false,
      "Lambda_Liquidity": 0.5749999999999807,
      "Drift": 0.010340175088956363,
      "Decay_Integral": -0.04477490874726883,
      "Inflection_Detected": true,
      "ZF_Score": 0.6288162160636575,
      "Previous_Direction": "NEUTRAL",
      "Previous_Drift": 0.018424471537166653,
      "Previous_ZF_Score": 0.5934602594075791,
      "Previous_Lambda_Liquidity": 0.54000000000014,
      "Previous_Liquidity_Status": "LAMINAR",
      "Delta_Drift": -0.00808429644821029,
      "Delta_ZF_Score": 0.03535595665607838,
      "Delta_Lambda": 0.034999999999840714,
      "Direction_Changed": false,
      "Liquidity_Status_Changed": false,
      "Memory_Status": "LAMINAR",
      "Risk_Mode": "NORMAL",
      "Trade_Allowed": false,
      "Action_Signal": "STANDBY",
      "Risk_Note": "",
      "Session_Phase": "LAMINAR",
      "User_Recommendation": "Tidak ada entry. Tunggu sinyal BUY/SELL berikutnya.",
      "Historical_Status": "TRADEABLE",
      "Historical_Expectancy_R": 0.0461,
      "Historical_Win_Rate": 46.3,
      "Historical_Signals": 813,
      "Live_Expectancy_R": 0.125,
      "Live_Signals": 2,
      "Market_Session": "NEW_YORK",
      "Accuracy_Quality_Score": 29.99,
      "Accuracy_Gate": "NEUTRAL",
      "Accuracy_Gate_Reason": "Belum ada arah BUY/SELL matang.",
      "Ranking_Score": 30.32098108031829
    },
    {
      "Symbol": "EURJPY.m",
      "Close": 185.923,
      "Bid": 185.923,
      "Ask": 185.933,
      "Mid_Price": 185.928,
      "Direction": "NEUTRAL",
      "Projected_Direction": "NEUTRAL",
      "Signal_Type": "NEUTRAL",
      "Setup_Maturity": 0.7367,
      "Projection_Score": 0.6402,
      "Projection_Price_Slope": 0.02411428571428362,
      "Regime": "RANGE",
      "Confidence": 0,
      "Optimizer_Mode": "DEFAULT",
      "Optimizer_Confidence_Floor": 60,
      "Optimizer_Max_Spread_Pips": 3.0,
      "Optimizer_Max_Slippage_Pips": 2.0,
      "Optimizer_Projection_Maturity_Floor": 0.55,
      "Optimizer_Projection_ZF_Floor": 0.45,
      "Optimizer_Projection_Confidence_Floor": 58,
      "Dynamic_Lot": 0.0,
      "Entry_Price": 185.923,
      "SL_Pips": 11.5,
      "SL_Points": 115.0,
      "SL_Price": NaN,
      "SL_Model": "DATA_DRIVEN",
      "TP_Pips": 0.0,
      "TP_Points": 0.0,
      "TP_Price": NaN,
      "TP_Model": "NO_SIGNAL",
      "RR_Ratio": 0.0,
      "Spread_Pips": 0.9999999999990905,
      "Slippage_Est_Pips": 0.87,
      "Bid_Depth": 0.0,
      "Ask_Depth": 0.0,
      "Total_Depth": 0.0,
      "Depth_Imbalance": 0.0,
      "Depth_Available": false,
      "Liquidity_Cluster_Price": NaN,
      "Liquidity_Cluster_Volume": 0.0,
      "Liquidity_Stress": 0.6499999999996817,
      "Liquidity_Status": "LAMINAR",
      "Liquidity_Void": false,
      "Lambda_Liquidity": 0.7499999999996817,
      "Drift": 0.017087117787657726,
      "Decay_Integral": -0.19330061844566035,
      "Inflection_Detected": false,
      "ZF_Score": 0.6567570249912972,
      "Previous_Direction": "NEUTRAL",
      "Previous_Drift": 0.010875759209298048,
      "Previous_ZF_Score": 0.6708630480052455,
      "Previous_Lambda_Liquidity": 0.7150000000005093,
      "Previous_Liquidity_Status": "LAMINAR",
      "Delta_Drift": 0.006211358578359678,
      "Delta_ZF_Score": -0.014106023013948366,
      "Delta_Lambda": 0.03499999999917236,
      "Direction_Changed": false,
      "Liquidity_Status_Changed": false,
      "Memory_Status": "LAMINAR",
      "Risk_Mode": "NORMAL",
      "Trade_Allowed": false,
      "Action_Signal": "STANDBY",
      "Risk_Note": "",
      "Session_Phase": "LAMINAR",
      "User_Recommendation": "Tidak ada entry. Tunggu sinyal BUY/SELL berikutnya.",
      "Historical_Status": "WATCH_ONLY",
      "Historical_Expectancy_R": 0.0078,
      "Historical_Win_Rate": 43.87,
      "Historical_Signals": 772,
      "Live_Expectancy_R": NaN,
      "Live_Signals": 0,
      "Market_Session": "NEW_YORK",
      "Accuracy_Quality_Score": 29.25,
      "Accuracy_Gate": "NEUTRAL",
      "Accuracy_Gate_Reason": "Belum ada arah BUY/SELL matang.",
      "Ranking_Score": 34.73048512495649
    },
    {
      "Symbol": "EURUSD.m",
      "Close": 1.16007,
      "Bid": 1.16007,
      "Ask": 1.16009,
      "Mid_Price": 1.16008,
      "Direction": "NEUTRAL",
      "Projected_Direction": "NEUTRAL",
      "Signal_Type": "NEUTRAL",
      "Setup_Maturity": 0.6358,
      "Projection_Score": 0.5704,
      "Projection_Price_Slope": -2.314285714285458e-05,
      "Regime": "RANGE",
      "Confidence": 0,
      "Optimizer_Mode": "DEFAULT",
      "Optimizer_Confidence_Floor": 60,
      "Optimizer_Max_Spread_Pips": 3.0,
      "Optimizer_Max_Slippage_Pips": 2.0,
      "Optimizer_Projection_Maturity_Floor": 0.55,
      "Optimizer_Projection_ZF_Floor": 0.45,
      "Optimizer_Projection_Confidence_Floor": 58,
      "Dynamic_Lot": 0.0,
      "Entry_Price": 1.16007,
      "SL_Pips": 9.0,
      "SL_Points": 90.0,
      "SL_Price": NaN,
      "SL_Model": "DATA_DRIVEN",
      "TP_Pips": 0.0,
      "TP_Points": 0.0,
      "TP_Price": NaN,
      "TP_Model": "NO_SIGNAL",
      "RR_Ratio": 0.0,
      "Spread_Pips": 0.20000000000131024,
      "Slippage_Est_Pips": 0.18,
      "Bid_Depth": 0.0,
      "Ask_Depth": 0.0,
      "Total_Depth": 0.0,
      "Depth_Imbalance": 0.0,
      "Depth_Available": false,
      "Liquidity_Cluster_Price": NaN,
      "Liquidity_Cluster_Volume": 0.0,
      "Liquidity_Stress": 0.3700000000004586,
      "Liquidity_Status": "LAMINAR",
      "Liquidity_Void": false,
      "Lambda_Liquidity": 0.4700000000004586,
      "Drift": 0.012296204469216743,
      "Decay_Integral": -0.11376161945800467,
      "Inflection_Detected": true,
      "ZF_Score": 0.6205372151225153,
      "Previous_Direction": "NEUTRAL",
      "Previous_Drift": 0.008816444458083102,
      "Previous_ZF_Score": 0.6266192943550888,
      "Previous_Lambda_Liquidity": 0.46999999999968145,
      "Previous_Liquidity_Status": "LAMINAR",
      "Delta_Drift": 0.003479760011133641,
      "Delta_ZF_Score": -0.006082079232573534,
      "Delta_Lambda": 7.771561172376096e-13,
      "Direction_Changed": false,
      "Liquidity_Status_Changed": false,
      "Memory_Status": "LAMINAR",
      "Risk_Mode": "NORMAL",
      "Trade_Allowed": false,
      "Action_Signal": "STANDBY",
      "Risk_Note": "",
      "Session_Phase": "LAMINAR",
      "User_Recommendation": "Tidak ada entry. Tunggu sinyal BUY/SELL berikutnya.",
      "Historical_Status": "AVOID",
      "Historical_Expectancy_R": -0.0451,
      "Historical_Win_Rate": 41.05,
      "Historical_Signals": 802,
      "Live_Expectancy_R": NaN,
      "Live_Signals": 0,
      "Market_Session": "NEW_YORK",
      "Accuracy_Quality_Score": 32.47,
      "Accuracy_Gate": "NEUTRAL",
      "Accuracy_Gate_Reason": "Belum ada arah BUY/SELL matang.",
      "Ranking_Score": 34.05718607561258
    },
    {
      "Symbol": "GBPAUD.m",
      "Close": 1.8968500000000001,
      "Bid": 1.8968500000000001,
      "Ask": 1.89702,
      "Mid_Price": 1.896935,
      "Direction": "NEUTRAL",
      "Projected_Direction": "NEUTRAL",
      "Signal_Type": "NEUTRAL",
      "Setup_Maturity": 0.1445,
      "Projection_Score": 0.3035,
      "Projection_Price_Slope": 6.028571428575464e-05,
      "Regime": "RANGE",
      "Confidence": 0,
      "Optimizer_Mode": "DEFAULT",
      "Optimizer_Confidence_Floor": 60,
      "Optimizer_Max_Spread_Pips": 3.0,
      "Optimizer_Max_Slippage_Pips": 2.0,
      "Optimizer_Projection_Maturity_Floor": 0.55,
      "Optimizer_Projection_ZF_Floor": 0.45,
      "Optimizer_Projection_Confidence_Floor": 58,
      "Dynamic_Lot": 0.0,
      "Entry_Price": 1.89685,
      "SL_Pips": 13.5,
      "SL_Points": 135.0,
      "SL_Price": NaN,
      "SL_Model": "DATA_DRIVEN",
      "TP_Pips": 0.0,
      "TP_Points": 0.0,
      "TP_Price": NaN,
      "TP_Model": "NO_SIGNAL",
      "RR_Ratio": 0.0,
      "Spread_Pips": 1.6999999999978144,
      "Slippage_Est_Pips": 1.49,
      "Bid_Depth": 0.0,
      "Ask_Depth": 0.0,
      "Total_Depth": 0.0,
      "Depth_Imbalance": 0.0,
      "Depth_Available": false,
      "Liquidity_Cluster_Price": NaN,
      "Liquidity_Cluster_Volume": 0.0,
      "Liquidity_Stress": 0.8949999999992351,
      "Liquidity_Status": "STRESSED",
      "Liquidity_Void": false,
      "Lambda_Liquidity": 0.994999999999235,
      "Drift": 0.013715493809406294,
      "Decay_Integral": -0.2555380025679027,
      "Inflection_Detected": true,
      "ZF_Score": 0.7124114890368923,
      "Previous_Direction": "NEUTRAL",
      "Previous_Drift": 0.002801841357637412,
      "Previous_ZF_Score": 0.7075881129107872,
      "Previous_Lambda_Liquidity": 0.8550000000006491,
      "Previous_Liquidity_Status": "STRESSED",
      "Delta_Drift": 0.010913652451768882,
      "Delta_ZF_Score": 0.004823376126105172,
      "Delta_Lambda": 0.13999999999858592,
      "Direction_Changed": false,
      "Liquidity_Status_Changed": false,
      "Memory_Status": "LAMINAR",
      "Risk_Mode": "NORMAL",
      "Trade_Allowed": false,
      "Action_Signal": "STANDBY",
      "Risk_Note": "",
      "Session_Phase": "STRESSED",
      "User_Recommendation": "Tidak ada entry. Tunggu sinyal BUY/SELL berikutnya.",
      "Historical_Status": "WATCH_ONLY",
      "Historical_Expectancy_R": 0.0081,
      "Historical_Win_Rate": 43.83,
      "Historical_Signals": 802,
      "Live_Expectancy_R": NaN,
      "Live_Signals": 0,
      "Market_Session": "NEW_YORK",
      "Accuracy_Quality_Score": 13.02,
      "Accuracy_Gate": "NEUTRAL",
      "Accuracy_Gate_Reason": "Belum ada arah BUY/SELL matang.",
      "Ranking_Score": 16.60625744518446
    },
    {
      "Symbol": "GBPCHF.m",
      "Close": 1.06574,
      "Bid": 1.06574,
      "Ask": 1.06582,
      "Mid_Price": 1.06578,
      "Direction": "NEUTRAL",
      "Projected_Direction": "NEUTRAL",
      "Signal_Type": "NEUTRAL",
      "Setup_Maturity": 0.5427,
      "Projection_Score": 0.5388,
      "Projection_Price_Slope": -1.7428571428650247e-05,
      "Regime": "RANGE",
      "Confidence": 0,
      "Optimizer_Mode": "DEFAULT",
      "Optimizer_Confidence_Floor": 60,
      "Optimizer_Max_Spread_Pips": 3.0,
      "Optimizer_Max_Slippage_Pips": 2.0,
      "Optimizer_Projection_Maturity_Floor": 0.55,
      "Optimizer_Projection_ZF_Floor": 0.45,
      "Optimizer_Projection_Confidence_Floor": 58,
      "Dynamic_Lot": 0.0,
      "Entry_Price": 1.06574,
      "SL_Pips": 7.9,
      "SL_Points": 79.0,
      "SL_Price": NaN,
      "SL_Model": "DATA_DRIVEN",
      "TP_Pips": 0.0,
      "TP_Points": 0.0,
      "TP_Price": NaN,
      "TP_Model": "NO_SIGNAL",
      "RR_Ratio": 0.0,
      "Spread_Pips": 0.8000000000008001,
      "Slippage_Est_Pips": 0.7,
      "Bid_Depth": 0.0,
      "Ask_Depth": 0.0,
      "Total_Depth": 0.0,
      "Depth_Imbalance": 0.0,
      "Depth_Available": false,
      "Liquidity_Cluster_Price": NaN,
      "Liquidity_Cluster_Volume": 0.0,
      "Liquidity_Stress": 0.5800000000002801,
      "Liquidity_Status": "LAMINAR",
      "Liquidity_Void": false,
      "Lambda_Liquidity": 0.68000000000028,
      "Drift": 0.005402583671450417,
      "Decay_Integral": 0.051212748025351966,
      "Inflection_Detected": false,
      "ZF_Score": 0.7070252217950637,
      "Previous_Direction": "NEUTRAL",
      "Previous_Drift": 0.0034073410197296367,
      "Previous_ZF_Score": 0.7082235127977539,
      "Previous_Lambda_Liquidity": 0.6450000000000506,
      "Previous_Liquidity_Status": "LAMINAR",
      "Delta_Drift": 0.00199524265172078,
      "Delta_ZF_Score": -0.0011982910026901994,
      "Delta_Lambda": 0.0350000000002294,
      "Direction_Changed": false,
      "Liquidity_Status_Changed": false,
      "Memory_Status": "LAMINAR",
      "Risk_Mode": "NORMAL",
      "Trade_Allowed": false,
      "Action_Signal": "STANDBY",
      "Risk_Note": "",
      "Session_Phase": "LAMINAR",
      "User_Recommendation": "Tidak ada entry. Tunggu sinyal BUY/SELL berikutnya.",
      "Historical_Status": "AVOID",
      "Historical_Expectancy_R": -0.1003,
      "Historical_Win_Rate": 38.14,
      "Historical_Signals": 891,
      "Live_Expectancy_R": NaN,
      "Live_Signals": 0,
      "Market_Session": "NEW_YORK",
      "Accuracy_Quality_Score": 24.87,
      "Accuracy_Gate": "NEUTRAL",
      "Accuracy_Gate_Reason": "Belum ada arah BUY/SELL matang.",
      "Ranking_Score": 28.14562610897532
    },
    {
      "Symbol": "GBPJPY.m",
      "Close": 215.212,
      "Bid": 215.212,
      "Ask": 215.242,
      "Mid_Price": 215.22699999999998,
      "Direction": "NEUTRAL",
      "Projected_Direction": "NEUTRAL",
      "Signal_Type": "NEUTRAL",
      "Setup_Maturity": 0.4059,
      "Projection_Score": 0.4771,
      "Projection_Price_Slope": 0.012542857142844074,
      "Regime": "RANGE",
      "Confidence": 0,
      "Optimizer_Mode": "DEFAULT",
      "Optimizer_Confidence_Floor": 60,
      "Optimizer_Max_Spread_Pips": 3.0,
      "Optimizer_Max_Slippage_Pips": 2.0,
      "Optimizer_Projection_Maturity_Floor": 0.55,
      "Optimizer_Projection_ZF_Floor": 0.45,
      "Optimizer_Projection_Confidence_Floor": 58,
      "Dynamic_Lot": 0.0,
      "Entry_Price": 215.212,
      "SL_Pips": 16.1,
      "SL_Points": 161.0,
      "SL_Price": NaN,
      "SL_Model": "DATA_DRIVEN",
      "TP_Pips": 0.0,
      "TP_Points": 0.0,
      "TP_Price": NaN,
      "TP_Model": "NO_SIGNAL",
      "RR_Ratio": 0.0,
      "Spread_Pips": 3.0000000000001137,
      "Slippage_Est_Pips": 2.63,
      "Bid_Depth": 0.0,
      "Ask_Depth": 0.0,
      "Total_Depth": 0.0,
      "Depth_Imbalance": 0.0,
      "Depth_Available": false,
      "Liquidity_Cluster_Price": NaN,
      "Liquidity_Cluster_Volume": 0.0,
      "Liquidity_Stress": 1.0,
      "Liquidity_Status": "VOID",
      "Liquidity_Void": true,
      "Lambda_Liquidity": 1.1,
      "Drift": 0.003925402702085742,
      "Decay_Integral": -0.24423534129087582,
      "Inflection_Detected": true,
      "ZF_Score": 0.7738631578589075,
      "Previous_Direction": "NEUTRAL",
      "Previous_Drift": 0.00822389058686801,
      "Previous_ZF_Score": 0.7578581215736293,
      "Previous_Lambda_Liquidity": 1.0650000000001911,
      "Previous_Liquidity_Status": "STRESSED",
      "Delta_Drift": -0.004298487884782268,
      "Delta_ZF_Score": 0.016005036285278162,
      "Delta_Lambda": 0.03499999999980896,
      "Direction_Changed": false,
      "Liquidity_Status_Changed": true,
      "Memory_Status": "RESONANCE_MISMATCH",
      "Risk_Mode": "LIQUIDITY_LOCK",
      "Trade_Allowed": false,
      "Action_Signal": "PERTAHANAN LIKUIDITAS",
      "Risk_Note": "Liquidity void atau spread terlalu lebar.",
      "Session_Phase": "ANOMALOUS",
      "User_Recommendation": "Jangan entry. Likuiditas/spread sedang tidak sehat.",
      "Historical_Status": "AVOID",
      "Historical_Expectancy_R": -0.054,
      "Historical_Win_Rate": 40.56,
      "Historical_Signals": 816,
      "Live_Expectancy_R": NaN,
      "Live_Signals": 0,
      "Market_Session": "NEW_YORK",
      "Accuracy_Quality_Score": 5.57,
      "Accuracy_Gate": "NEUTRAL",
      "Accuracy_Gate_Reason": "Belum ada arah BUY/SELL matang.",
      "Ranking_Score": 16.24001578929454
    },
    {
      "Symbol": "GBPUSD.m",
      "Close": 1.34284,
      "Bid": 1.34284,
      "Ask": 1.34292,
      "Mid_Price": 1.34288,
      "Direction": "NEUTRAL",
      "Projected_Direction": "NEUTRAL",
      "Signal_Type": "NEUTRAL",
      "Setup_Maturity": 0.4089,
      "Projection_Score": 0.447,
      "Projection_Price_Slope": -0.00011971428571428989,
      "Regime": "RANGE",
      "Confidence": 0,
      "Optimizer_Mode": "DEFAULT",
      "Optimizer_Confidence_Floor": 60,
      "Optimizer_Max_Spread_Pips": 3.0,
      "Optimizer_Max_Slippage_Pips": 2.0,
      "Optimizer_Projection_Maturity_Floor": 0.55,
      "Optimizer_Projection_ZF_Floor": 0.45,
      "Optimizer_Projection_Confidence_Floor": 58,
      "Dynamic_Lot": 0.0,
      "Entry_Price": 1.34284,
      "SL_Pips": 11.7,
      "SL_Points": 117.0,
      "SL_Price": NaN,
      "SL_Model": "DATA_DRIVEN",
      "TP_Pips": 0.0,
      "TP_Points": 0.0,
      "TP_Price": NaN,
      "TP_Model": "NO_SIGNAL",
      "RR_Ratio": 0.0,
      "Spread_Pips": 0.7999999999985795,
      "Slippage_Est_Pips": 0.7,
      "Bid_Depth": 0.0,
      "Ask_Depth": 0.0,
      "Total_Depth": 0.0,
      "Depth_Imbalance": 0.0,
      "Depth_Available": false,
      "Liquidity_Cluster_Price": NaN,
      "Liquidity_Cluster_Volume": 0.0,
      "Liquidity_Stress": 0.5799999999995028,
      "Liquidity_Status": "LAMINAR",
      "Liquidity_Void": false,
      "Lambda_Liquidity": 0.6799999999995028,
      "Drift": 0.024623079748018764,
      "Decay_Integral": -0.15000860173039549,
      "Inflection_Detected": false,
      "ZF_Score": 0.6584636929909318,
      "Previous_Direction": "NEUTRAL",
      "Previous_Drift": 0.028285837113974897,
      "Previous_ZF_Score": 0.6432335817387658,
      "Previous_Lambda_Liquidity": 0.6450000000000506,
      "Previous_Liquidity_Status": "LAMINAR",
      "Delta_Drift": -0.0036627573659561326,
      "Delta_ZF_Score": 0.015230111252166001,
      "Delta_Lambda": 0.034999999999452136,
      "Direction_Changed": false,
      "Liquidity_Status_Changed": false,
      "Memory_Status": "LAMINAR",
      "Risk_Mode": "NORMAL",
      "Trade_Allowed": false,
      "Action_Signal": "STANDBY",
      "Risk_Note": "",
      "Session_Phase": "LAMINAR",
      "User_Recommendation": "Tidak ada entry. Tunggu sinyal BUY/SELL berikutnya.",
      "Historical_Status": "WATCH_ONLY",
      "Historical_Expectancy_R": 0.0098,
      "Historical_Win_Rate": 44.12,
      "Historical_Signals": 814,
      "Live_Expectancy_R": NaN,
      "Live_Signals": 0,
      "Market_Session": "NEW_YORK",
      "Accuracy_Quality_Score": 25.09,
      "Accuracy_Gate": "NEUTRAL",
      "Accuracy_Gate_Reason": "Belum ada arah BUY/SELL matang.",
      "Ranking_Score": 27.242218464954657
    },
    {
      "Symbol": "NZDUSD.m",
      "Close": 0.583,
      "Bid": 0.583,
      "Ask": 0.58307,
      "Mid_Price": 0.583035,
      "Direction": "NEUTRAL",
      "Projected_Direction": "NEUTRAL",
      "Signal_Type": "NEUTRAL",
      "Setup_Maturity": 0.6592,
      "Projection_Score": 0.5851,
      "Projection_Price_Slope": -0.00016571428571429163,
      "Regime": "RANGE",
      "Confidence": 0,
      "Optimizer_Mode": "DEFAULT",
      "Optimizer_Confidence_Floor": 60,
      "Optimizer_Max_Spread_Pips": 3.0,
      "Optimizer_Max_Slippage_Pips": 2.0,
      "Optimizer_Projection_Maturity_Floor": 0.55,
      "Optimizer_Projection_ZF_Floor": 0.45,
      "Optimizer_Projection_Confidence_Floor": 58,
      "Dynamic_Lot": 0.0,
      "Entry_Price": 0.583,
      "SL_Pips": 6.5,
      "SL_Points": 65.0,
      "SL_Price": NaN,
      "SL_Model": "DATA_DRIVEN",
      "TP_Pips": 0.0,
      "TP_Points": 0.0,
      "TP_Price": NaN,
      "TP_Model": "NO_SIGNAL",
      "RR_Ratio": 0.0,
      "Spread_Pips": 0.7000000000001448,
      "Slippage_Est_Pips": 0.61,
      "Bid_Depth": 0.0,
      "Ask_Depth": 0.0,
      "Total_Depth": 0.0,
      "Depth_Imbalance": 0.0,
      "Depth_Available": false,
      "Liquidity_Cluster_Price": NaN,
      "Liquidity_Cluster_Volume": 0.0,
      "Liquidity_Stress": 0.5450000000000507,
      "Liquidity_Status": "LAMINAR",
      "Liquidity_Void": false,
      "Lambda_Liquidity": 0.6450000000000506,
      "Drift": 0.03895669787779086,
      "Decay_Integral": -0.44993550126852416,
      "Inflection_Detected": false,
      "ZF_Score": 0.6210622262451009,
      "Previous_Direction": "NEUTRAL",
      "Previous_Drift": 0.04418749334105611,
      "Previous_ZF_Score": 0.6051810702413991,
      "Previous_Lambda_Liquidity": 0.6100000000002099,
      "Previous_Liquidity_Status": "LAMINAR",
      "Delta_Drift": -0.005230795463265249,
      "Delta_ZF_Score": 0.01588115600370177,
      "Delta_Lambda": 0.034999999999840714,
      "Direction_Changed": false,
      "Liquidity_Status_Changed": false,
      "Memory_Status": "LAMINAR",
      "Risk_Mode": "NORMAL",
      "Trade_Allowed": false,
      "Action_Signal": "STANDBY",
      "Risk_Note": "",
      "Session_Phase": "LAMINAR",
      "User_Recommendation": "Tidak ada entry. Tunggu sinyal BUY/SELL berikutnya.",
      "Historical_Status": "AVOID",
      "Historical_Expectancy_R": -0.0892,
      "Historical_Win_Rate": 38.68,
      "Historical_Signals": 776,
      "Live_Expectancy_R": NaN,
      "Live_Signals": 0,
      "Market_Session": "NEW_YORK",
      "Accuracy_Quality_Score": 27.59,
      "Accuracy_Gate": "NEUTRAL",
      "Accuracy_Gate_Reason": "Belum ada arah BUY/SELL matang.",
      "Ranking_Score": 31.207811131225508
    },
    {
      "Symbol": "USDCAD.m",
      "Close": 1.3981,
      "Bid": 1.3981,
      "Ask": 1.39819,
      "Mid_Price": 1.398145,
      "Direction": "NEUTRAL",
      "Projected_Direction": "NEUTRAL",
      "Signal_Type": "NEUTRAL",
      "Setup_Maturity": 0.2631,
      "Projection_Score": 0.3667,
      "Projection_Price_Slope": 1.0857142857156685e-05,
      "Regime": "RANGE",
      "Confidence": 0,
      "Optimizer_Mode": "DEFAULT",
      "Optimizer_Confidence_Floor": 60,
      "Optimizer_Max_Spread_Pips": 3.0,
      "Optimizer_Max_Slippage_Pips": 2.0,
      "Optimizer_Projection_Maturity_Floor": 0.55,
      "Optimizer_Projection_ZF_Floor": 0.45,
      "Optimizer_Projection_Confidence_Floor": 58,
      "Dynamic_Lot": 0.0,
      "Entry_Price": 1.3981,
      "SL_Pips": 10.7,
      "SL_Points": 107.0,
      "SL_Price": NaN,
      "SL_Model": "DATA_DRIVEN",
      "TP_Pips": 0.0,
      "TP_Points": 0.0,
      "TP_Price": NaN,
      "TP_Model": "NO_SIGNAL",
      "RR_Ratio": 0.0,
      "Spread_Pips": 0.9000000000014552,
      "Slippage_Est_Pips": 0.79,
      "Bid_Depth": 0.0,
      "Ask_Depth": 0.0,
      "Total_Depth": 0.0,
      "Depth_Imbalance": 0.0,
      "Depth_Available": false,
      "Liquidity_Cluster_Price": NaN,
      "Liquidity_Cluster_Volume": 0.0,
      "Liquidity_Stress": 0.6150000000005094,
      "Liquidity_Status": "LAMINAR",
      "Liquidity_Void": false,
      "Lambda_Liquidity": 0.7150000000005093,
      "Drift": 0.00963953514388122,
      "Decay_Integral": 0.07930254851344384,
      "Inflection_Detected": true,
      "ZF_Score": 0.6843274277871448,
      "Previous_Direction": "NEUTRAL",
      "Previous_Drift": 0.008429556893118747,
      "Previous_ZF_Score": 0.6975234653484286,
      "Previous_Lambda_Liquidity": 0.7499999999999615,
      "Previous_Liquidity_Status": "LAMINAR",
      "Delta_Drift": 0.0012099782507624737,
      "Delta_ZF_Score": -0.013196037561283736,
      "Delta_Lambda": -0.034999999999452136,
      "Direction_Changed": false,
      "Liquidity_Status_Changed": false,
      "Memory_Status": "LAMINAR",
      "Risk_Mode": "NORMAL",
      "Trade_Allowed": false,
      "Action_Signal": "STANDBY",
      "Risk_Note": "",
      "Session_Phase": "LAMINAR",
      "User_Recommendation": "Tidak ada entry. Tunggu sinyal BUY/SELL berikutnya.",
      "Historical_Status": "AVOID",
      "Historical_Expectancy_R": -0.0203,
      "Historical_Win_Rate": 42.24,
      "Historical_Signals": 816,
      "Live_Expectancy_R": NaN,
      "Live_Signals": 0,
      "Market_Session": "NEW_YORK",
      "Accuracy_Quality_Score": 20.92,
      "Accuracy_Gate": "NEUTRAL",
      "Accuracy_Gate_Reason": "Belum ada arah BUY/SELL matang.",
      "Ranking_Score": 22.354037138935727
    },
    {
      "Symbol": "USDCHF.m",
      "Close": 0.79362,
      "Bid": 0.79362,
      "Ask": 0.79369,
      "Mid_Price": 0.793655,
      "Direction": "NEUTRAL",
      "Projected_Direction": "NEUTRAL",
      "Signal_Type": "NEUTRAL",
      "Setup_Maturity": 0.6932,
      "Projection_Score": 0.6112,
      "Projection_Price_Slope": 5.971428571426881e-05,
      "Regime": "RANGE",
      "Confidence": 0,
      "Optimizer_Mode": "DEFAULT",
      "Optimizer_Confidence_Floor": 60,
      "Optimizer_Max_Spread_Pips": 3.0,
      "Optimizer_Max_Slippage_Pips": 2.0,
      "Optimizer_Projection_Maturity_Floor": 0.55,
      "Optimizer_Projection_ZF_Floor": 0.45,
      "Optimizer_Projection_Confidence_Floor": 58,
      "Dynamic_Lot": 0.0,
      "Entry_Price": 0.79362,
      "SL_Pips": 7.3,
      "SL_Points": 73.0,
      "SL_Price": NaN,
      "SL_Model": "DATA_DRIVEN",
      "TP_Pips": 0.0,
      "TP_Points": 0.0,
      "TP_Price": NaN,
      "TP_Model": "NO_SIGNAL",
      "RR_Ratio": 0.0,
      "Spread_Pips": 0.7000000000001448,
      "Slippage_Est_Pips": 0.61,
      "Bid_Depth": 0.0,
      "Ask_Depth": 0.0,
      "Total_Depth": 0.0,
      "Depth_Imbalance": 0.0,
      "Depth_Available": false,
      "Liquidity_Cluster_Price": NaN,
      "Liquidity_Cluster_Volume": 0.0,
      "Liquidity_Stress": 0.5450000000000507,
      "Liquidity_Status": "LAMINAR",
      "Liquidity_Void": false,
      "Lambda_Liquidity": 0.6450000000000506,
      "Drift": 0.01841904469643692,
      "Decay_Integral": 0.16206037243644686,
      "Inflection_Detected": false,
      "ZF_Score": 0.6406510638620324,
      "Previous_Direction": "NEUTRAL",
      "Previous_Drift": 0.030702859798937724,
      "Previous_ZF_Score": 0.6154761078219821,
      "Previous_Lambda_Liquidity": 0.6450000000000506,
      "Previous_Liquidity_Status": "LAMINAR",
      "Delta_Drift": -0.012283815102500803,
      "Delta_ZF_Score": 0.025174956040050267,
      "Delta_Lambda": 0.0,
      "Direction_Changed": false,
      "Liquidity_Status_Changed": false,
      "Memory_Status": "LAMINAR",
      "Risk_Mode": "NORMAL",
      "Trade_Allowed": false,
      "Action_Signal": "STANDBY",
      "Risk_Note": "",
      "Session_Phase": "LAMINAR",
      "User_Recommendation": "Tidak ada entry. Tunggu sinyal BUY/SELL berikutnya.",
      "Historical_Status": "AVOID",
      "Historical_Expectancy_R": -0.0759,
      "Historical_Win_Rate": 39.23,
      "Historical_Signals": 811,
      "Live_Expectancy_R": NaN,
      "Live_Signals": 0,
      "Market_Session": "NEW_YORK",
      "Accuracy_Quality_Score": 28.63,
      "Accuracy_Gate": "NEUTRAL",
      "Accuracy_Gate_Reason": "Belum ada arah BUY/SELL matang.",
      "Ranking_Score": 32.57215531931016
    },
    {
      "Symbol": "USDJPY.m",
      "Close": 160.267,
      "Bid": 160.267,
      "Ask": 160.279,
      "Mid_Price": 160.273,
      "Direction": "NEUTRAL",
      "Projected_Direction": "NEUTRAL",
      "Signal_Type": "NEUTRAL",
      "Setup_Maturity": 0.0183,
      "Projection_Score": 0.2054,
      "Projection_Price_Slope": 0.0236285714285685,
      "Regime": "TREND",
      "Confidence": 0,
      "Optimizer_Mode": "DEFAULT",
      "Optimizer_Confidence_Floor": 60,
      "Optimizer_Max_Spread_Pips": 3.0,
      "Optimizer_Max_Slippage_Pips": 2.0,
      "Optimizer_Projection_Maturity_Floor": 0.55,
      "Optimizer_Projection_ZF_Floor": 0.45,
      "Optimizer_Projection_Confidence_Floor": 58,
      "Dynamic_Lot": 0.0,
      "Entry_Price": 160.267,
      "SL_Pips": 11.5,
      "SL_Points": 115.0,
      "SL_Price": NaN,
      "SL_Model": "DATA_DRIVEN",
      "TP_Pips": 0.0,
      "TP_Points": 0.0,
      "TP_Price": NaN,
      "TP_Model": "NO_SIGNAL",
      "RR_Ratio": 0.0,
      "Spread_Pips": 1.2000000000000455,
      "Slippage_Est_Pips": 1.05,
      "Bid_Depth": 0.0,
      "Ask_Depth": 0.0,
      "Total_Depth": 0.0,
      "Depth_Imbalance": 0.0,
      "Depth_Available": false,
      "Liquidity_Cluster_Price": NaN,
      "Liquidity_Cluster_Volume": 0.0,
      "Liquidity_Stress": 0.720000000000016,
      "Liquidity_Status": "LAMINAR",
      "Liquidity_Void": false,
      "Lambda_Liquidity": 0.8200000000000159,
      "Drift": 0.02847457955324337,
      "Decay_Integral": -0.020984521086527187,
      "Inflection_Detected": true,
      "ZF_Score": 0.6278158608433267,
      "Previous_Direction": "NEUTRAL",
      "Previous_Drift": 0.0201900249727657,
      "Previous_ZF_Score": 0.5979733080988991,
      "Previous_Lambda_Liquidity": 0.5749999999998409,
      "Previous_Liquidity_Status": "LAMINAR",
      "Delta_Drift": 0.008284554580477672,
      "Delta_ZF_Score": 0.029842552744427597,
      "Delta_Lambda": 0.24500000000017508,
      "Direction_Changed": false,
      "Liquidity_Status_Changed": false,
      "Memory_Status": "LAMINAR",
      "Risk_Mode": "NORMAL",
      "Trade_Allowed": false,
      "Action_Signal": "STANDBY",
      "Risk_Note": "",
      "Session_Phase": "LAMINAR",
      "User_Recommendation": "Tidak ada entry. Tunggu sinyal BUY/SELL berikutnya.",
      "Historical_Status": "AVOID",
      "Historical_Expectancy_R": -0.0504,
      "Historical_Win_Rate": 40.86,
      "Historical_Signals": 889,
      "Live_Expectancy_R": NaN,
      "Live_Signals": 0,
      "Market_Session": "NEW_YORK",
      "Accuracy_Quality_Score": 12.93,
      "Accuracy_Gate": "NEUTRAL",
      "Accuracy_Gate_Reason": "Belum ada arah BUY/SELL matang.",
      "Ranking_Score": 13.408979304216633
    },
    {
      "Symbol": "AUDCAD.m",
      "Close": 0.98969,
      "Bid": 0.98969,
      "Ask": 0.98977,
      "Mid_Price": 0.98973,
      "Direction": "NEUTRAL",
      "Projected_Direction": "NEUTRAL",
      "Signal_Type": "NEUTRAL",
      "Setup_Maturity": 0.176,
      "Projection_Score": 0.279,
      "Projection_Price_Slope": -0.00011657142857152875,
      "Regime": "RANGE",
      "Confidence": 0,
      "Optimizer_Mode": "DEFAULT",
      "Optimizer_Confidence_Floor": 60,
      "Optimizer_Max_Spread_Pips": 3.0,
      "Optimizer_Max_Slippage_Pips": 2.0,
      "Optimizer_Projection_Maturity_Floor": 0.55,
      "Optimizer_Projection_ZF_Floor": 0.45,
      "Optimizer_Projection_Confidence_Floor": 58,
      "Dynamic_Lot": 0.0,
      "Entry_Price": 0.98969,
      "SL_Pips": 7.9,
      "SL_Points": 79.0,
      "SL_Price": NaN,
      "SL_Model": "DATA_DRIVEN",
      "TP_Pips": 0.0,
      "TP_Points": 0.0,
      "TP_Price": NaN,
      "TP_Model": "NO_SIGNAL",
      "RR_Ratio": 0.0,
      "Spread_Pips": 0.8000000000008001,
      "Slippage_Est_Pips": 0.7,
      "Bid_Depth": 0.0,
      "Ask_Depth": 0.0,
      "Total_Depth": 0.0,
      "Depth_Imbalance": 0.0,
      "Depth_Available": false,
      "Liquidity_Cluster_Price": NaN,
      "Liquidity_Cluster_Volume": 0.0,
      "Liquidity_Stress": 0.5800000000002801,
      "Liquidity_Status": "LAMINAR",
      "Liquidity_Void": false,
      "Lambda_Liquidity": 0.68000000000028,
      "Drift": 0.049192057715029325,
      "Decay_Integral": 0.08447156103096118,
      "Inflection_Detected": false,
      "ZF_Score": 0.5692555778148385,
      "Previous_Direction": "NEUTRAL",
      "Previous_Drift": 0.03440786976810752,
      "Previous_ZF_Score": 0.5956817959913921,
      "Previous_Lambda_Liquidity": 0.68000000000028,
      "Previous_Liquidity_Status": "LAMINAR",
      "Delta_Drift": 0.014784187946921802,
      "Delta_ZF_Score": -0.026426218176553662,
      "Delta_Lambda": 0.0,
      "Direction_Changed": false,
      "Liquidity_Status_Changed": false,
      "Memory_Status": "LAMINAR",
      "Risk_Mode": "NORMAL",
      "Trade_Allowed": false,
      "Action_Signal": "STANDBY",
      "Risk_Note": "",
      "Session_Phase": "LAMINAR",
      "User_Recommendation": "Tidak ada entry. Tunggu sinyal BUY/SELL berikutnya.",
      "Historical_Status": "TRADEABLE",
      "Historical_Expectancy_R": 0.0449,
      "Historical_Win_Rate": 46.02,
      "Historical_Signals": 750,
      "Live_Expectancy_R": NaN,
      "Live_Signals": 0,
      "Market_Session": "NEW_YORK",
      "Accuracy_Quality_Score": 21.29,
      "Accuracy_Gate": "NEUTRAL",
      "Accuracy_Gate_Reason": "Belum ada arah BUY/SELL matang.",
      "Ranking_Score": 21.412577889074193
    },
    {
      "Symbol": "AUDCHF.m",
      "Close": 0.56181,
      "Bid": 0.56181,
      "Ask": 0.56188,
      "Mid_Price": 0.561845,
      "Direction": "NEUTRAL",
      "Projected_Direction": "NEUTRAL",
      "Signal_Type": "NEUTRAL",
      "Setup_Maturity": 0.4192,
      "Projection_Score": 0.4405,
      "Projection_Price_Slope": -2.914285714285882e-05,
      "Regime": "RANGE",
      "Confidence": 0,
      "Optimizer_Mode": "DEFAULT",
      "Optimizer_Confidence_Floor": 60,
      "Optimizer_Max_Spread_Pips": 3.0,
      "Optimizer_Max_Slippage_Pips": 2.0,
      "Optimizer_Projection_Maturity_Floor": 0.55,
      "Optimizer_Projection_ZF_Floor": 0.45,
      "Optimizer_Projection_Confidence_Floor": 58,
      "Dynamic_Lot": 0.0,
      "Entry_Price": 0.56181,
      "SL_Pips": 6.5,
      "SL_Points": 65.0,
      "SL_Price": NaN,
      "SL_Model": "DATA_DRIVEN",
      "TP_Pips": 0.0,
      "TP_Points": 0.0,
      "TP_Price": NaN,
      "TP_Model": "NO_SIGNAL",
      "RR_Ratio": 0.0,
      "Spread_Pips": 0.7000000000001448,
      "Slippage_Est_Pips": 0.61,
      "Bid_Depth": 0.0,
      "Ask_Depth": 0.0,
      "Total_Depth": 0.0,
      "Depth_Imbalance": 0.0,
      "Depth_Available": false,
      "Liquidity_Cluster_Price": NaN,
      "Liquidity_Cluster_Volume": 0.0,
      "Liquidity_Stress": 0.5450000000000507,
      "Liquidity_Status": "LAMINAR",
      "Liquidity_Void": false,
      "Lambda_Liquidity": 0.6450000000000506,
      "Drift": 0.021662072981599254,
      "Decay_Integral": 0.16826449519988074,
      "Inflection_Detected": true,
      "ZF_Score": 0.6212275300357044,
      "Previous_Direction": "NEUTRAL",
      "Previous_Drift": 0.0037174745790616226,
      "Previous_ZF_Score": 0.6678866587364465,
      "Previous_Lambda_Liquidity": 0.6449999999996621,
      "Previous_Liquidity_Status": "LAMINAR",
      "Delta_Drift": 0.01794459840253763,
      "Delta_ZF_Score": -0.04665912870074207,
      "Delta_Lambda": 3.885780586188048e-13,
      "Direction_Changed": false,
      "Liquidity_Status_Changed": false,
      "Memory_Status": "LAMINAR",
      "Risk_Mode": "NORMAL",
      "Trade_Allowed": false,
      "Action_Signal": "STANDBY",
      "Risk_Note": "",
      "Session_Phase": "LAMINAR",
      "User_Recommendation": "Tidak ada entry. Tunggu sinyal BUY/SELL berikutnya.",
      "Historical_Status": "AVOID",
      "Historical_Expectancy_R": -0.0519,
      "Historical_Win_Rate": 41.07,
      "Historical_Signals": 757,
      "Live_Expectancy_R": NaN,
      "Live_Signals": 0,
      "Market_Session": "NEW_YORK",
      "Accuracy_Quality_Score": 24.33,
      "Accuracy_Gate": "NEUTRAL",
      "Accuracy_Gate_Reason": "Belum ada arah BUY/SELL matang.",
      "Ranking_Score": 26.065237650178524
    },
    {
      "Symbol": "EURNZD.m",
      "Close": 1.9896500000000001,
      "Bid": 1.9896500000000001,
      "Ask": 1.9898,
      "Mid_Price": 1.989725,
      "Direction": "NEUTRAL",
      "Projected_Direction": "NEUTRAL",
      "Signal_Type": "NEUTRAL",
      "Setup_Maturity": 0.3537,
      "Projection_Score": 0.4123,
      "Projection_Price_Slope": 0.0005248571428570534,
      "Regime": "RANGE",
      "Confidence": 0,
      "Optimizer_Mode": "DEFAULT",
      "Optimizer_Confidence_Floor": 60,
      "Optimizer_Max_Spread_Pips": 3.0,
      "Optimizer_Max_Slippage_Pips": 2.0,
      "Optimizer_Projection_Maturity_Floor": 0.55,
      "Optimizer_Projection_ZF_Floor": 0.45,
      "Optimizer_Projection_Confidence_Floor": 58,
      "Dynamic_Lot": 0.0,
      "Entry_Price": 1.98965,
      "SL_Pips": 14.1,
      "SL_Points": 141.0,
      "SL_Price": NaN,
      "SL_Model": "DATA_DRIVEN",
      "TP_Pips": 0.0,
      "TP_Points": 0.0,
      "TP_Price": NaN,
      "TP_Model": "NO_SIGNAL",
      "RR_Ratio": 0.0,
      "Spread_Pips": 1.4999999999987244,
      "Slippage_Est_Pips": 1.31,
      "Bid_Depth": 0.0,
      "Ask_Depth": 0.0,
      "Total_Depth": 0.0,
      "Depth_Imbalance": 0.0,
      "Depth_Available": false,
      "Liquidity_Cluster_Price": NaN,
      "Liquidity_Cluster_Volume": 0.0,
      "Liquidity_Stress": 0.8249999999995534,
      "Liquidity_Status": "STRESSED",
      "Liquidity_Void": false,
      "Lambda_Liquidity": 0.9249999999995534,
      "Drift": 0.021836595523784592,
      "Decay_Integral": 0.32812016886342016,
      "Inflection_Detected": false,
      "ZF_Score": 0.6658754822601686,
      "Previous_Direction": "NEUTRAL",
      "Previous_Drift": 0.03160181948417464,
      "Previous_ZF_Score": 0.6180888387808201,
      "Previous_Lambda_Liquidity": 0.8900000000001013,
      "Previous_Liquidity_Status": "STRESSED",
      "Delta_Drift": -0.009765223960390049,
      "Delta_ZF_Score": 0.04778664347934847,
      "Delta_Lambda": 0.034999999999452136,
      "Direction_Changed": false,
      "Liquidity_Status_Changed": false,
      "Memory_Status": "LAMINAR",
      "Risk_Mode": "NORMAL",
      "Trade_Allowed": false,
      "Action_Signal": "STANDBY",
      "Risk_Note": "",
      "Session_Phase": "STRESSED",
      "User_Recommendation": "Tidak ada entry. Tunggu sinyal BUY/SELL berikutnya.",
      "Historical_Status": "WATCH_ONLY",
      "Historical_Expectancy_R": 0.0244,
      "Historical_Win_Rate": 44.84,
      "Historical_Signals": 845,
      "Live_Expectancy_R": NaN,
      "Live_Signals": 0,
      "Market_Session": "NEW_YORK",
      "Accuracy_Quality_Score": 18.66,
      "Accuracy_Gate": "NEUTRAL",
      "Accuracy_Gate_Reason": "Belum ada arah BUY/SELL matang.",
      "Ranking_Score": 23.033977411300846
    },
    {
      "Symbol": "GBPCAD.m",
      "Close": 1.87741,
      "Bid": 1.87741,
      "Ask": 1.8774899999999999,
      "Mid_Price": 1.87745,
      "Direction": "NEUTRAL",
      "Projected_Direction": "NEUTRAL",
      "Signal_Type": "NEUTRAL",
      "Setup_Maturity": 0.3804,
      "Projection_Score": 0.4134,
      "Projection_Price_Slope": -0.00015600000000008635,
      "Regime": "RANGE",
      "Confidence": 0,
      "Optimizer_Mode": "DEFAULT",
      "Optimizer_Confidence_Floor": 60,
      "Optimizer_Max_Spread_Pips": 3.0,
      "Optimizer_Max_Slippage_Pips": 2.0,
      "Optimizer_Projection_Maturity_Floor": 0.55,
      "Optimizer_Projection_ZF_Floor": 0.45,
      "Optimizer_Projection_Confidence_Floor": 58,
      "Dynamic_Lot": 0.0,
      "Entry_Price": 1.87741,
      "SL_Pips": 15.2,
      "SL_Points": 152.0,
      "SL_Price": NaN,
      "SL_Model": "DATA_DRIVEN",
      "TP_Pips": 0.0,
      "TP_Points": 0.0,
      "TP_Price": NaN,
      "TP_Model": "NO_SIGNAL",
      "RR_Ratio": 0.0,
      "Spread_Pips": 0.7999999999985795,
      "Slippage_Est_Pips": 0.7,
      "Bid_Depth": 0.0,
      "Ask_Depth": 0.0,
      "Total_Depth": 0.0,
      "Depth_Imbalance": 0.0,
      "Depth_Available": false,
      "Liquidity_Cluster_Price": NaN,
      "Liquidity_Cluster_Volume": 0.0,
      "Liquidity_Stress": 0.5799999999995028,
      "Liquidity_Status": "LAMINAR",
      "Liquidity_Void": false,
      "Lambda_Liquidity": 0.6799999999995028,
      "Drift": 0.032895066405613155,
      "Decay_Integral": -0.055369763853276424,
      "Inflection_Detected": false,
      "ZF_Score": 0.6142991289561267,
      "Previous_Direction": "NEUTRAL",
      "Previous_Drift": 0.03537940104511075,
      "Previous_ZF_Score": 0.6125769823084307,
      "Previous_Lambda_Liquidity": 0.7149999999997322,
      "Previous_Liquidity_Status": "LAMINAR",
      "Delta_Drift": -0.0024843346394975985,
      "Delta_ZF_Score": 0.001722146647695988,
      "Delta_Lambda": -0.0350000000002294,
      "Direction_Changed": false,
      "Liquidity_Status_Changed": false,
      "Memory_Status": "LAMINAR",
      "Risk_Mode": "NORMAL",
      "Trade_Allowed": false,
      "Action_Signal": "STANDBY",
      "Risk_Note": "",
      "Session_Phase": "LAMINAR",
      "User_Recommendation": "Tidak ada entry. Tunggu sinyal BUY/SELL berikutnya.",
      "Historical_Status": "AVOID",
      "Historical_Expectancy_R": -0.157,
      "Historical_Win_Rate": 34.78,
      "Historical_Signals": 794,
      "Live_Expectancy_R": NaN,
      "Live_Signals": 0,
      "Market_Session": "NEW_YORK",
      "Accuracy_Quality_Score": 19.84,
      "Accuracy_Gate": "NEUTRAL",
      "Accuracy_Gate_Reason": "Belum ada arah BUY/SELL matang.",
      "Ranking_Score": 21.596295644780632
    },
    {
      "Symbol": "GBPNZD.m",
      "Close": 2.30313,
      "Bid": 2.30313,
      "Ask": 2.30339,
      "Mid_Price": 2.30326,
      "Direction": "NEUTRAL",
      "Projected_Direction": "SELL",
      "Signal_Type": "NEUTRAL",
      "Setup_Maturity": 0.5629,
      "Projection_Score": 0.5598,
      "Projection_Price_Slope": 0.0004402857142857061,
      "Regime": "RANGE",
      "Confidence": 0,
      "Optimizer_Mode": "DEFAULT",
      "Optimizer_Confidence_Floor": 60,
      "Optimizer_Max_Spread_Pips": 3.0,
      "Optimizer_Max_Slippage_Pips": 2.0,
      "Optimizer_Projection_Maturity_Floor": 0.55,
      "Optimizer_Projection_ZF_Floor": 0.45,
      "Optimizer_Projection_Confidence_Floor": 58,
      "Dynamic_Lot": 0.0,
      "Entry_Price": 2.30313,
      "SL_Pips": 18.4,
      "SL_Points": 184.0,
      "SL_Price": NaN,
      "SL_Model": "DATA_DRIVEN",
      "TP_Pips": 0.0,
      "TP_Points": 0.0,
      "TP_Price": NaN,
      "TP_Model": "NO_SIGNAL",
      "RR_Ratio": 0.0,
      "Spread_Pips": 2.599999999999269,
      "Slippage_Est_Pips": 2.27,
      "Bid_Depth": 0.0,
      "Ask_Depth": 0.0,
      "Total_Depth": 0.0,
      "Depth_Imbalance": 0.0,
      "Depth_Available": false,
      "Liquidity_Cluster_Price": NaN,
      "Liquidity_Cluster_Volume": 0.0,
      "Liquidity_Stress": 1.0,
      "Liquidity_Status": "STRESSED",
      "Liquidity_Void": false,
      "Lambda_Liquidity": 1.1,
      "Drift": 0.009177208052031875,
      "Decay_Integral": 0.4404517545078435,
      "Inflection_Detected": false,
      "ZF_Score": 0.7396147637490722,
      "Previous_Direction": "NEUTRAL",
      "Previous_Drift": 0.012367842122411288,
      "Previous_ZF_Score": 0.7299974875515645,
      "Previous_Lambda_Liquidity": 1.1,
      "Previous_Liquidity_Status": "STRESSED",
      "Delta_Drift": -0.0031906340703794136,
      "Delta_ZF_Score": 0.00961727619750774,
      "Delta_Lambda": 0.0,
      "Direction_Changed": false,
      "Liquidity_Status_Changed": false,
      "Memory_Status": "LAMINAR",
      "Risk_Mode": "SLIPPAGE_LOCK",
      "Trade_Allowed": false,
      "Action_Signal": "TUNGGU SLIPPAGE",
      "Risk_Note": "Estimasi slippage melebihi batas.",
      "Session_Phase": "STRESSED",
      "User_Recommendation": "Jangan entry. Risiko slippage terlalu besar.",
      "Historical_Status": "AVOID",
      "Historical_Expectancy_R": -0.0526,
      "Historical_Win_Rate": 40.72,
      "Historical_Signals": 846,
      "Live_Expectancy_R": NaN,
      "Live_Signals": 0,
      "Market_Session": "NEW_YORK",
      "Accuracy_Quality_Score": 11.64,
      "Accuracy_Gate": "NEUTRAL",
      "Accuracy_Gate_Reason": "Belum ada arah BUY/SELL matang.",
      "Ranking_Score": 21.94327381874536
    },
    {
      "Symbol": "NZDCAD.m",
      "Close": 0.81508,
      "Bid": 0.81508,
      "Ask": 0.81518,
      "Mid_Price": 0.81513,
      "Direction": "NEUTRAL",
      "Projected_Direction": "NEUTRAL",
      "Signal_Type": "NEUTRAL",
      "Setup_Maturity": 0.7274,
      "Projection_Score": 0.6161,
      "Projection_Price_Slope": -0.0002260000000000009,
      "Regime": "RANGE",
      "Confidence": 0,
      "Optimizer_Mode": "DEFAULT",
      "Optimizer_Confidence_Floor": 60,
      "Optimizer_Max_Spread_Pips": 3.0,
      "Optimizer_Max_Slippage_Pips": 2.0,
      "Optimizer_Projection_Maturity_Floor": 0.55,
      "Optimizer_Projection_ZF_Floor": 0.45,
      "Optimizer_Projection_Confidence_Floor": 58,
      "Dynamic_Lot": 0.0,
      "Entry_Price": 0.81508,
      "SL_Pips": 8.1,
      "SL_Points": 81.0,
      "SL_Price": NaN,
      "SL_Model": "DATA_DRIVEN",
      "TP_Pips": 0.0,
      "TP_Points": 0.0,
      "TP_Price": NaN,
      "TP_Model": "NO_SIGNAL",
      "RR_Ratio": 0.0,
      "Spread_Pips": 0.9999999999998899,
      "Slippage_Est_Pips": 0.87,
      "Bid_Depth": 0.0,
      "Ask_Depth": 0.0,
      "Total_Depth": 0.0,
      "Depth_Imbalance": 0.0,
      "Depth_Available": false,
      "Liquidity_Cluster_Price": NaN,
      "Liquidity_Cluster_Volume": 0.0,
      "Liquidity_Stress": 0.6499999999999615,
      "Liquidity_Status": "LAMINAR",
      "Liquidity_Void": false,
      "Lambda_Liquidity": 0.7499999999999615,
      "Drift": 0.047636979520834434,
      "Decay_Integral": -0.42439591066647275,
      "Inflection_Detected": false,
      "ZF_Score": 0.5979929284312365,
      "Previous_Direction": "NEUTRAL",
      "Previous_Drift": 0.05180775179012436,
      "Previous_ZF_Score": 0.5803301240698494,
      "Previous_Lambda_Liquidity": 0.7150000000001208,
      "Previous_Liquidity_Status": "LAMINAR",
      "Delta_Drift": -0.004170772269289927,
      "Delta_ZF_Score": 0.01766280436138712,
      "Delta_Lambda": 0.034999999999840714,
      "Direction_Changed": false,
      "Liquidity_Status_Changed": false,
      "Memory_Status": "LAMINAR",
      "Risk_Mode": "NORMAL",
      "Trade_Allowed": false,
      "Action_Signal": "STANDBY",
      "Risk_Note": "",
      "Session_Phase": "LAMINAR",
      "User_Recommendation": "Tidak ada entry. Tunggu sinyal BUY/SELL berikutnya.",
      "Historical_Status": "AVOID",
      "Historical_Expectancy_R": -0.0932,
      "Historical_Win_Rate": 38.74,
      "Historical_Signals": 824,
      "Live_Expectancy_R": NaN,
      "Live_Signals": 0,
      "Market_Session": "NEW_YORK",
      "Accuracy_Quality_Score": 26.13,
      "Accuracy_Gate": "NEUTRAL",
      "Accuracy_Gate_Reason": "Belum ada arah BUY/SELL matang.",
      "Ranking_Score": 31.353464642156183
    },
    {
      "Symbol": "NZDCHF.m",
      "Close": 0.46269,
      "Bid": 0.46269,
      "Ask": 0.46277,
      "Mid_Price": 0.46273,
      "Direction": "NEUTRAL",
      "Projected_Direction": "NEUTRAL",
      "Signal_Type": "NEUTRAL",
      "Setup_Maturity": 0.2912,
      "Projection_Score": 0.3643,
      "Projection_Price_Slope": -9.657142857144795e-05,
      "Regime": "RANGE",
      "Confidence": 0,
      "Optimizer_Mode": "LEARNING",
      "Optimizer_Confidence_Floor": 60,
      "Optimizer_Max_Spread_Pips": 3.0,
      "Optimizer_Max_Slippage_Pips": 2.0,
      "Optimizer_Projection_Maturity_Floor": 0.55,
      "Optimizer_Projection_ZF_Floor": 0.45,
      "Optimizer_Projection_Confidence_Floor": 58,
      "Dynamic_Lot": 0.0,
      "Entry_Price": 0.46269,
      "SL_Pips": 7.0,
      "SL_Points": 70.0,
      "SL_Price": NaN,
      "SL_Model": "DATA_DRIVEN",
      "TP_Pips": 0.0,
      "TP_Points": 0.0,
      "TP_Price": NaN,
      "TP_Model": "NO_SIGNAL",
      "RR_Ratio": 0.0,
      "Spread_Pips": 0.800000000000245,
      "Slippage_Est_Pips": 0.7,
      "Bid_Depth": 0.0,
      "Ask_Depth": 0.0,
      "Total_Depth": 0.0,
      "Depth_Imbalance": 0.0,
      "Depth_Available": false,
      "Liquidity_Cluster_Price": NaN,
      "Liquidity_Cluster_Volume": 0.0,
      "Liquidity_Stress": 0.5800000000000858,
      "Liquidity_Status": "LAMINAR",
      "Liquidity_Void": false,
      "Lambda_Liquidity": 0.6800000000000858,
      "Drift": 0.01946097566447524,
      "Decay_Integral": -0.2781746625254486,
      "Inflection_Detected": false,
      "ZF_Score": 0.630170402499091,
      "Previous_Direction": "NEUTRAL",
      "Previous_Drift": 0.012634400479376204,
      "Previous_ZF_Score": 0.6468166110173226,
      "Previous_Lambda_Liquidity": 0.6450000000000506,
      "Previous_Liquidity_Status": "LAMINAR",
      "Delta_Drift": 0.0068265751850990364,
      "Delta_ZF_Score": -0.01664620851823162,
      "Delta_Lambda": 0.035000000000035114,
      "Direction_Changed": false,
      "Liquidity_Status_Changed": false,
      "Memory_Status": "LAMINAR",
      "Risk_Mode": "NORMAL",
      "Trade_Allowed": false,
      "Action_Signal": "STANDBY",
      "Risk_Note": "",
      "Session_Phase": "LAMINAR",
      "User_Recommendation": "Tidak ada entry. Tunggu sinyal BUY/SELL berikutnya.",
      "Historical_Status": "TRADEABLE",
      "Historical_Expectancy_R": 0.0403,
      "Historical_Win_Rate": 45.74,
      "Historical_Signals": 775,
      "Live_Expectancy_R": -1.0,
      "Live_Signals": 1,
      "Market_Session": "NEW_YORK",
      "Accuracy_Quality_Score": 18.6,
      "Accuracy_Gate": "NEUTRAL",
      "Accuracy_Gate_Reason": "Belum ada arah BUY/SELL matang.",
      "Ranking_Score": 22.02165201249546
    },
    {
      "Symbol": "NZDJPY.m",
      "Close": 93.437,
      "Bid": 93.437,
      "Ask": 93.452,
      "Mid_Price": 93.4445,
      "Direction": "BUY",
      "Projected_Direction": "BUY",
      "Signal_Type": "PROJECTED",
      "Setup_Maturity": 0.8874,
      "Projection_Score": 0.7461,
      "Projection_Price_Slope": -0.012800000000000296,
      "Regime": "TREND",
      "Confidence": 55,
      "Optimizer_Mode": "DEFAULT",
      "Optimizer_Confidence_Floor": 60,
      "Optimizer_Max_Spread_Pips": 3.0,
      "Optimizer_Max_Slippage_Pips": 2.0,
      "Optimizer_Projection_Maturity_Floor": 0.55,
      "Optimizer_Projection_ZF_Floor": 0.45,
      "Optimizer_Projection_Confidence_Floor": 58,
      "Dynamic_Lot": 0.0,
      "Entry_Price": 93.437,
      "SL_Pips": 13.5,
      "SL_Points": 135.0,
      "SL_Price": 93.302,
      "SL_Model": "DATA_DRIVEN",
      "TP_Pips": 16.9,
      "TP_Points": 169.0,
      "TP_Price": 93.606,
      "TP_Model": "DATA_DRIVEN",
      "RR_Ratio": 1.25,
      "Spread_Pips": 1.5000000000000568,
      "Slippage_Est_Pips": 1.31,
      "Bid_Depth": 0.0,
      "Ask_Depth": 0.0,
      "Total_Depth": 0.0,
      "Depth_Imbalance": 0.0,
      "Depth_Available": false,
      "Liquidity_Cluster_Price": NaN,
      "Liquidity_Cluster_Volume": 0.0,
      "Liquidity_Stress": 0.8250000000000199,
      "Liquidity_Status": "STRESSED",
      "Liquidity_Void": false,
      "Lambda_Liquidity": 0.9250000000000199,
      "Drift": 0.009427113420764698,
      "Decay_Integral": -0.6525958342492998,
      "Inflection_Detected": false,
      "ZF_Score": 0.7053291706232698,
      "Previous_Direction": "BUY",
      "Previous_Drift": 0.023594061630878006,
      "Previous_ZF_Score": 0.6446272339582325,
      "Previous_Lambda_Liquidity": 0.7499999999996817,
      "Previous_Liquidity_Status": "LAMINAR",
      "Delta_Drift": -0.014166948210113307,
      "Delta_ZF_Score": 0.060701936665037315,
      "Delta_Lambda": 0.17500000000033822,
      "Direction_Changed": false,
      "Liquidity_Status_Changed": true,
      "Memory_Status": "RESONANCE_MISMATCH",
      "Risk_Mode": "PROFILE_LOCK",
      "Trade_Allowed": false,
      "Action_Signal": "WATCH HISTORIS",
      "Risk_Note": "Pair historis negatif/belum tervalidasi; tidak masuk TOP eksekusi.",
      "Session_Phase": "ANOMALOUS",
      "User_Recommendation": "Jangan entry. Pair ini belum lolos validasi historis.",
      "Historical_Status": "AVOID",
      "Historical_Expectancy_R": -0.0455,
      "Historical_Win_Rate": 41.31,
      "Historical_Signals": 823,
      "Live_Expectancy_R": NaN,
      "Live_Signals": 0,
      "Market_Session": "NEW_YORK",
      "Accuracy_Quality_Score": 42.3,
      "Accuracy_Gate": "WATCH",
      "Accuracy_Gate_Reason": "quality 42.3 < 62 | status historis AVOID | winrate historis 41.31% < 45.00% | expectancy historis -0.0455R < 0.0200R",
      "Ranking_Score": 53.83084585311635
    },
    {
      "Symbol": "XAGUSD.m",
      "Close": 70.122,
      "Bid": 70.122,
      "Ask": 70.149,
      "Mid_Price": 70.13550000000001,
      "Direction": "BUY",
      "Projected_Direction": "BUY",
      "Signal_Type": "PROJECTED",
      "Setup_Maturity": 0.9959,
      "Projection_Score": 0.8404,
      "Projection_Price_Slope": -0.1190571428571409,
      "Regime": "RANGE",
      "Confidence": 62,
      "Optimizer_Mode": "DEFAULT",
      "Optimizer_Confidence_Floor": 60,
      "Optimizer_Max_Spread_Pips": 3.0,
      "Optimizer_Max_Slippage_Pips": 2.0,
      "Optimizer_Projection_Maturity_Floor": 0.55,
      "Optimizer_Projection_ZF_Floor": 0.45,
      "Optimizer_Projection_Confidence_Floor": 58,
      "Dynamic_Lot": 0.0,
      "Entry_Price": 70.122,
      "SL_Pips": 45.8,
      "SL_Points": 458.0,
      "SL_Price": 69.664,
      "SL_Model": "DATA_DRIVEN",
      "TP_Pips": 57.9,
      "TP_Points": 579.0,
      "TP_Price": 70.701,
      "TP_Model": "DATA_DRIVEN",
      "RR_Ratio": 1.26,
      "Spread_Pips": 2.7000000000001023,
      "Slippage_Est_Pips": 2.36,
      "Bid_Depth": 0.0,
      "Ask_Depth": 0.0,
      "Total_Depth": 0.0,
      "Depth_Imbalance": 0.0,
      "Depth_Available": false,
      "Liquidity_Cluster_Price": NaN,
      "Liquidity_Cluster_Volume": 0.0,
      "Liquidity_Stress": 1.0,
      "Liquidity_Status": "STRESSED",
      "Liquidity_Void": false,
      "Lambda_Liquidity": 1.1,
      "Drift": 0.29714606631011065,
      "Decay_Integral": -6.944389237623447,
      "Inflection_Detected": true,
      "ZF_Score": 0.7122139055692431,
      "Previous_Direction": "BUY",
      "Previous_Drift": 0.3236639644454702,
      "Previous_ZF_Score": 0.7060591670787904,
      "Previous_Lambda_Liquidity": 1.1,
      "Previous_Liquidity_Status": "STRESSED",
      "Delta_Drift": -0.02651789813535954,
      "Delta_ZF_Score": 0.006154738490452782,
      "Delta_Lambda": 0.0,
      "Direction_Changed": false,
      "Liquidity_Status_Changed": false,
      "Memory_Status": "LAMINAR",
      "Risk_Mode": "PROFILE_LOCK",
      "Trade_Allowed": false,
      "Action_Signal": "WATCH HISTORIS",
      "Risk_Note": "Pair historis negatif/belum tervalidasi; tidak masuk TOP eksekusi.",
      "Session_Phase": "STRESSED",
      "User_Recommendation": "Jangan entry. Pair ini belum lolos validasi historis.",
      "Historical_Status": "AVOID",
      "Historical_Expectancy_R": -0.0625,
      "Historical_Win_Rate": 40.12,
      "Historical_Signals": 835,
      "Live_Expectancy_R": NaN,
      "Live_Signals": 0,
      "Market_Session": "NEW_YORK",
      "Accuracy_Quality_Score": 35.41,
      "Accuracy_Gate": "WATCH",
      "Accuracy_Gate_Reason": "quality 35.4 < 62 | status historis AVOID | winrate historis 40.12% < 45.00% | expectancy historis -0.0625R < 0.0200R",
      "Ranking_Score": 52.84056952784622
    },
    {
      "Symbol": "XAUUSD.m",
      "Close": 4329.55,
      "Bid": 4329.55,
      "Ask": 4329.82,
      "Mid_Price": 4329.6849999999995,
      "Direction": "BUY",
      "Projected_Direction": "BUY",
      "Signal_Type": "STRICT",
      "Setup_Maturity": 1.25,
      "Projection_Score": 0.9949,
      "Projection_Price_Slope": -5.879428571428474,
      "Regime": "RANGE",
      "Confidence": 58,
      "Optimizer_Mode": "DEFAULT",
      "Optimizer_Confidence_Floor": 60,
      "Optimizer_Max_Spread_Pips": 3.0,
      "Optimizer_Max_Slippage_Pips": 2.0,
      "Optimizer_Projection_Maturity_Floor": 0.55,
      "Optimizer_Projection_ZF_Floor": 0.45,
      "Optimizer_Projection_Confidence_Floor": 58,
      "Dynamic_Lot": 0.0,
      "Entry_Price": 4329.55,
      "SL_Pips": 1512.7,
      "SL_Points": 1513.0,
      "SL_Price": 4314.42,
      "SL_Model": "DATA_DRIVEN",
      "TP_Pips": 1910.8,
      "TP_Points": 1911.0,
      "TP_Price": 4348.66,
      "TP_Model": "DATA_DRIVEN",
      "RR_Ratio": 1.26,
      "Spread_Pips": 26.999999999952706,
      "Slippage_Est_Pips": 23.62,
      "Bid_Depth": 0.0,
      "Ask_Depth": 0.0,
      "Total_Depth": 0.0,
      "Depth_Imbalance": 0.0,
      "Depth_Available": false,
      "Liquidity_Cluster_Price": NaN,
      "Liquidity_Cluster_Volume": 0.0,
      "Liquidity_Stress": 1.0,
      "Liquidity_Status": "VOID",
      "Liquidity_Void": true,
      "Lambda_Liquidity": 1.1,
      "Drift": 0.29354005991911886,
      "Decay_Integral": -3.8341386621900857,
      "Inflection_Detected": true,
      "ZF_Score": 0.6500477324116591,
      "Previous_Direction": "BUY",
      "Previous_Drift": 0.25841030999732667,
      "Previous_ZF_Score": 0.6625397338550367,
      "Previous_Lambda_Liquidity": 1.1,
      "Previous_Liquidity_Status": "VOID",
      "Delta_Drift": 0.035129749921792186,
      "Delta_ZF_Score": -0.012492001443377587,
      "Delta_Lambda": 0.0,
      "Direction_Changed": false,
      "Liquidity_Status_Changed": false,
      "Memory_Status": "LAMINAR",
      "Risk_Mode": "LIQUIDITY_LOCK",
      "Trade_Allowed": false,
      "Action_Signal": "PERTAHANAN LIKUIDITAS",
      "Risk_Note": "Liquidity void atau spread terlalu lebar.",
      "Session_Phase": "ANOMALOUS",
      "User_Recommendation": "Jangan entry. Likuiditas/spread sedang tidak sehat.",
      "Historical_Status": "TRADEABLE",
      "Historical_Expectancy_R": 0.0753,
      "Historical_Win_Rate": 47.74,
      "Historical_Signals": 757,
      "Live_Expectancy_R": NaN,
      "Live_Signals": 0,
      "Market_Session": "NEW_YORK",
      "Accuracy_Quality_Score": 34.46,
      "Accuracy_Gate": "WATCH",
      "Accuracy_Gate_Reason": "quality 34.5 < 62",
      "Ranking_Score": 57.0648386620583
    }
  ]
}