{
  "scan_time": "2026-06-18T11:00:10.268930+08:00",
  "account_equity": 9995.41,
  "news_status": "LOW RISK",
  "macro": {
    "DXY": 100.25,
    "US10Y": 4.463000297546387,
    "GOLD": 4334.2001953125
  },
  "summary": {
    "symbols_scanned": 11,
    "buy_candidates": 1,
    "sell_candidates": 2,
    "resonance_mismatches": 2
  },
  "previous_archive": "D:\\FOREX\\zf_archival_vault\\zf_scan_20260618_104503.json",
  "top_buy": [
    {
      "Symbol": "CADCHFm",
      "Asset_Class": "forex",
      "Timeframe": "M15",
      "Exit_Mode": "DYNAMIC_SL_TP",
      "Expected_Hold_Hours": 7.28,
      "Close": 0.56641,
      "Bid": 0.56641,
      "Ask": 0.56649,
      "Mid_Price": 0.56645,
      "Direction": "BUY",
      "Projected_Direction": "NEUTRAL",
      "Signal_Type": "STRICT",
      "Setup_Maturity": 1.25,
      "Projection_Score": 0.9473,
      "Projection_Price_Slope": 2.6571428571429867e-05,
      "Regime": "RANGE",
      "Confidence": 83,
      "Optimizer_Mode": "DEFAULT",
      "Optimizer_Confidence_Floor": 60,
      "Optimizer_Max_Spread_Pips": 3.0,
      "Optimizer_Max_Slippage_Pips": 2.0,
      "Optimizer_Projection_Maturity_Floor": 0.55,
      "Optimizer_Projection_ZF_Floor": 0.45,
      "Optimizer_Projection_Confidence_Floor": 58,
      "Historical_Optimizer_ZF_Floor": 0.5,
      "Kelly_Full": 0.0,
      "Kelly_Risk_Multiplier": 0.5,
      "Dynamic_Lot": 1.0,
      "Entry_Price": 0.56638,
      "Entry_Model": "ZF_FIBO_BUY_LIMIT",
      "SL_Pips": 7.0,
      "SL_Points": 70.0,
      "SL_Price": 0.56568,
      "SL_Model": "DATA_DRIVEN",
      "TP_Pips": 8.8,
      "TP_Points": 88.0,
      "TP_Price": 0.56726,
      "TP_Model": "DATA_DRIVEN",
      "RR_Ratio": 1.25,
      "Spread_Pips": 0.8000000000008001,
      "Slippage_Est_Pips": 0.7,
      "Bid_Depth": 0.0,
      "Ask_Depth": 0.0,
      "Total_Depth": 0.0,
      "Depth_Imbalance": 0.0,
      "Depth_Available": false,
      "Liquidity_Cluster_Price": NaN,
      "Liquidity_Cluster_Volume": 0.0,
      "Liquidity_Stress": 0.5800000000002801,
      "Liquidity_Status": "LAMINAR",
      "Liquidity_Void": false,
      "Lambda_Liquidity": 0.68000000000028,
      "Fibo_Position": 0.5102,
      "Fibo_Aligned": true,
      "Fibo_382": 0.56603,
      "Fibo_500": 0.56638,
      "Fibo_618": 0.56673,
      "Metal_Gate_Ok": true,
      "OKX_Status": "NOT_CRYPTO",
      "OKX_Instrument": "",
      "OKX_Last": NaN,
      "OKX_Funding_Rate": NaN,
      "OKX_Open_Interest": NaN,
      "OKX_Open_Interest_USD": NaN,
      "OKX_OI_Change_Pct": NaN,
      "OKX_External_Stress": 0.0,
      "OKX_Funding_Bias": "NEUTRAL",
      "Drift": 0.022408697331722807,
      "Decay_Integral": -0.5510120154852018,
      "Inflection_Detected": true,
      "ZF_Score": 0.6361287492039137,
      "Previous_Direction": "BUY",
      "Previous_Drift": 0.029096676528454303,
      "Previous_ZF_Score": 0.6215795048271906,
      "Previous_Lambda_Liquidity": 0.6799999999998914,
      "Previous_Liquidity_Status": "LAMINAR",
      "Delta_Drift": -0.006687979196731496,
      "Delta_ZF_Score": 0.014549244376723114,
      "Delta_Lambda": 3.886890809212673e-13,
      "Direction_Changed": false,
      "Liquidity_Status_Changed": false,
      "Memory_Status": "LAMINAR",
      "Risk_Mode": "NORMAL",
      "Trade_Allowed": true,
      "Action_Signal": "EKSEKUSI",
      "Risk_Note": "",
      "Session_Phase": "LAMINAR",
      "User_Recommendation": "Setup BUY valid. Entry manual boleh dipertimbangkan dengan SL/TP yang tampil. Akurasi historis resolved sekitar 81.25%.",
      "Historical_Status": "TRADEABLE",
      "Historical_Expectancy_R": 0.3989,
      "Historical_Win_Rate": 81.25,
      "Historical_Signals": 17,
      "Live_Expectancy_R": NaN,
      "Live_Signals": 0,
      "Market_Session": "THIN_SESSION",
      "Accuracy_Quality_Score": 75.12,
      "Accuracy_Gate": "PASS",
      "Accuracy_Gate_Reason": "",
      "Ranking_Score": 89.12784374601956
    }
  ],
  "top_sell": [
    {
      "Symbol": "GBPCADm",
      "Asset_Class": "forex",
      "Timeframe": "M15",
      "Exit_Mode": "DYNAMIC_SL_TP",
      "Expected_Hold_Hours": 4.54,
      "Close": 1.87717,
      "Bid": 1.87717,
      "Ask": 1.8773499999999999,
      "Mid_Price": 1.87726,
      "Direction": "SELL",
      "Projected_Direction": "NEUTRAL",
      "Signal_Type": "STRICT",
      "Setup_Maturity": 1.2403,
      "Projection_Score": 0.9684,
      "Projection_Price_Slope": -2.8571428571296905e-05,
      "Regime": "RANGE",
      "Confidence": 73,
      "Optimizer_Mode": "DEFAULT",
      "Optimizer_Confidence_Floor": 60,
      "Optimizer_Max_Spread_Pips": 3.0,
      "Optimizer_Max_Slippage_Pips": 2.0,
      "Optimizer_Projection_Maturity_Floor": 0.55,
      "Optimizer_Projection_ZF_Floor": 0.45,
      "Optimizer_Projection_Confidence_Floor": 58,
      "Historical_Optimizer_ZF_Floor": 0.5,
      "Kelly_Full": 0.0,
      "Kelly_Risk_Multiplier": 0.5,
      "Dynamic_Lot": 0.61,
      "Entry_Price": 1.87717,
      "Entry_Model": "ZF_FIBO_SELL_LIMIT",
      "SL_Pips": 12.3,
      "SL_Points": 123.0,
      "SL_Price": 1.8784,
      "SL_Model": "DATA_DRIVEN",
      "TP_Pips": 15.4,
      "TP_Points": 154.0,
      "TP_Price": 1.87563,
      "TP_Model": "DATA_DRIVEN",
      "RR_Ratio": 1.25,
      "Spread_Pips": 1.7999999999984695,
      "Slippage_Est_Pips": 1.57,
      "Bid_Depth": 0.0,
      "Ask_Depth": 0.0,
      "Total_Depth": 0.0,
      "Depth_Imbalance": 0.0,
      "Depth_Available": false,
      "Liquidity_Cluster_Price": NaN,
      "Liquidity_Cluster_Volume": 0.0,
      "Liquidity_Stress": 0.9299999999994644,
      "Liquidity_Status": "STRESSED",
      "Liquidity_Void": false,
      "Lambda_Liquidity": 1.0299999999994645,
      "Fibo_Position": 0.6467,
      "Fibo_Aligned": true,
      "Fibo_382": 1.87482,
      "Fibo_500": 1.87587,
      "Fibo_618": 1.87692,
      "Metal_Gate_Ok": true,
      "OKX_Status": "NOT_CRYPTO",
      "OKX_Instrument": "",
      "OKX_Last": NaN,
      "OKX_Funding_Rate": NaN,
      "OKX_Open_Interest": NaN,
      "OKX_Open_Interest_USD": NaN,
      "OKX_OI_Change_Pct": NaN,
      "OKX_External_Stress": 0.0,
      "OKX_Funding_Bias": "NEUTRAL",
      "Drift": 0.01968430438847674,
      "Decay_Integral": 0.8185866531045649,
      "Inflection_Detected": false,
      "ZF_Score": 0.706623329767511,
      "Previous_Direction": "SELL",
      "Previous_Drift": 0.02212122672238969,
      "Previous_ZF_Score": 0.7016787486021874,
      "Previous_Lambda_Liquidity": 1.0300000000002416,
      "Previous_Liquidity_Status": "STRESSED",
      "Delta_Drift": -0.0024369223339129505,
      "Delta_ZF_Score": 0.004944581165323592,
      "Delta_Lambda": -7.771561172376096e-13,
      "Direction_Changed": false,
      "Liquidity_Status_Changed": false,
      "Memory_Status": "LAMINAR",
      "Risk_Mode": "NORMAL",
      "Trade_Allowed": true,
      "Action_Signal": "EKSEKUSI",
      "Risk_Note": "",
      "Session_Phase": "STRESSED",
      "User_Recommendation": "Setup SELL valid. Entry manual boleh dipertimbangkan dengan SL/TP yang tampil. Akurasi historis resolved sekitar 81.25%.",
      "Historical_Status": "TRADEABLE",
      "Historical_Expectancy_R": 0.633,
      "Historical_Win_Rate": 81.25,
      "Historical_Signals": 17,
      "Live_Expectancy_R": NaN,
      "Live_Signals": 0,
      "Market_Session": "THIN_SESSION",
      "Accuracy_Quality_Score": 65.17,
      "Accuracy_Gate": "PASS",
      "Accuracy_Gate_Reason": "",
      "Ranking_Score": 83.92541664883755
    },
    {
      "Symbol": "AUDJPYm",
      "Asset_Class": "forex",
      "Timeframe": "M15",
      "Exit_Mode": "DYNAMIC_SL_TP",
      "Expected_Hold_Hours": 2.83,
      "Close": 112.982,
      "Bid": 112.982,
      "Ask": 113.001,
      "Mid_Price": 112.9915,
      "Direction": "SELL",
      "Projected_Direction": "NEUTRAL",
      "Signal_Type": "STRICT",
      "Setup_Maturity": 1.1404,
      "Projection_Score": 0.9144,
      "Projection_Price_Slope": 0.007628571428571847,
      "Regime": "TREND",
      "Confidence": 73,
      "Optimizer_Mode": "DEFAULT",
      "Optimizer_Confidence_Floor": 60,
      "Optimizer_Max_Spread_Pips": 3.0,
      "Optimizer_Max_Slippage_Pips": 2.0,
      "Optimizer_Projection_Maturity_Floor": 0.55,
      "Optimizer_Projection_ZF_Floor": 0.45,
      "Optimizer_Projection_Confidence_Floor": 58,
      "Historical_Optimizer_ZF_Floor": 0.5,
      "Kelly_Full": 0.0,
      "Kelly_Risk_Multiplier": 0.5,
      "Dynamic_Lot": 0.47,
      "Entry_Price": 112.982,
      "Entry_Model": "ZF_FIBO_SELL_LIMIT",
      "SL_Pips": 16.1,
      "SL_Points": 161.0,
      "SL_Price": 113.143,
      "SL_Model": "DATA_DRIVEN",
      "TP_Pips": 20.1,
      "TP_Points": 201.0,
      "TP_Price": 112.781,
      "TP_Model": "DATA_DRIVEN",
      "RR_Ratio": 1.25,
      "Spread_Pips": 1.9000000000005457,
      "Slippage_Est_Pips": 1.66,
      "Bid_Depth": 0.0,
      "Ask_Depth": 0.0,
      "Total_Depth": 0.0,
      "Depth_Imbalance": 0.0,
      "Depth_Available": false,
      "Liquidity_Cluster_Price": NaN,
      "Liquidity_Cluster_Volume": 0.0,
      "Liquidity_Stress": 0.965000000000191,
      "Liquidity_Status": "STRESSED",
      "Liquidity_Void": false,
      "Lambda_Liquidity": 1.0650000000001911,
      "Fibo_Position": 0.5844,
      "Fibo_Aligned": true,
      "Fibo_382": 112.803,
      "Fibo_500": 112.907,
      "Fibo_618": 113.012,
      "Metal_Gate_Ok": true,
      "OKX_Status": "NOT_CRYPTO",
      "OKX_Instrument": "",
      "OKX_Last": NaN,
      "OKX_Funding_Rate": NaN,
      "OKX_Open_Interest": NaN,
      "OKX_Open_Interest_USD": NaN,
      "OKX_OI_Change_Pct": NaN,
      "OKX_External_Stress": 0.0,
      "OKX_Funding_Bias": "NEUTRAL",
      "Drift": 0.029728934615042814,
      "Decay_Integral": 1.4475336783555564,
      "Inflection_Detected": true,
      "ZF_Score": 0.7132508430258597,
      "Previous_Direction": "NEUTRAL",
      "Previous_Drift": 0.026365582021563708,
      "Previous_ZF_Score": 0.7173023527675342,
      "Previous_Lambda_Liquidity": 1.0649999999996937,
      "Previous_Liquidity_Status": "STRESSED",
      "Delta_Drift": 0.003363352593479106,
      "Delta_ZF_Score": -0.004051509741674453,
      "Delta_Lambda": 4.973799150320701e-13,
      "Direction_Changed": true,
      "Liquidity_Status_Changed": false,
      "Memory_Status": "RESONANCE_MISMATCH",
      "Risk_Mode": "NORMAL",
      "Trade_Allowed": true,
      "Action_Signal": "EKSEKUSI",
      "Risk_Note": "",
      "Session_Phase": "ANOMALOUS",
      "User_Recommendation": "Setup SELL valid. Entry manual boleh dipertimbangkan dengan SL/TP yang tampil. Akurasi historis resolved sekitar 63.16%.",
      "Historical_Status": "TRADEABLE",
      "Historical_Expectancy_R": 0.1447,
      "Historical_Win_Rate": 63.16,
      "Historical_Signals": 21,
      "Live_Expectancy_R": NaN,
      "Live_Signals": 0,
      "Market_Session": "THIN_SESSION",
      "Accuracy_Quality_Score": 56.5,
      "Accuracy_Gate": "PASS",
      "Accuracy_Gate_Reason": "",
      "Ranking_Score": 72.23805421512931
    }
  ],
  "resonance_mismatches": [
    {
      "Symbol": "EURCADm",
      "Asset_Class": "forex",
      "Timeframe": "M15",
      "Exit_Mode": "DYNAMIC_SL_TP",
      "Expected_Hold_Hours": 6.71,
      "Close": 1.62416,
      "Bid": 1.62416,
      "Ask": 1.62431,
      "Mid_Price": 1.624235,
      "Direction": "SELL",
      "Projected_Direction": "NEUTRAL",
      "Signal_Type": "STRICT",
      "Setup_Maturity": 1.0626,
      "Projection_Score": 0.849,
      "Projection_Price_Slope": -2.6571428571286807e-05,
      "Regime": "TREND",
      "Confidence": 73,
      "Optimizer_Mode": "DEFAULT",
      "Optimizer_Confidence_Floor": 60,
      "Optimizer_Max_Spread_Pips": 3.0,
      "Optimizer_Max_Slippage_Pips": 2.0,
      "Optimizer_Projection_Maturity_Floor": 0.55,
      "Optimizer_Projection_ZF_Floor": 0.45,
      "Optimizer_Projection_Confidence_Floor": 58,
      "Historical_Optimizer_ZF_Floor": 0.5,
      "Kelly_Full": 0.0,
      "Kelly_Risk_Multiplier": 0.5,
      "Dynamic_Lot": 0.0,
      "Entry_Price": 1.62416,
      "Entry_Model": "ZF_FIBO_SELL_LIMIT",
      "SL_Pips": 13.5,
      "SL_Points": 135.0,
      "SL_Price": 1.62551,
      "SL_Model": "DATA_DRIVEN",
      "TP_Pips": 16.9,
      "TP_Points": 169.0,
      "TP_Price": 1.62247,
      "TP_Model": "DATA_DRIVEN",
      "RR_Ratio": 1.25,
      "Spread_Pips": 1.4999999999987244,
      "Slippage_Est_Pips": 1.31,
      "Bid_Depth": 0.0,
      "Ask_Depth": 0.0,
      "Total_Depth": 0.0,
      "Depth_Imbalance": 0.0,
      "Depth_Available": false,
      "Liquidity_Cluster_Price": NaN,
      "Liquidity_Cluster_Volume": 0.0,
      "Liquidity_Stress": 0.8249999999995534,
      "Liquidity_Status": "STRESSED",
      "Liquidity_Void": false,
      "Lambda_Liquidity": 0.9249999999995534,
      "Fibo_Position": 0.6115,
      "Fibo_Aligned": true,
      "Fibo_382": 1.62256,
      "Fibo_500": 1.62338,
      "Fibo_618": 1.62421,
      "Metal_Gate_Ok": true,
      "OKX_Status": "NOT_CRYPTO",
      "OKX_Instrument": "",
      "OKX_Last": NaN,
      "OKX_Funding_Rate": NaN,
      "OKX_Open_Interest": NaN,
      "OKX_Open_Interest_USD": NaN,
      "OKX_OI_Change_Pct": NaN,
      "OKX_External_Stress": 0.0,
      "OKX_Funding_Bias": "NEUTRAL",
      "Drift": 0.0211374622153641,
      "Decay_Integral": 0.6747653323120659,
      "Inflection_Detected": true,
      "ZF_Score": 0.6814970376344455,
      "Previous_Direction": "NEUTRAL",
      "Previous_Drift": 0.025077044247348888,
      "Previous_ZF_Score": 0.6715034015147018,
      "Previous_Lambda_Liquidity": 0.9249999999995534,
      "Previous_Liquidity_Status": "STRESSED",
      "Delta_Drift": -0.003939582031984787,
      "Delta_ZF_Score": 0.009993636119743687,
      "Delta_Lambda": 0.0,
      "Direction_Changed": true,
      "Liquidity_Status_Changed": false,
      "Memory_Status": "RESONANCE_MISMATCH",
      "Risk_Mode": "ACCURACY_LOCK",
      "Trade_Allowed": false,
      "Action_Signal": "TUNGGU AKURASI",
      "Risk_Note": "winrate historis 56.25% < 58.00%",
      "Session_Phase": "ANOMALOUS",
      "User_Recommendation": "Jangan entry dulu. Sinyal ditahan oleh mode akurasi ketat. Alasan: winrate historis 56.25% < 58.00%.",
      "Historical_Status": "TRADEABLE",
      "Historical_Expectancy_R": 0.1091,
      "Historical_Win_Rate": 56.25,
      "Historical_Signals": 17,
      "Live_Expectancy_R": NaN,
      "Live_Signals": 0,
      "Market_Session": "THIN_SESSION",
      "Accuracy_Quality_Score": 57.73,
      "Accuracy_Gate": "LOCKED",
      "Accuracy_Gate_Reason": "winrate historis 56.25% < 58.00%",
      "Mismatch_Rank": 0.009993636119743687
    },
    {
      "Symbol": "AUDJPYm",
      "Asset_Class": "forex",
      "Timeframe": "M15",
      "Exit_Mode": "DYNAMIC_SL_TP",
      "Expected_Hold_Hours": 2.83,
      "Close": 112.982,
      "Bid": 112.982,
      "Ask": 113.001,
      "Mid_Price": 112.9915,
      "Direction": "SELL",
      "Projected_Direction": "NEUTRAL",
      "Signal_Type": "STRICT",
      "Setup_Maturity": 1.1404,
      "Projection_Score": 0.9144,
      "Projection_Price_Slope": 0.007628571428571847,
      "Regime": "TREND",
      "Confidence": 73,
      "Optimizer_Mode": "DEFAULT",
      "Optimizer_Confidence_Floor": 60,
      "Optimizer_Max_Spread_Pips": 3.0,
      "Optimizer_Max_Slippage_Pips": 2.0,
      "Optimizer_Projection_Maturity_Floor": 0.55,
      "Optimizer_Projection_ZF_Floor": 0.45,
      "Optimizer_Projection_Confidence_Floor": 58,
      "Historical_Optimizer_ZF_Floor": 0.5,
      "Kelly_Full": 0.0,
      "Kelly_Risk_Multiplier": 0.5,
      "Dynamic_Lot": 0.47,
      "Entry_Price": 112.982,
      "Entry_Model": "ZF_FIBO_SELL_LIMIT",
      "SL_Pips": 16.1,
      "SL_Points": 161.0,
      "SL_Price": 113.143,
      "SL_Model": "DATA_DRIVEN",
      "TP_Pips": 20.1,
      "TP_Points": 201.0,
      "TP_Price": 112.781,
      "TP_Model": "DATA_DRIVEN",
      "RR_Ratio": 1.25,
      "Spread_Pips": 1.9000000000005457,
      "Slippage_Est_Pips": 1.66,
      "Bid_Depth": 0.0,
      "Ask_Depth": 0.0,
      "Total_Depth": 0.0,
      "Depth_Imbalance": 0.0,
      "Depth_Available": false,
      "Liquidity_Cluster_Price": NaN,
      "Liquidity_Cluster_Volume": 0.0,
      "Liquidity_Stress": 0.965000000000191,
      "Liquidity_Status": "STRESSED",
      "Liquidity_Void": false,
      "Lambda_Liquidity": 1.0650000000001911,
      "Fibo_Position": 0.5844,
      "Fibo_Aligned": true,
      "Fibo_382": 112.803,
      "Fibo_500": 112.907,
      "Fibo_618": 113.012,
      "Metal_Gate_Ok": true,
      "OKX_Status": "NOT_CRYPTO",
      "OKX_Instrument": "",
      "OKX_Last": NaN,
      "OKX_Funding_Rate": NaN,
      "OKX_Open_Interest": NaN,
      "OKX_Open_Interest_USD": NaN,
      "OKX_OI_Change_Pct": NaN,
      "OKX_External_Stress": 0.0,
      "OKX_Funding_Bias": "NEUTRAL",
      "Drift": 0.029728934615042814,
      "Decay_Integral": 1.4475336783555564,
      "Inflection_Detected": true,
      "ZF_Score": 0.7132508430258597,
      "Previous_Direction": "NEUTRAL",
      "Previous_Drift": 0.026365582021563708,
      "Previous_ZF_Score": 0.7173023527675342,
      "Previous_Lambda_Liquidity": 1.0649999999996937,
      "Previous_Liquidity_Status": "STRESSED",
      "Delta_Drift": 0.003363352593479106,
      "Delta_ZF_Score": -0.004051509741674453,
      "Delta_Lambda": 4.973799150320701e-13,
      "Direction_Changed": true,
      "Liquidity_Status_Changed": false,
      "Memory_Status": "RESONANCE_MISMATCH",
      "Risk_Mode": "NORMAL",
      "Trade_Allowed": true,
      "Action_Signal": "EKSEKUSI",
      "Risk_Note": "",
      "Session_Phase": "ANOMALOUS",
      "User_Recommendation": "Setup SELL valid. Entry manual boleh dipertimbangkan dengan SL/TP yang tampil. Akurasi historis resolved sekitar 63.16%.",
      "Historical_Status": "TRADEABLE",
      "Historical_Expectancy_R": 0.1447,
      "Historical_Win_Rate": 63.16,
      "Historical_Signals": 21,
      "Live_Expectancy_R": NaN,
      "Live_Signals": 0,
      "Market_Session": "THIN_SESSION",
      "Accuracy_Quality_Score": 56.5,
      "Accuracy_Gate": "PASS",
      "Accuracy_Gate_Reason": "",
      "Mismatch_Rank": 0.004051509741674453
    }
  ],
  "results": [
    {
      "Symbol": "GBPCADm",
      "Asset_Class": "forex",
      "Timeframe": "M15",
      "Exit_Mode": "DYNAMIC_SL_TP",
      "Expected_Hold_Hours": 4.54,
      "Close": 1.87717,
      "Bid": 1.87717,
      "Ask": 1.8773499999999999,
      "Mid_Price": 1.87726,
      "Direction": "SELL",
      "Projected_Direction": "NEUTRAL",
      "Signal_Type": "STRICT",
      "Setup_Maturity": 1.2403,
      "Projection_Score": 0.9684,
      "Projection_Price_Slope": -2.8571428571296905e-05,
      "Regime": "RANGE",
      "Confidence": 73,
      "Optimizer_Mode": "DEFAULT",
      "Optimizer_Confidence_Floor": 60,
      "Optimizer_Max_Spread_Pips": 3.0,
      "Optimizer_Max_Slippage_Pips": 2.0,
      "Optimizer_Projection_Maturity_Floor": 0.55,
      "Optimizer_Projection_ZF_Floor": 0.45,
      "Optimizer_Projection_Confidence_Floor": 58,
      "Historical_Optimizer_ZF_Floor": 0.5,
      "Kelly_Full": 0.0,
      "Kelly_Risk_Multiplier": 0.5,
      "Dynamic_Lot": 0.61,
      "Entry_Price": 1.87717,
      "Entry_Model": "ZF_FIBO_SELL_LIMIT",
      "SL_Pips": 12.3,
      "SL_Points": 123.0,
      "SL_Price": 1.8784,
      "SL_Model": "DATA_DRIVEN",
      "TP_Pips": 15.4,
      "TP_Points": 154.0,
      "TP_Price": 1.87563,
      "TP_Model": "DATA_DRIVEN",
      "RR_Ratio": 1.25,
      "Spread_Pips": 1.7999999999984695,
      "Slippage_Est_Pips": 1.57,
      "Bid_Depth": 0.0,
      "Ask_Depth": 0.0,
      "Total_Depth": 0.0,
      "Depth_Imbalance": 0.0,
      "Depth_Available": false,
      "Liquidity_Cluster_Price": NaN,
      "Liquidity_Cluster_Volume": 0.0,
      "Liquidity_Stress": 0.9299999999994644,
      "Liquidity_Status": "STRESSED",
      "Liquidity_Void": false,
      "Lambda_Liquidity": 1.0299999999994645,
      "Fibo_Position": 0.6467,
      "Fibo_Aligned": true,
      "Fibo_382": 1.87482,
      "Fibo_500": 1.87587,
      "Fibo_618": 1.87692,
      "Metal_Gate_Ok": true,
      "OKX_Status": "NOT_CRYPTO",
      "OKX_Instrument": "",
      "OKX_Last": NaN,
      "OKX_Funding_Rate": NaN,
      "OKX_Open_Interest": NaN,
      "OKX_Open_Interest_USD": NaN,
      "OKX_OI_Change_Pct": NaN,
      "OKX_External_Stress": 0.0,
      "OKX_Funding_Bias": "NEUTRAL",
      "Drift": 0.01968430438847674,
      "Decay_Integral": 0.8185866531045649,
      "Inflection_Detected": false,
      "ZF_Score": 0.706623329767511,
      "Previous_Direction": "SELL",
      "Previous_Drift": 0.02212122672238969,
      "Previous_ZF_Score": 0.7016787486021874,
      "Previous_Lambda_Liquidity": 1.0300000000002416,
      "Previous_Liquidity_Status": "STRESSED",
      "Delta_Drift": -0.0024369223339129505,
      "Delta_ZF_Score": 0.004944581165323592,
      "Delta_Lambda": -7.771561172376096e-13,
      "Direction_Changed": false,
      "Liquidity_Status_Changed": false,
      "Memory_Status": "LAMINAR",
      "Risk_Mode": "NORMAL",
      "Trade_Allowed": true,
      "Action_Signal": "EKSEKUSI",
      "Risk_Note": "",
      "Session_Phase": "STRESSED",
      "User_Recommendation": "Setup SELL valid. Entry manual boleh dipertimbangkan dengan SL/TP yang tampil. Akurasi historis resolved sekitar 81.25%.",
      "Historical_Status": "TRADEABLE",
      "Historical_Expectancy_R": 0.633,
      "Historical_Win_Rate": 81.25,
      "Historical_Signals": 17,
      "Live_Expectancy_R": NaN,
      "Live_Signals": 0,
      "Market_Session": "THIN_SESSION",
      "Accuracy_Quality_Score": 65.17,
      "Accuracy_Gate": "PASS",
      "Accuracy_Gate_Reason": "",
      "Ranking_Score": 83.92541664883755
    },
    {
      "Symbol": "CADCHFm",
      "Asset_Class": "forex",
      "Timeframe": "M15",
      "Exit_Mode": "DYNAMIC_SL_TP",
      "Expected_Hold_Hours": 7.28,
      "Close": 0.56641,
      "Bid": 0.56641,
      "Ask": 0.56649,
      "Mid_Price": 0.56645,
      "Direction": "BUY",
      "Projected_Direction": "NEUTRAL",
      "Signal_Type": "STRICT",
      "Setup_Maturity": 1.25,
      "Projection_Score": 0.9473,
      "Projection_Price_Slope": 2.6571428571429867e-05,
      "Regime": "RANGE",
      "Confidence": 83,
      "Optimizer_Mode": "DEFAULT",
      "Optimizer_Confidence_Floor": 60,
      "Optimizer_Max_Spread_Pips": 3.0,
      "Optimizer_Max_Slippage_Pips": 2.0,
      "Optimizer_Projection_Maturity_Floor": 0.55,
      "Optimizer_Projection_ZF_Floor": 0.45,
      "Optimizer_Projection_Confidence_Floor": 58,
      "Historical_Optimizer_ZF_Floor": 0.5,
      "Kelly_Full": 0.0,
      "Kelly_Risk_Multiplier": 0.5,
      "Dynamic_Lot": 1.0,
      "Entry_Price": 0.56638,
      "Entry_Model": "ZF_FIBO_BUY_LIMIT",
      "SL_Pips": 7.0,
      "SL_Points": 70.0,
      "SL_Price": 0.56568,
      "SL_Model": "DATA_DRIVEN",
      "TP_Pips": 8.8,
      "TP_Points": 88.0,
      "TP_Price": 0.56726,
      "TP_Model": "DATA_DRIVEN",
      "RR_Ratio": 1.25,
      "Spread_Pips": 0.8000000000008001,
      "Slippage_Est_Pips": 0.7,
      "Bid_Depth": 0.0,
      "Ask_Depth": 0.0,
      "Total_Depth": 0.0,
      "Depth_Imbalance": 0.0,
      "Depth_Available": false,
      "Liquidity_Cluster_Price": NaN,
      "Liquidity_Cluster_Volume": 0.0,
      "Liquidity_Stress": 0.5800000000002801,
      "Liquidity_Status": "LAMINAR",
      "Liquidity_Void": false,
      "Lambda_Liquidity": 0.68000000000028,
      "Fibo_Position": 0.5102,
      "Fibo_Aligned": true,
      "Fibo_382": 0.56603,
      "Fibo_500": 0.56638,
      "Fibo_618": 0.56673,
      "Metal_Gate_Ok": true,
      "OKX_Status": "NOT_CRYPTO",
      "OKX_Instrument": "",
      "OKX_Last": NaN,
      "OKX_Funding_Rate": NaN,
      "OKX_Open_Interest": NaN,
      "OKX_Open_Interest_USD": NaN,
      "OKX_OI_Change_Pct": NaN,
      "OKX_External_Stress": 0.0,
      "OKX_Funding_Bias": "NEUTRAL",
      "Drift": 0.022408697331722807,
      "Decay_Integral": -0.5510120154852018,
      "Inflection_Detected": true,
      "ZF_Score": 0.6361287492039137,
      "Previous_Direction": "BUY",
      "Previous_Drift": 0.029096676528454303,
      "Previous_ZF_Score": 0.6215795048271906,
      "Previous_Lambda_Liquidity": 0.6799999999998914,
      "Previous_Liquidity_Status": "LAMINAR",
      "Delta_Drift": -0.006687979196731496,
      "Delta_ZF_Score": 0.014549244376723114,
      "Delta_Lambda": 3.886890809212673e-13,
      "Direction_Changed": false,
      "Liquidity_Status_Changed": false,
      "Memory_Status": "LAMINAR",
      "Risk_Mode": "NORMAL",
      "Trade_Allowed": true,
      "Action_Signal": "EKSEKUSI",
      "Risk_Note": "",
      "Session_Phase": "LAMINAR",
      "User_Recommendation": "Setup BUY valid. Entry manual boleh dipertimbangkan dengan SL/TP yang tampil. Akurasi historis resolved sekitar 81.25%.",
      "Historical_Status": "TRADEABLE",
      "Historical_Expectancy_R": 0.3989,
      "Historical_Win_Rate": 81.25,
      "Historical_Signals": 17,
      "Live_Expectancy_R": NaN,
      "Live_Signals": 0,
      "Market_Session": "THIN_SESSION",
      "Accuracy_Quality_Score": 75.12,
      "Accuracy_Gate": "PASS",
      "Accuracy_Gate_Reason": "",
      "Ranking_Score": 89.12784374601956
    },
    {
      "Symbol": "GBPNZDm",
      "Asset_Class": "forex",
      "Timeframe": "M15",
      "Exit_Mode": "DYNAMIC_SL_TP",
      "Expected_Hold_Hours": 3.43,
      "Close": 2.2981,
      "Bid": 2.2981,
      "Ask": 2.29834,
      "Mid_Price": 2.2982199999999997,
      "Direction": "BUY",
      "Projected_Direction": "NEUTRAL",
      "Signal_Type": "STRICT",
      "Setup_Maturity": 1.1069,
      "Projection_Score": 0.8919,
      "Projection_Price_Slope": -0.0002208571428572279,
      "Regime": "RANGE",
      "Confidence": 73,
      "Optimizer_Mode": "DEFAULT",
      "Optimizer_Confidence_Floor": 60,
      "Optimizer_Max_Spread_Pips": 3.0,
      "Optimizer_Max_Slippage_Pips": 2.0,
      "Optimizer_Projection_Maturity_Floor": 0.55,
      "Optimizer_Projection_ZF_Floor": 0.45,
      "Optimizer_Projection_Confidence_Floor": 58,
      "Historical_Optimizer_ZF_Floor": 0.55,
      "Kelly_Full": 0.0,
      "Kelly_Risk_Multiplier": 0.5,
      "Dynamic_Lot": 0.0,
      "Entry_Price": 2.2981,
      "Entry_Model": "ZF_FIBO_BUY_LIMIT",
      "SL_Pips": 16.2,
      "SL_Points": 162.0,
      "SL_Price": 2.29648,
      "SL_Model": "DATA_DRIVEN",
      "TP_Pips": 20.5,
      "TP_Points": 205.0,
      "TP_Price": 2.30015,
      "TP_Model": "DATA_DRIVEN",
      "RR_Ratio": 1.26,
      "Spread_Pips": 2.4000000000023998,
      "Slippage_Est_Pips": 2.1,
      "Bid_Depth": 0.0,
      "Ask_Depth": 0.0,
      "Total_Depth": 0.0,
      "Depth_Imbalance": 0.0,
      "Depth_Available": false,
      "Liquidity_Cluster_Price": NaN,
      "Liquidity_Cluster_Volume": 0.0,
      "Liquidity_Stress": 1.0,
      "Liquidity_Status": "STRESSED",
      "Liquidity_Void": false,
      "Lambda_Liquidity": 1.1,
      "Fibo_Position": 0.0789,
      "Fibo_Aligned": true,
      "Fibo_382": 2.30136,
      "Fibo_500": 2.30263,
      "Fibo_618": 2.30391,
      "Metal_Gate_Ok": true,
      "OKX_Status": "NOT_CRYPTO",
      "OKX_Instrument": "",
      "OKX_Last": NaN,
      "OKX_Funding_Rate": NaN,
      "OKX_Open_Interest": NaN,
      "OKX_Open_Interest_USD": NaN,
      "OKX_OI_Change_Pct": NaN,
      "OKX_External_Stress": 0.0,
      "OKX_Funding_Bias": "NEUTRAL",
      "Drift": 0.011892409717794847,
      "Decay_Integral": -0.6834708061604616,
      "Inflection_Detected": true,
      "ZF_Score": 0.7535435450176948,
      "Previous_Direction": "BUY",
      "Previous_Drift": 0.014047762972193328,
      "Previous_ZF_Score": 0.7500447840260582,
      "Previous_Lambda_Liquidity": 1.1,
      "Previous_Liquidity_Status": "STRESSED",
      "Delta_Drift": -0.00215535325439848,
      "Delta_ZF_Score": 0.003498760991636596,
      "Delta_Lambda": 0.0,
      "Direction_Changed": false,
      "Liquidity_Status_Changed": false,
      "Memory_Status": "LAMINAR",
      "Risk_Mode": "SLIPPAGE_LOCK",
      "Trade_Allowed": false,
      "Action_Signal": "TUNGGU SLIPPAGE",
      "Risk_Note": "Estimasi slippage melebihi batas.",
      "Session_Phase": "STRESSED",
      "User_Recommendation": "Jangan entry. Risiko slippage terlalu besar.",
      "Historical_Status": "TRADEABLE",
      "Historical_Expectancy_R": 0.3584,
      "Historical_Win_Rate": 73.33,
      "Historical_Signals": 15,
      "Live_Expectancy_R": NaN,
      "Live_Signals": 0,
      "Market_Session": "THIN_SESSION",
      "Accuracy_Quality_Score": 57.97,
      "Accuracy_Gate": "PASS",
      "Accuracy_Gate_Reason": "",
      "Ranking_Score": 75.23521772508848
    },
    {
      "Symbol": "USDCHFm",
      "Asset_Class": "forex",
      "Timeframe": "M15",
      "Exit_Mode": "DYNAMIC_SL_TP",
      "Expected_Hold_Hours": 7.1,
      "Close": 0.79874,
      "Bid": 0.79874,
      "Ask": 0.79887,
      "Mid_Price": 0.798805,
      "Direction": "NEUTRAL",
      "Projected_Direction": "NEUTRAL",
      "Signal_Type": "FIBO_BLOCK",
      "Setup_Maturity": 1.25,
      "Projection_Score": 0.9756,
      "Projection_Price_Slope": -2.0571428571475973e-05,
      "Regime": "RANGE",
      "Confidence": 0,
      "Optimizer_Mode": "DEFAULT",
      "Optimizer_Confidence_Floor": 60,
      "Optimizer_Max_Spread_Pips": 3.0,
      "Optimizer_Max_Slippage_Pips": 2.0,
      "Optimizer_Projection_Maturity_Floor": 0.55,
      "Optimizer_Projection_ZF_Floor": 0.45,
      "Optimizer_Projection_Confidence_Floor": 58,
      "Historical_Optimizer_ZF_Floor": 0.5,
      "Kelly_Full": 0.0,
      "Kelly_Risk_Multiplier": 0.5,
      "Dynamic_Lot": 0.0,
      "Entry_Price": 0.79874,
      "Entry_Model": "MARKET_REFERENCE",
      "SL_Pips": 9.6,
      "SL_Points": 96.0,
      "SL_Price": NaN,
      "SL_Model": "DATA_DRIVEN",
      "TP_Pips": 0.0,
      "TP_Points": 0.0,
      "TP_Price": NaN,
      "TP_Model": "NO_SIGNAL",
      "RR_Ratio": 0.0,
      "Spread_Pips": 1.2999999999996346,
      "Slippage_Est_Pips": 1.14,
      "Bid_Depth": 0.0,
      "Ask_Depth": 0.0,
      "Total_Depth": 0.0,
      "Depth_Imbalance": 0.0,
      "Depth_Available": false,
      "Liquidity_Cluster_Price": NaN,
      "Liquidity_Cluster_Volume": 0.0,
      "Liquidity_Stress": 0.754999999999872,
      "Liquidity_Status": "STRESSED",
      "Liquidity_Void": false,
      "Lambda_Liquidity": 0.854999999999872,
      "Fibo_Position": 0.7402,
      "Fibo_Aligned": false,
      "Fibo_382": 0.79497,
      "Fibo_500": 0.79622,
      "Fibo_618": 0.79746,
      "Metal_Gate_Ok": true,
      "OKX_Status": "NOT_CRYPTO",
      "OKX_Instrument": "",
      "OKX_Last": NaN,
      "OKX_Funding_Rate": NaN,
      "OKX_Open_Interest": NaN,
      "OKX_Open_Interest_USD": NaN,
      "OKX_OI_Change_Pct": NaN,
      "OKX_External_Stress": 0.0,
      "OKX_Funding_Bias": "NEUTRAL",
      "Drift": 0.01838805614546702,
      "Decay_Integral": -1.3743146329015625,
      "Inflection_Detected": true,
      "ZF_Score": 0.6775479343060552,
      "Previous_Direction": "NEUTRAL",
      "Previous_Drift": 0.010387680767359492,
      "Previous_ZF_Score": 0.6852583658739988,
      "Previous_Lambda_Liquidity": 0.854999999999872,
      "Previous_Liquidity_Status": "STRESSED",
      "Delta_Drift": 0.008000375378107528,
      "Delta_ZF_Score": -0.007710431567943599,
      "Delta_Lambda": 0.0,
      "Direction_Changed": false,
      "Liquidity_Status_Changed": false,
      "Memory_Status": "LAMINAR",
      "Risk_Mode": "NORMAL",
      "Trade_Allowed": false,
      "Action_Signal": "STANDBY",
      "Risk_Note": "",
      "Session_Phase": "STRESSED",
      "User_Recommendation": "Tidak ada entry. Tunggu sinyal BUY/SELL berikutnya.",
      "Historical_Status": "TRADEABLE",
      "Historical_Expectancy_R": 0.2677,
      "Historical_Win_Rate": 65.22,
      "Historical_Signals": 29,
      "Live_Expectancy_R": NaN,
      "Live_Signals": 0,
      "Market_Session": "THIN_SESSION",
      "Accuracy_Quality_Score": 39.89,
      "Accuracy_Gate": "NEUTRAL",
      "Accuracy_Gate_Reason": "Belum ada arah BUY/SELL matang.",
      "Ranking_Score": 52.68643967153027
    },
    {
      "Symbol": "BTCJPYm",
      "Asset_Class": "crypto",
      "Timeframe": "M15",
      "Exit_Mode": "DYNAMIC_SL_TP",
      "Expected_Hold_Hours": 4.88,
      "Close": 10374186.0,
      "Bid": 10374186.0,
      "Ask": 10376425.0,
      "Mid_Price": 10375305.5,
      "Direction": "NEUTRAL",
      "Projected_Direction": "NEUTRAL",
      "Signal_Type": "NEUTRAL",
      "Setup_Maturity": 0.5395,
      "Projection_Score": 0.5671,
      "Projection_Price_Slope": 3596.371428571254,
      "Regime": "RANGE",
      "Confidence": 0,
      "Optimizer_Mode": "DEFAULT",
      "Optimizer_Confidence_Floor": 60,
      "Optimizer_Max_Spread_Pips": 3.0,
      "Optimizer_Max_Slippage_Pips": 2.0,
      "Optimizer_Projection_Maturity_Floor": 0.55,
      "Optimizer_Projection_ZF_Floor": 0.45,
      "Optimizer_Projection_Confidence_Floor": 58,
      "Historical_Optimizer_ZF_Floor": 0.55,
      "Kelly_Full": 0.0,
      "Kelly_Risk_Multiplier": 0.5,
      "Dynamic_Lot": 0.0,
      "Entry_Price": 10374186.0,
      "Entry_Model": "MARKET_REFERENCE",
      "SL_Pips": 33523.2,
      "SL_Points": 33523.0,
      "SL_Price": NaN,
      "SL_Model": "DATA_DRIVEN",
      "TP_Pips": 0.0,
      "TP_Points": 0.0,
      "TP_Price": NaN,
      "TP_Model": "NO_SIGNAL",
      "RR_Ratio": 0.0,
      "Spread_Pips": 2239.0,
      "Slippage_Est_Pips": 1959.12,
      "Bid_Depth": 0.0,
      "Ask_Depth": 0.0,
      "Total_Depth": 0.0,
      "Depth_Imbalance": 0.0,
      "Depth_Available": false,
      "Liquidity_Cluster_Price": NaN,
      "Liquidity_Cluster_Volume": 0.0,
      "Liquidity_Stress": 1.0,
      "Liquidity_Status": "VOID",
      "Liquidity_Void": true,
      "Lambda_Liquidity": 1.1,
      "Fibo_Position": 0.3074,
      "Fibo_Aligned": false,
      "Fibo_382": 10402547.252,
      "Fibo_500": 10447421.0,
      "Fibo_618": 10492294.748,
      "Metal_Gate_Ok": true,
      "OKX_Status": "ERROR: HTTPSConnectionPool(host='www.okx.com', port=443): Max retries exceeded with url: /api/v5/market/ticker?instId=BTC-USDT-SWAP (Caused by SSLError(SSLCertVerificationError(1, \"[SSL: CERTIFICATE_VERIFY_FAILED] certificate verify failed: Hostname mismatch, certificate is not valid for 'www.okx.com'. (_ssl.c:1081)\")))",
      "OKX_Instrument": "BTC-USDT-SWAP",
      "OKX_Last": NaN,
      "OKX_Funding_Rate": NaN,
      "OKX_Open_Interest": NaN,
      "OKX_Open_Interest_USD": NaN,
      "OKX_OI_Change_Pct": NaN,
      "OKX_External_Stress": 0.0,
      "OKX_Funding_Bias": "NEUTRAL",
      "Drift": 0.06432164063665785,
      "Decay_Integral": 3.312799082059643,
      "Inflection_Detected": true,
      "ZF_Score": 0.5708346122639283,
      "Previous_Direction": "NEUTRAL",
      "Previous_Drift": 0.014865866732361588,
      "Previous_ZF_Score": 0.584594574324589,
      "Previous_Lambda_Liquidity": 1.1,
      "Previous_Liquidity_Status": "VOID",
      "Delta_Drift": 0.049455773904296264,
      "Delta_ZF_Score": -0.013759962060660658,
      "Delta_Lambda": 0.0,
      "Direction_Changed": false,
      "Liquidity_Status_Changed": false,
      "Memory_Status": "LAMINAR",
      "Risk_Mode": "LIQUIDITY_LOCK",
      "Trade_Allowed": false,
      "Action_Signal": "PERTAHANAN LIKUIDITAS",
      "Risk_Note": "Liquidity void atau spread terlalu lebar.",
      "Session_Phase": "ANOMALOUS",
      "User_Recommendation": "Jangan entry. Likuiditas/spread sedang tidak sehat.",
      "Historical_Status": "TRADEABLE",
      "Historical_Expectancy_R": 0.1932,
      "Historical_Win_Rate": 68.75,
      "Historical_Signals": 16,
      "Live_Expectancy_R": NaN,
      "Live_Signals": 0,
      "Market_Session": "THIN_SESSION",
      "Accuracy_Quality_Score": 11.4,
      "Accuracy_Gate": "NEUTRAL",
      "Accuracy_Gate_Reason": "Belum ada arah BUY/SELL matang.",
      "Ranking_Score": 24.801773061319643
    },
    {
      "Symbol": "BTCCNHm",
      "Asset_Class": "crypto",
      "Timeframe": "M15",
      "Exit_Mode": "DYNAMIC_SL_TP",
      "Expected_Hold_Hours": 6.94,
      "Close": 436900.1,
      "Bid": 436900.1,
      "Ask": 437204.2,
      "Mid_Price": 437052.15,
      "Direction": "NEUTRAL",
      "Projected_Direction": "NEUTRAL",
      "Signal_Type": "NEUTRAL",
      "Setup_Maturity": 0.5225,
      "Projection_Score": 0.559,
      "Projection_Price_Slope": 146.07714285713988,
      "Regime": "RANGE",
      "Confidence": 0,
      "Optimizer_Mode": "DEFAULT",
      "Optimizer_Confidence_Floor": 60,
      "Optimizer_Max_Spread_Pips": 3.0,
      "Optimizer_Max_Slippage_Pips": 2.0,
      "Optimizer_Projection_Maturity_Floor": 0.55,
      "Optimizer_Projection_ZF_Floor": 0.45,
      "Optimizer_Projection_Confidence_Floor": 58,
      "Historical_Optimizer_ZF_Floor": 0.45,
      "Kelly_Full": 0.0,
      "Kelly_Risk_Multiplier": 0.5,
      "Dynamic_Lot": 0.0,
      "Entry_Price": 436900.1,
      "Entry_Model": "MARKET_REFERENCE",
      "SL_Pips": 13965.6,
      "SL_Points": 13966.0,
      "SL_Price": NaN,
      "SL_Model": "DATA_DRIVEN",
      "TP_Pips": 0.0,
      "TP_Points": 0.0,
      "TP_Price": NaN,
      "TP_Model": "NO_SIGNAL",
      "RR_Ratio": 0.0,
      "Spread_Pips": 3041.0000000003492,
      "Slippage_Est_Pips": 2660.88,
      "Bid_Depth": 0.0,
      "Ask_Depth": 0.0,
      "Total_Depth": 0.0,
      "Depth_Imbalance": 0.0,
      "Depth_Available": false,
      "Liquidity_Cluster_Price": NaN,
      "Liquidity_Cluster_Volume": 0.0,
      "Liquidity_Stress": 1.0,
      "Liquidity_Status": "VOID",
      "Liquidity_Void": true,
      "Lambda_Liquidity": 1.1,
      "Fibo_Position": 0.2719,
      "Fibo_Aligned": false,
      "Fibo_382": 438679.3,
      "Fibo_500": 440585.7,
      "Fibo_618": 442492.0,
      "Metal_Gate_Ok": true,
      "OKX_Status": "ERROR: HTTPSConnectionPool(host='www.okx.com', port=443): Max retries exceeded with url: /api/v5/market/ticker?instId=BTC-USDT-SWAP (Caused by SSLError(SSLCertVerificationError(1, \"[SSL: CERTIFICATE_VERIFY_FAILED] certificate verify failed: Hostname mismatch, certificate is not valid for 'www.okx.com'. (_ssl.c:1081)\")))",
      "OKX_Instrument": "BTC-USDT-SWAP",
      "OKX_Last": NaN,
      "OKX_Funding_Rate": NaN,
      "OKX_Open_Interest": NaN,
      "OKX_Open_Interest_USD": NaN,
      "OKX_OI_Change_Pct": NaN,
      "OKX_External_Stress": 0.0,
      "OKX_Funding_Bias": "NEUTRAL",
      "Drift": 0.0487908384417385,
      "Decay_Integral": 3.0814630366161366,
      "Inflection_Detected": true,
      "ZF_Score": 0.5750376998186797,
      "Previous_Direction": "NEUTRAL",
      "Previous_Drift": 0.035664106292022095,
      "Previous_ZF_Score": 0.5800338512750964,
      "Previous_Lambda_Liquidity": 1.1,
      "Previous_Liquidity_Status": "VOID",
      "Delta_Drift": 0.013126732149716408,
      "Delta_ZF_Score": -0.004996151456416742,
      "Delta_Lambda": 0.0,
      "Direction_Changed": false,
      "Liquidity_Status_Changed": false,
      "Memory_Status": "LAMINAR",
      "Risk_Mode": "LIQUIDITY_LOCK",
      "Trade_Allowed": false,
      "Action_Signal": "PERTAHANAN LIKUIDITAS",
      "Risk_Note": "Liquidity void atau spread terlalu lebar.",
      "Session_Phase": "ANOMALOUS",
      "User_Recommendation": "Jangan entry. Likuiditas/spread sedang tidak sehat.",
      "Historical_Status": "TRADEABLE",
      "Historical_Expectancy_R": 0.1491,
      "Historical_Win_Rate": 71.43,
      "Historical_Signals": 16,
      "Live_Expectancy_R": NaN,
      "Live_Signals": 0,
      "Market_Session": "THIN_SESSION",
      "Accuracy_Quality_Score": 10.97,
      "Accuracy_Gate": "NEUTRAL",
      "Accuracy_Gate_Reason": "Belum ada arah BUY/SELL matang.",
      "Ranking_Score": 24.175888499093396
    },
    {
      "Symbol": "AUDJPYm",
      "Asset_Class": "forex",
      "Timeframe": "M15",
      "Exit_Mode": "DYNAMIC_SL_TP",
      "Expected_Hold_Hours": 2.83,
      "Close": 112.982,
      "Bid": 112.982,
      "Ask": 113.001,
      "Mid_Price": 112.9915,
      "Direction": "SELL",
      "Projected_Direction": "NEUTRAL",
      "Signal_Type": "STRICT",
      "Setup_Maturity": 1.1404,
      "Projection_Score": 0.9144,
      "Projection_Price_Slope": 0.007628571428571847,
      "Regime": "TREND",
      "Confidence": 73,
      "Optimizer_Mode": "DEFAULT",
      "Optimizer_Confidence_Floor": 60,
      "Optimizer_Max_Spread_Pips": 3.0,
      "Optimizer_Max_Slippage_Pips": 2.0,
      "Optimizer_Projection_Maturity_Floor": 0.55,
      "Optimizer_Projection_ZF_Floor": 0.45,
      "Optimizer_Projection_Confidence_Floor": 58,
      "Historical_Optimizer_ZF_Floor": 0.5,
      "Kelly_Full": 0.0,
      "Kelly_Risk_Multiplier": 0.5,
      "Dynamic_Lot": 0.47,
      "Entry_Price": 112.982,
      "Entry_Model": "ZF_FIBO_SELL_LIMIT",
      "SL_Pips": 16.1,
      "SL_Points": 161.0,
      "SL_Price": 113.143,
      "SL_Model": "DATA_DRIVEN",
      "TP_Pips": 20.1,
      "TP_Points": 201.0,
      "TP_Price": 112.781,
      "TP_Model": "DATA_DRIVEN",
      "RR_Ratio": 1.25,
      "Spread_Pips": 1.9000000000005457,
      "Slippage_Est_Pips": 1.66,
      "Bid_Depth": 0.0,
      "Ask_Depth": 0.0,
      "Total_Depth": 0.0,
      "Depth_Imbalance": 0.0,
      "Depth_Available": false,
      "Liquidity_Cluster_Price": NaN,
      "Liquidity_Cluster_Volume": 0.0,
      "Liquidity_Stress": 0.965000000000191,
      "Liquidity_Status": "STRESSED",
      "Liquidity_Void": false,
      "Lambda_Liquidity": 1.0650000000001911,
      "Fibo_Position": 0.5844,
      "Fibo_Aligned": true,
      "Fibo_382": 112.803,
      "Fibo_500": 112.907,
      "Fibo_618": 113.012,
      "Metal_Gate_Ok": true,
      "OKX_Status": "NOT_CRYPTO",
      "OKX_Instrument": "",
      "OKX_Last": NaN,
      "OKX_Funding_Rate": NaN,
      "OKX_Open_Interest": NaN,
      "OKX_Open_Interest_USD": NaN,
      "OKX_OI_Change_Pct": NaN,
      "OKX_External_Stress": 0.0,
      "OKX_Funding_Bias": "NEUTRAL",
      "Drift": 0.029728934615042814,
      "Decay_Integral": 1.4475336783555564,
      "Inflection_Detected": true,
      "ZF_Score": 0.7132508430258597,
      "Previous_Direction": "NEUTRAL",
      "Previous_Drift": 0.026365582021563708,
      "Previous_ZF_Score": 0.7173023527675342,
      "Previous_Lambda_Liquidity": 1.0649999999996937,
      "Previous_Liquidity_Status": "STRESSED",
      "Delta_Drift": 0.003363352593479106,
      "Delta_ZF_Score": -0.004051509741674453,
      "Delta_Lambda": 4.973799150320701e-13,
      "Direction_Changed": true,
      "Liquidity_Status_Changed": false,
      "Memory_Status": "RESONANCE_MISMATCH",
      "Risk_Mode": "NORMAL",
      "Trade_Allowed": true,
      "Action_Signal": "EKSEKUSI",
      "Risk_Note": "",
      "Session_Phase": "ANOMALOUS",
      "User_Recommendation": "Setup SELL valid. Entry manual boleh dipertimbangkan dengan SL/TP yang tampil. Akurasi historis resolved sekitar 63.16%.",
      "Historical_Status": "TRADEABLE",
      "Historical_Expectancy_R": 0.1447,
      "Historical_Win_Rate": 63.16,
      "Historical_Signals": 21,
      "Live_Expectancy_R": NaN,
      "Live_Signals": 0,
      "Market_Session": "THIN_SESSION",
      "Accuracy_Quality_Score": 56.5,
      "Accuracy_Gate": "PASS",
      "Accuracy_Gate_Reason": "",
      "Ranking_Score": 72.23805421512931
    },
    {
      "Symbol": "EURCADm",
      "Asset_Class": "forex",
      "Timeframe": "M15",
      "Exit_Mode": "DYNAMIC_SL_TP",
      "Expected_Hold_Hours": 6.71,
      "Close": 1.62416,
      "Bid": 1.62416,
      "Ask": 1.62431,
      "Mid_Price": 1.624235,
      "Direction": "SELL",
      "Projected_Direction": "NEUTRAL",
      "Signal_Type": "STRICT",
      "Setup_Maturity": 1.0626,
      "Projection_Score": 0.849,
      "Projection_Price_Slope": -2.6571428571286807e-05,
      "Regime": "TREND",
      "Confidence": 73,
      "Optimizer_Mode": "DEFAULT",
      "Optimizer_Confidence_Floor": 60,
      "Optimizer_Max_Spread_Pips": 3.0,
      "Optimizer_Max_Slippage_Pips": 2.0,
      "Optimizer_Projection_Maturity_Floor": 0.55,
      "Optimizer_Projection_ZF_Floor": 0.45,
      "Optimizer_Projection_Confidence_Floor": 58,
      "Historical_Optimizer_ZF_Floor": 0.5,
      "Kelly_Full": 0.0,
      "Kelly_Risk_Multiplier": 0.5,
      "Dynamic_Lot": 0.0,
      "Entry_Price": 1.62416,
      "Entry_Model": "ZF_FIBO_SELL_LIMIT",
      "SL_Pips": 13.5,
      "SL_Points": 135.0,
      "SL_Price": 1.62551,
      "SL_Model": "DATA_DRIVEN",
      "TP_Pips": 16.9,
      "TP_Points": 169.0,
      "TP_Price": 1.62247,
      "TP_Model": "DATA_DRIVEN",
      "RR_Ratio": 1.25,
      "Spread_Pips": 1.4999999999987244,
      "Slippage_Est_Pips": 1.31,
      "Bid_Depth": 0.0,
      "Ask_Depth": 0.0,
      "Total_Depth": 0.0,
      "Depth_Imbalance": 0.0,
      "Depth_Available": false,
      "Liquidity_Cluster_Price": NaN,
      "Liquidity_Cluster_Volume": 0.0,
      "Liquidity_Stress": 0.8249999999995534,
      "Liquidity_Status": "STRESSED",
      "Liquidity_Void": false,
      "Lambda_Liquidity": 0.9249999999995534,
      "Fibo_Position": 0.6115,
      "Fibo_Aligned": true,
      "Fibo_382": 1.62256,
      "Fibo_500": 1.62338,
      "Fibo_618": 1.62421,
      "Metal_Gate_Ok": true,
      "OKX_Status": "NOT_CRYPTO",
      "OKX_Instrument": "",
      "OKX_Last": NaN,
      "OKX_Funding_Rate": NaN,
      "OKX_Open_Interest": NaN,
      "OKX_Open_Interest_USD": NaN,
      "OKX_OI_Change_Pct": NaN,
      "OKX_External_Stress": 0.0,
      "OKX_Funding_Bias": "NEUTRAL",
      "Drift": 0.0211374622153641,
      "Decay_Integral": 0.6747653323120659,
      "Inflection_Detected": true,
      "ZF_Score": 0.6814970376344455,
      "Previous_Direction": "NEUTRAL",
      "Previous_Drift": 0.025077044247348888,
      "Previous_ZF_Score": 0.6715034015147018,
      "Previous_Lambda_Liquidity": 0.9249999999995534,
      "Previous_Liquidity_Status": "STRESSED",
      "Delta_Drift": -0.003939582031984787,
      "Delta_ZF_Score": 0.009993636119743687,
      "Delta_Lambda": 0.0,
      "Direction_Changed": true,
      "Liquidity_Status_Changed": false,
      "Memory_Status": "RESONANCE_MISMATCH",
      "Risk_Mode": "ACCURACY_LOCK",
      "Trade_Allowed": false,
      "Action_Signal": "TUNGGU AKURASI",
      "Risk_Note": "winrate historis 56.25% < 58.00%",
      "Session_Phase": "ANOMALOUS",
      "User_Recommendation": "Jangan entry dulu. Sinyal ditahan oleh mode akurasi ketat. Alasan: winrate historis 56.25% < 58.00%.",
      "Historical_Status": "TRADEABLE",
      "Historical_Expectancy_R": 0.1091,
      "Historical_Win_Rate": 56.25,
      "Historical_Signals": 17,
      "Live_Expectancy_R": NaN,
      "Live_Signals": 0,
      "Market_Session": "THIN_SESSION",
      "Accuracy_Quality_Score": 57.73,
      "Accuracy_Gate": "LOCKED",
      "Accuracy_Gate_Reason": "winrate historis 56.25% < 58.00%",
      "Ranking_Score": 70.67338518817223
    },
    {
      "Symbol": "BTCUSDm",
      "Asset_Class": "crypto",
      "Timeframe": "M15",
      "Exit_Mode": "DYNAMIC_SL_TP",
      "Expected_Hold_Hours": 3.76,
      "Close": 64608.07,
      "Bid": 64606.86,
      "Ask": 64616.86,
      "Mid_Price": 64611.86,
      "Direction": "NEUTRAL",
      "Projected_Direction": "NEUTRAL",
      "Signal_Type": "NEUTRAL",
      "Setup_Maturity": 0.6308,
      "Projection_Score": 0.6365,
      "Projection_Price_Slope": 28.207428571429677,
      "Regime": "RANGE",
      "Confidence": 0,
      "Optimizer_Mode": "DEFAULT",
      "Optimizer_Confidence_Floor": 60,
      "Optimizer_Max_Spread_Pips": 3.0,
      "Optimizer_Max_Slippage_Pips": 2.0,
      "Optimizer_Projection_Maturity_Floor": 0.55,
      "Optimizer_Projection_ZF_Floor": 0.45,
      "Optimizer_Projection_Confidence_Floor": 58,
      "Historical_Optimizer_ZF_Floor": 0.45,
      "Kelly_Full": 0.0,
      "Kelly_Risk_Multiplier": 0.5,
      "Dynamic_Lot": 0.0,
      "Entry_Price": 64608.07,
      "Entry_Model": "MARKET_REFERENCE",
      "SL_Pips": 21127.9,
      "SL_Points": 21128.0,
      "SL_Price": NaN,
      "SL_Model": "DATA_DRIVEN",
      "TP_Pips": 0.0,
      "TP_Points": 0.0,
      "TP_Price": NaN,
      "TP_Model": "NO_SIGNAL",
      "RR_Ratio": 0.0,
      "Spread_Pips": 1000.0,
      "Slippage_Est_Pips": 875.0,
      "Bid_Depth": 0.0,
      "Ask_Depth": 0.0,
      "Total_Depth": 0.0,
      "Depth_Imbalance": 0.0,
      "Depth_Available": false,
      "Liquidity_Cluster_Price": NaN,
      "Liquidity_Cluster_Volume": 0.0,
      "Liquidity_Stress": 1.0,
      "Liquidity_Status": "VOID",
      "Liquidity_Void": true,
      "Lambda_Liquidity": 1.1,
      "Fibo_Position": 0.297,
      "Fibo_Aligned": false,
      "Fibo_382": 64824.76,
      "Fibo_500": 65125.57,
      "Fibo_618": 65426.38,
      "Metal_Gate_Ok": true,
      "OKX_Status": "ERROR: HTTPSConnectionPool(host='www.okx.com', port=443): Max retries exceeded with url: /api/v5/market/ticker?instId=BTC-USDT-SWAP (Caused by ConnectTimeoutError(<HTTPSConnection(host='www.okx.com', port=443) at 0x202607f1a90>, 'Connection to www.okx.com timed out. (connect timeout=8.0)'))",
      "OKX_Instrument": "BTC-USDT-SWAP",
      "OKX_Last": NaN,
      "OKX_Funding_Rate": NaN,
      "OKX_Open_Interest": NaN,
      "OKX_Open_Interest_USD": NaN,
      "OKX_OI_Change_Pct": NaN,
      "OKX_External_Stress": 0.0,
      "OKX_Funding_Bias": "NEUTRAL",
      "Drift": 0.044904014889514225,
      "Decay_Integral": 3.943020015319399,
      "Inflection_Detected": true,
      "ZF_Score": 0.5743734731244589,
      "Previous_Direction": "NEUTRAL",
      "Previous_Drift": 0.04150532768218798,
      "Previous_ZF_Score": 0.5768545354756803,
      "Previous_Lambda_Liquidity": 1.1,
      "Previous_Liquidity_Status": "VOID",
      "Delta_Drift": 0.003398687207326244,
      "Delta_ZF_Score": -0.0024810623512214747,
      "Delta_Lambda": 0.0,
      "Direction_Changed": false,
      "Liquidity_Status_Changed": false,
      "Memory_Status": "LAMINAR",
      "Risk_Mode": "LIQUIDITY_LOCK",
      "Trade_Allowed": false,
      "Action_Signal": "PERTAHANAN LIKUIDITAS",
      "Risk_Note": "Liquidity void atau spread terlalu lebar.",
      "Session_Phase": "ANOMALOUS",
      "User_Recommendation": "Jangan entry. Likuiditas/spread sedang tidak sehat.",
      "Historical_Status": "TRADEABLE",
      "Historical_Expectancy_R": 0.089,
      "Historical_Win_Rate": 69.05,
      "Historical_Signals": 42,
      "Live_Expectancy_R": NaN,
      "Live_Signals": 0,
      "Market_Session": "THIN_SESSION",
      "Accuracy_Quality_Score": 11.5,
      "Accuracy_Gate": "NEUTRAL",
      "Accuracy_Gate_Reason": "Belum ada arah BUY/SELL matang.",
      "Ranking_Score": 25.525667365622294
    },
    {
      "Symbol": "USDCADm",
      "Asset_Class": "forex",
      "Timeframe": "M15",
      "Exit_Mode": "DYNAMIC_SL_TP",
      "Expected_Hold_Hours": 7.31,
      "Close": 1.41013,
      "Bid": 1.41013,
      "Ask": 1.4102700000000001,
      "Mid_Price": 1.4102000000000001,
      "Direction": "NEUTRAL",
      "Projected_Direction": "BUY",
      "Signal_Type": "FIBO_BLOCK",
      "Setup_Maturity": 1.25,
      "Projection_Score": 0.9814,
      "Projection_Price_Slope": -9.600000000000533e-05,
      "Regime": "RANGE",
      "Confidence": 0,
      "Optimizer_Mode": "DEFAULT",
      "Optimizer_Confidence_Floor": 60,
      "Optimizer_Max_Spread_Pips": 3.0,
      "Optimizer_Max_Slippage_Pips": 2.0,
      "Optimizer_Projection_Maturity_Floor": 0.55,
      "Optimizer_Projection_ZF_Floor": 0.45,
      "Optimizer_Projection_Confidence_Floor": 58,
      "Historical_Optimizer_ZF_Floor": 0.45,
      "Kelly_Full": 0.0,
      "Kelly_Risk_Multiplier": 0.5,
      "Dynamic_Lot": 0.0,
      "Entry_Price": 1.41013,
      "Entry_Model": "MARKET_REFERENCE",
      "SL_Pips": 10.2,
      "SL_Points": 102.0,
      "SL_Price": NaN,
      "SL_Model": "DATA_DRIVEN",
      "TP_Pips": 0.0,
      "TP_Points": 0.0,
      "TP_Price": NaN,
      "TP_Model": "NO_SIGNAL",
      "RR_Ratio": 0.0,
      "Spread_Pips": 1.4000000000002897,
      "Slippage_Est_Pips": 1.23,
      "Bid_Depth": 0.0,
      "Ask_Depth": 0.0,
      "Total_Depth": 0.0,
      "Depth_Imbalance": 0.0,
      "Depth_Available": false,
      "Liquidity_Cluster_Price": NaN,
      "Liquidity_Cluster_Volume": 0.0,
      "Liquidity_Stress": 0.7900000000001013,
      "Liquidity_Status": "STRESSED",
      "Liquidity_Void": false,
      "Lambda_Liquidity": 0.8900000000001013,
      "Fibo_Position": 0.8363,
      "Fibo_Aligned": false,
      "Fibo_382": 1.40436,
      "Fibo_500": 1.40585,
      "Fibo_618": 1.40735,
      "Metal_Gate_Ok": true,
      "OKX_Status": "NOT_CRYPTO",
      "OKX_Instrument": "",
      "OKX_Last": NaN,
      "OKX_Funding_Rate": NaN,
      "OKX_Open_Interest": NaN,
      "OKX_Open_Interest_USD": NaN,
      "OKX_OI_Change_Pct": NaN,
      "OKX_External_Stress": 0.0,
      "OKX_Funding_Bias": "NEUTRAL",
      "Drift": 0.004554906607800439,
      "Decay_Integral": -0.7249229607688354,
      "Inflection_Detected": true,
      "ZF_Score": 0.7217029355189268,
      "Previous_Direction": "NEUTRAL",
      "Previous_Drift": 0.018993412671449994,
      "Previous_ZF_Score": 0.6965907485997326,
      "Previous_Lambda_Liquidity": 0.8900000000001013,
      "Previous_Liquidity_Status": "STRESSED",
      "Delta_Drift": -0.014438506063649555,
      "Delta_ZF_Score": 0.025112186919194257,
      "Delta_Lambda": 0.0,
      "Direction_Changed": false,
      "Liquidity_Status_Changed": false,
      "Memory_Status": "LAMINAR",
      "Risk_Mode": "NORMAL",
      "Trade_Allowed": false,
      "Action_Signal": "STANDBY",
      "Risk_Note": "",
      "Session_Phase": "STRESSED",
      "User_Recommendation": "Tidak ada entry. Tunggu sinyal BUY/SELL berikutnya.",
      "Historical_Status": "TRADEABLE",
      "Historical_Expectancy_R": 0.0832,
      "Historical_Win_Rate": 63.64,
      "Historical_Signals": 24,
      "Live_Expectancy_R": NaN,
      "Live_Signals": 0,
      "Market_Session": "THIN_SESSION",
      "Accuracy_Quality_Score": 36.11,
      "Accuracy_Gate": "NEUTRAL",
      "Accuracy_Gate_Reason": "Belum ada arah BUY/SELL matang.",
      "Ranking_Score": 49.225814677594634
    },
    {
      "Symbol": "XAUUSDm",
      "Asset_Class": "metal",
      "Timeframe": "M15",
      "Exit_Mode": "DYNAMIC_SL_TP",
      "Expected_Hold_Hours": 3.2,
      "Close": 4311.05,
      "Bid": 4311.05,
      "Ask": 4311.33,
      "Mid_Price": 4311.1900000000005,
      "Direction": "NEUTRAL",
      "Projected_Direction": "NEUTRAL",
      "Signal_Type": "NEUTRAL",
      "Setup_Maturity": 0.6651,
      "Projection_Score": 0.6518,
      "Projection_Price_Slope": -2.601714285714155,
      "Regime": "TREND",
      "Confidence": 0,
      "Optimizer_Mode": "DEFAULT",
      "Optimizer_Confidence_Floor": 60,
      "Optimizer_Max_Spread_Pips": 3.0,
      "Optimizer_Max_Slippage_Pips": 2.0,
      "Optimizer_Projection_Maturity_Floor": 0.55,
      "Optimizer_Projection_ZF_Floor": 0.45,
      "Optimizer_Projection_Confidence_Floor": 58,
      "Historical_Optimizer_ZF_Floor": 0.45,
      "Kelly_Full": 0.0,
      "Kelly_Risk_Multiplier": 0.5,
      "Dynamic_Lot": 0.0,
      "Entry_Price": 4311.05,
      "Entry_Model": "MARKET_REFERENCE",
      "SL_Pips": 1667.6,
      "SL_Points": 16676.0,
      "SL_Price": NaN,
      "SL_Model": "DATA_DRIVEN",
      "TP_Pips": 0.0,
      "TP_Points": 0.0,
      "TP_Price": NaN,
      "TP_Model": "NO_SIGNAL",
      "RR_Ratio": 0.0,
      "Spread_Pips": 27.999999999974534,
      "Slippage_Est_Pips": 24.5,
      "Bid_Depth": 0.0,
      "Ask_Depth": 0.0,
      "Total_Depth": 0.0,
      "Depth_Imbalance": 0.0,
      "Depth_Available": false,
      "Liquidity_Cluster_Price": NaN,
      "Liquidity_Cluster_Volume": 0.0,
      "Liquidity_Stress": 1.0,
      "Liquidity_Status": "VOID",
      "Liquidity_Void": true,
      "Lambda_Liquidity": 1.1,
      "Fibo_Position": 0.5636,
      "Fibo_Aligned": false,
      "Fibo_382": 4281.331,
      "Fibo_500": 4300.637,
      "Fibo_618": 4319.942,
      "Metal_Gate_Ok": true,
      "OKX_Status": "NOT_CRYPTO",
      "OKX_Instrument": "",
      "OKX_Last": NaN,
      "OKX_Funding_Rate": NaN,
      "OKX_Open_Interest": NaN,
      "OKX_Open_Interest_USD": NaN,
      "OKX_OI_Change_Pct": NaN,
      "OKX_External_Stress": 0.0,
      "OKX_Funding_Bias": "NEUTRAL",
      "Drift": 0.2795191693126131,
      "Decay_Integral": 2.7816121832502447,
      "Inflection_Detected": false,
      "ZF_Score": 0.6851933278689443,
      "Previous_Direction": "NEUTRAL",
      "Previous_Drift": 0.24434198541226623,
      "Previous_ZF_Score": 0.6939795062397586,
      "Previous_Lambda_Liquidity": 1.1,
      "Previous_Liquidity_Status": "VOID",
      "Delta_Drift": 0.03517718390034688,
      "Delta_ZF_Score": -0.008786178370814302,
      "Delta_Lambda": 0.0,
      "Direction_Changed": false,
      "Liquidity_Status_Changed": false,
      "Memory_Status": "LAMINAR",
      "Risk_Mode": "LIQUIDITY_LOCK",
      "Trade_Allowed": false,
      "Action_Signal": "PERTAHANAN LIKUIDITAS",
      "Risk_Note": "Liquidity void atau spread terlalu lebar.",
      "Session_Phase": "ANOMALOUS",
      "User_Recommendation": "Jangan entry. Likuiditas/spread sedang tidak sehat.",
      "Historical_Status": "FOCUS",
      "Historical_Expectancy_R": -0.1695,
      "Historical_Win_Rate": 52.63,
      "Historical_Signals": 38,
      "Live_Expectancy_R": NaN,
      "Live_Signals": 0,
      "Market_Session": "THIN_SESSION",
      "Accuracy_Quality_Score": 5.46,
      "Accuracy_Gate": "NEUTRAL",
      "Accuracy_Gate_Reason": "Belum ada arah BUY/SELL matang.",
      "Ranking_Score": 19.92496663934472
    }
  ]
}